Workbook

Sheet ▶️ Инструкция
B2: ИНСТРУКЦИЯ ПО НАСТРОЙКЕ КАЛЬКУЛЯТОРА:
I5: 01.1 | Z5: 01.2 | AQ5: 01.3
E6: Жмем «Файл» → «Создать копию» → Вводим свое название → «Копировать» | T6: Вручную обновите данные во вкладке «📄Комиссии» в ячейках ниже 6-ой строки на актуальные из личного кабинета селлера по ссылке | AM6: Вручную обновите данные во вкладке «🔒Доп. информация» в ячейках I9:N10 и C12:F100 на актуальные из личного кабинета селлера по ссылке
D13: 02 | G13: 03 | N13: 04 | R13: 05 | U13: 06 | Y13: 07 | AD13: 08 | AI13: 09
C14: Названия ваших ИП | G14: Что для нас важно — маржинальность от пришедших денег на счет или маржинальность от цены продажи? | N14: Маржинальность в процентах, ниже которой нам не интересно работать | R14: Налог УСН «Доходы» + страховые | Y14: Выбираем, как считать налог — с продаж (это правильно) или с денег, пришедших на счет | AD14: Налог НДС | AI14: Выбираем процент эквайринга на WB. Может быть от 0,4% до 3,0%
C16: ИП Копытина К.В. | G16: Маржинальность прихода | N16: 0.15 | R16: 0.07 | Y16: Налог с продаж | AD16: 0 | AI16: 0.03
C17: ип Samga | G17: Маржинальность прихода | N17: 0.1 | R17: 0.04 | Y17: Налог с продаж | AD17: 0 | AI17: 0.02
C18: ип F | G18: Маржинальность прихода | N18: 0.05 | R18: 0.04 | Y18: Налог с продаж | AD18: 0 | AI18: 0.02
C19: ИП Кузнецов И.И.
M22: 12 | AA22: 13 | AQ22: 14
I23: В «🤖 Калькулятор» в столбце AP выбираем ваше ИП | T23: В «🤖 Калькулятор» в столбце AQ выбираем название маркетплейса, для которого делаем расчет | AK23: В «🤖 Калькулятор» в столбце AR выбираем FBO или FBS
R30: 15
R31: Чтобы верно посчитать Unit-экономику WB, нужно использовать коэффициенты самого дорого нашего склада.
R34: Вписываем, на какие склады WB мы готовы грузиться или уже грузимся
S36: Коледино, Электросталь, Краснодар (Тихорецкая), Казань, Санкт-Петербург (Уткина Заводь), СЦ Хабаровск, Тула
R41: 16
P42: Выбор опций для ваших ИП из Конструктора тарифов на WB
R45: Выбираем ИП из вашего списка в пункте 02:
R46: ИП Копытина К.В. | AG46: Суммарный %: | AK46: =IFERROR(__xludf.DUMMYFUNCTION("SUM(ArrayFormula(SUMIF('🔒 Доп. информация'!J:J,TRANSPOSE(SPLIT(Q48,"", "",FALSE,TRUE)),'🔒 Доп. информация'!P:P)))"),0.0) -> 0
Q47: Выбираем опции тарифа:
R53: Выбираем ИП из вашего списка в пункте 02:
R54: ИП Кузнецов И.И. | AG54: Суммарный %: | AK54: =IFERROR(__xludf.DUMMYFUNCTION("SUM(ArrayFormula(SUMIF('🔒 Доп. информация'!J:J,TRANSPOSE(SPLIT(Q56,"", "",FALSE,TRUE)),'🔒 Доп. информация'!P:P)))"),0.0) -> 0
Q55: Выбираем опции тарифа:
R61: Выбираем ИП из вашего списка в пункте 02:
R62: 2 Бренд | AG62: Суммарный %: | AK62: =IFERROR(__xludf.DUMMYFUNCTION("SUM(ArrayFormula(SUMIF('🔒 Доп. информация'!J:J,TRANSPOSE(SPLIT(Q64,"", "",FALSE,TRUE)),'🔒 Доп. информация'!P:P)))"),0.0) -> 0
Q63: Выбираем опции тарифа:
R69: Выбираем ИП из вашего списка в пункте 02:
AG70: Суммарный %: | AK70: =IFERROR(__xludf.DUMMYFUNCTION("SUM(ArrayFormula(SUMIF('🔒 Доп. информация'!J:J,TRANSPOSE(SPLIT(Q72,"", "",FALSE,TRUE)),'🔒 Доп. информация'!P:P)))"),0.0) -> 0
Q71: Выбираем опции тарифа:
R77: Выбираем ИП из вашего списка в пункте 02:
AG78: Суммарный %: | AK78: =IFERROR(__xludf.DUMMYFUNCTION("SUM(ArrayFormula(SUMIF('🔒 Доп. информация'!J:J,TRANSPOSE(SPLIT(Q80,"", "",FALSE,TRUE)),'🔒 Доп. информация'!P:P)))"),0.0) -> 0
Q79: Выбираем опции тарифа:
R85: Выбираем ИП из вашего списка в пункте 02:
AG86: Суммарный %: | AK86: =IFERROR(__xludf.DUMMYFUNCTION("SUM(ArrayFormula(SUMIF('🔒 Доп. информация'!J:J,TRANSPOSE(SPLIT(Q88,"", "",FALSE,TRUE)),'🔒 Доп. информация'!P:P)))"),0.0) -> 0
Q87: Выбираем опции тарифа:
A93: ОПИСАНИЕ ВКЛАДОК:
M95: 01 | AE95: 02
M96: В 5 строчке в «🤖Калькулятор» указаны объяснения значений каждого столбца калькулятора. Их можно скрыть или открыть, нажав на ➕слева от строки 4 | AE96: Во вкладке «📄Комиссии» — актуальные комиссии всех марктелпейсов. Эти данные периодически меняются, ссылки на актуальные данные указаны в таблице
M103: 03
M104: Во вкладке «🔒Доп. информация» указаны актуальные дополнительные данные от марктеплейсов. Эти данные периодически меняются, ссылки на актуальные данные указаны в таблице

Sheet 🤖 Калькулятор
G1: ✏️ ЗАПОЛНИТЬ | AT1: 💼 УСЛОВИЯ | AW1: 📈 ЭФФЕКТИВНОСТЬ ПРОДАЖИ | BJ1: 🧮 РАСЧЁТЫ
G2: ⬇️ | H2: ⬇️ | I2: ⬇️ | J2: ⬇️ | K2: 💰 | L2: ⬇️ | M2: ⬇️ | N2: 🔒 | O2: 💰 | Q2: 💰 | S2: ⬇️ | T2: ⬇️ | U2: ⬇️ | V2: 💰 | W2: 💰 | X2: 💰 | Y2: 💰 | Z2: ⬇️ | AA2: 🔒 | AB2: 💰 | AC2: 💰 | AD2: 💰 | AE2: ⬇️ | AF2: ⬇️ | AG2: ⬇️ | AH2: ⬇️ | AI2: 🔒 | AJ2: 🔒 | AK2: 💰 | AL2: 🔒 | AM2: 💰 | AN2: ⬇️ | AO2: ⬇️ | AP2: ⬇️ | AQ2: ⬇️ | AR2: ⬇️ | AS2: ⬇️ | AW2: 🔒 | AX2: 🔒 | AY2: 🔒 | AZ2: ⬇️ | BA2: 🔒 | BB2: 🔒 | BC2: 🔒 | BD2: 🔒 | BE2: 🔒 | BF2: 🔒 | BG2: 🔒 | BH2: 🔒
A3: ✅/❌ | B3: FBS/ FBO | C3: SKU | D3: Вкл. строку | E3: Менеджер | F3: Вывод | G3: Закупка, 1 шт | H3: Продажа, 1 шт | I3: Предпола- гаемый СПП + Кошелек WB | J3: Кешбек WB | K3: Сколько % комиссии снижает акция OZON | L3: Сколько штук в партии? | M3: Комиссия маркетплейса | S3: Куда и как отгружаем WB? | U3: ИЛ WB | V3: Индекс лока- лизации OZON | W3: Обработка товара в составе грузоместа OZON | Y3: Доля локаль- ных продаж Я.Маркет | Z3: Коэфф приемки WB | AA3: Приемка WB | AB3: Передал до рекомендованного слота отгрузки OZON | AC3: Приемка OZON | AD3: Приемка Я.Маркет | AE3: Дней на продажу партии FBW | AF3: Высота Ширина Длина в !СМ! | AI3: Объем/ объем. вес | AJ3: Доп. объем | AK3: Вес, кг Я.Маркет | AL3: Эквай- ринг WB | AM3: Перевод платежей Я.Маркет | AN3: Цена отгруз-ки еди- ницы на FBO | AO3: Цена отгруз-ки еди- ницы на FBS | AP3: Доп. затра- ты на еди- ницу | AQ3: % выкупа | AR3: % брака | AS3: % на марке- тинг | AT3: ИП | AU3: Площадка | AV3: Направ- ление | AW3: CPO Цена заказа | AX3: CPS Цена продажи | AY3: Процент рекламы в ЧП | AZ3: CPO (задаем) | BA3: ДРР из CPO | BB3: ЦЕНА- CPO | BC3: ЧП 1 шт. | BD3: ЧП партии | BE3: Выручка партии | BF3: Рентабель- ность инвестиций | BG3: Маржинальность продаж | BH3: Маржинальность прихода | BJ3: Xране- ние | BK3: Логис- тика | BL3: Доставка до места выдачи OZON | BM3: Между нас. пунктами/ Ср. миля Я.Маркет | BN3: Обра- ботка воз- врата | BO3: Цена воз- врата | BP3: МП → Клиент | BQ3: Комис- сия МП | BR3: Удер- жания МП Итог | BS3: НДС | BT3: Налог с НДС | BU3: Косты без закуп | BV3: Реально тратим | BW3: Приход на счет | BX3: При- быль
M4: WB | O4: OZON | Q4: Я.Маркет
A5: Прода- ем или нет | B5: FBS или FBO, выбран- ный в столбце AQ:AQ | C5: Название товара, для вашего удобства | D5: Вклю- чение отобра- жения строки. Можно выкл. то, чем не пользу- емся, чтобы не мешало | E5: Имя менеджера, для вашего удобства | F5: Вывод, продаем или не продаем товар, основываясь на типе и размере маржинальности во вкладке «▶️ Инструкция» | G5: Закупочная себесто- имость 1 единицы товара (1 штуки, если продаете по одному, сумма нескольких штук, если продаете комплектом) | H5: Цена, по которой планируется продажа 1 единицы товара (1 штуки, если продаете по одному, сумма нескольких штук, если продаете комплектом) | I5: Предполага- емый СПП от WB и Соинвест от OZON для правиль- ного расчета налогов | J5: Укажите кешбек, который вернете клиенту. Автоматом плюсуется 10% комиссии WB на этот кешбек | K5: % комиссии, на который OZON снижает свою комиссию, если мы будем участвовать в акции | L5: Пример- ное количест- во штук в постав- ляемой партии (может быть 1, для простоты расчетов) | M5: Название категории, подгружается автоматически после введения первых букв названия | N5: Комис- сия маркет- плейса подгру- жается автома- тически | O5: Название категории, подгружается автоматически после введения первых букв названия | P5: Комис- сия маркет- плейса подгру- жается автома- тически | Q5: Название категории, подгружается автоматически после введения первых букв названия | R5: Комис- сия маркет- плейса подгру- жается автома- тически | S5: Название склада для отгрузки. Если складов несколько, то задаем их в «▶️ Инструкция» в столбце Е:Е, а потом тут выбираем «Макс. из наших» | T5: Выбираем как отгружаем, коробами или монопал- летами | U5: Коэффициент территориального распределения за неделю из ЛК WB | V5: Индекс локали- зации из ЛК OZON | W5: Подробнее об этом – тут | Y5: Доля локальных продаж из ЛК Я.Маркет | Z5: Коэффициент приемки на WB тут | AA5: Цена приемки WB во время сдачи товара тут | AB5: При передаче до рекомендованного слота отгрузки – скидка 4% по FBS | AC5: Цена приемки OZON, формируется исходя из выбора, сделанного в «⚙️Настройки» | AD5: Цена приемки Я.Маркет, формируется исходя из выбора, сделанного в «⚙️Настройки» | AE5: Пример- ное время распро- дажи партии из колич- ества, указан- ного в К:К, поставля- емой на WB, для расчета цены хранения единицы | AF5: Высота, ширина и длина в санти- метрах 1 единицы товара (1 штуки, если продаете по одному, сумма несколь- ких штук, если продаете комплектом) | AI5: Объем или объем- ный вес выбира- ется и рассчи- тывается автома- тически | AJ5: Допол- нитель- ный объем сверх указан- ной на МП нормы выбира- ется и рассчи- тывается автома- тически | AK5: Вес товара нужно ввести вручную для расчета цены логистики | AL5: Стоимость эквайринга рассчиты- вается автомати- чески, исходя из выбора, сделанного в «▶️ Инструкция» | AM5: Стоимость Перевода платежей от Я.Маркет вам рассчиты- вается автомати- чески, исходя из выбора, сделанного в «⚙️Настройки» | AN5: Цена отгрузки 1 единицы или комплекта товара для FBO и/или FBS. Обычно эту цену определяет фулфилмент, она колеблется от 20 до 150 рублей за одну отгрузку. | AP5: Все дополни- тельные затраты для продажи — на логистику, дизайнера, фотографа и прочее на каждую единицу. Можно оставить ноль. | AQ5: Предпо- лагаемый или факти- ческий процент выкупа | AR5: Предпо- лагаемый или факти- ческий процент брака | AS5: Предпо- лагаемый или факти- ческий процент, заложен- ный на весь внутрен- ний и внешний маркетинг | AT5: Выбор вашего ИП, на основе которого будет считаться процент налога в столбце BH:BH | AU5: Выбор площадки, для которой делаем расчет | AV5: Выбор направле- ния, для которого делаем расчет | AW5: Цена заказа | AX5: Цена продажи | AY5: Процент рекалмы в ЧП | AZ5: Задайте тут желаемый CPO, чтобы справа получить нужный вам для этого ДРР | BA5: Получившийся ДРР из заданного левее CPO | BB5: Цена продажи минус CPO | BC5: Чистая прибыль с одной продажи, учитывая все те траты (косты), которые вы внесли | BD5: Чистая прибыль всей партии, указанной в K:K | BE5: Выручка до всех трат и комиссий от продажи партии, указанной в К:К | BF5: Рентабельность инвестиций (ROI) или отношение чистой прибыли к реально затраченным на продажу средствам | BG5: Отношение чистой прибыли от продажи к цене до СПП и соинвеста, по которой товар был продан | BH5: Отношение чистой прибыли от продажи к деньгам, пришедшим на счет после всех трат и комиссий маркет- плейсов | BJ5: Обнуляем хранение, потому что на ВБ оно стало беслптаным до 60 дней, на Озон и Я.маркет до 120 дней. | BK5: Расчет цены логис- тики | BL5: Расчет цены доставки до места выдачи на OZON | BM5: Расчет цены средней мили на Я.Маркет | BN5: Цена обра- ботки возврата | BO5: Цена воз- врата, с учетом всех дополни- тельных затрат на возврат | BP5: Цена хранения и логис- тики до получения товара клиентом | BQ5: Комис- сия маркет- плейса | BR5: Итоговая сумма всех удержа- ний маркет- плейса | BS5: Рассчет вашего НДС | BT5: Налог, рассчиты- ваемый на основании данных в «▶️ Инструкция» | BU5: Все траты (косты), без учета цены закупки товара | BV5: Расчет реальных трат до продажи и получе- ния выплат от маркет- плейса | BW5: Расчет денег, теорети- чески прихо- дящих на счет | BX5: Чистая прибыль с одной продажи, учитывая все те траты (косты), которые вы внесли
A6: =if(D6=true,if(F6=data!A$1,data!A$10,data!A$11),) | B6: =AV6 -> FBO | C6: 9785855906 | D6: FALSE | E6: Кристина | F6: {=IF(D6=TRUE,IF(IF(BG$3=VLOOKUP(AT6,{'▶️ Инструкция'!C:C,'▶️ Инструкция'!G:G},2,FALSE),BG6,BH6)>VLOOKUP(AT6,{'▶️ Инструкция'!C:C,'▶️ Инструкция'!N:N},2,FALSE),data!A$1,data!A$2),)} | G6: 560 | H6: 2905 | I6: 0.26 | J6: 0 | K6: =IF($D6,"🔒",) | L6: 0 | M6: Свитеры | N6: =IFERROR(__xludf.DUMMYFUNCTION("ArrayFormula(let(category,VLOOKUP($M6, {'📄 Комиссии'!$C:$C , '📄 Комиссии'!$B:$B}, 2, 0), data,MATCH('🔒 Доп. информация'!$J$15:$J203,TRANSPOSE(SPLIT(INDEX('▶️ Инструкция'!$Q:$Q,MATCH($AT6,'▶️ Инструкция'!$R:$R,0)+2),"", "",FALSE)),0), options,COUNTA( if"&"na( FILTER('🔒 Доп. информация'!$J$15:$J203,('🔒 Доп. информация'!$N$15:$N203=FALSE)*data*('🔒 Доп. информация'!$O$15:$O203=""Опция"")))), commission,VLOOKUP($M6,'📄 Комиссии'!$C:$E,IF($AV6=data!A$8,2,3),0), IF(NOT(ISBLANK($M6)),commission/100+ IFERROR(VL"&"OOKUP($AT6,{'▶️ Инструкция'!$R:$R,'▶️ Инструкция'!$AK:$AK},2,0)+ IF((( category = ""Одежда"")+( category = ""Обувь"" ))*((options+SUM( ifna( FILTER('🔒 Доп. информация'!$M$15:$M203,('🔒 Доп. информация'!$N$15:$N203=FALSE)*data*('🔒 Доп. информация'!$O$15:"&"$O203=""Пакет"")))))>=5), -5% + 2%, IF((options>=1)* (COUNTA( ifna( FILTER('🔒 Доп. информация'!$J$15:$J203,('🔒 Доп. информация'!$N$15:$N203=FALSE)*data*('🔒 Доп. информация'!$O$15:$O203=""Пакет""))))>=1)* (commission>=14.5)* (category<> ""Одежда"")*( c"&"ategory <> ""Обувь"" ),-3% + 2%,0))))))"),0.345) -> 0.345 | O6: =IF($D6,"🔒",) | Q6: =IF($D6,"🔒",) | S6: Макс. из наших | T6: Короб | U6: 1.17 | V6: =IF($D6,"🔒",) | W6: =IF($D6,"🔒",) | X6: =IF($D6,"🔒",) | Y6: =IF($D6,"🔒",) | Z6: 0 | AA6: 0 | AB6: =IF($D6,"🔒",) | AC6: =IF($D6,"🔒",) | AD6: =IF($D6,"🔒",) | AE6: 30 | AF6: 11 | AG6: 31 | AH6: 31 | AI6: =(AF6*AG6*AH6)/1000 -> 10.571 | AJ6: =if(AI6>1,(AI6-1),0) -> 9.571 | AK6: =IF($D6,"🔒",) | AL6: {=H6*(1-I6)*VLOOKUP(AT6,{'▶️ Инструкция'!C:C,'▶️ Инструкция'!AI:AI},2,false)} -> 64.491 | AM6: =IF($D6,"🔒",) | AN6: 0 | AO6: 0 | AP6: 0 | AQ6: 0.47 | AR6: 0 | AS6: 0.01 | AT6: ИП Копытина К.В. | AU6: WB | AV6: FBO | AW6: =AS6*H6 -> 29.05 | AX6: =(1/(AQ6))*H6*AS6 -> 61.808511 | AY6: =AX6/BC6 -> -0.18472524 | AZ6: 100 | BA6: =AZ6/H6 -> 0.034423408 | BB6: =H6-AW6 -> 2875.95 | BC6: =BX6 -> -334.597 | BD6: =BC6*L6 -> 0 | BE6: =H6*(1-I6)*L6 -> 0 | BF6: =IFERROR(BC6/BV6,) -> -0.47094566 | BG6: =IFERROR(BC6/H6,) -> -0.11517969 | BH6: =IFERROR(if(BW6>0,BC6/BW6,-BC6/BW6),) -> -0.890165 | BJ6: =IFERROR(__xludf.DUMMYFUNCTION("IF(AU6=data!A$5, IF(AV6=data!A$8, IF(T6=data!A$3, VLOOKUP(S6,filter('🔒 Доп. информация'!D:H,'🔒 Доп. информация'!C:C=T6),4,FALSE)+VLOOKUP(S6,filter('🔒 Доп. информация'!D:H,'🔒 Доп. информация'!C:C=T6),5,FALSE)*AJ6, IF(AND(MAX(AF6:AH6)<80,SUM(AF6:AH6)<=1"&"60,AI6<20,XLOOKUP(M6,'📄 Комиссии'!C:C,'📄 Комиссии'!B:B)<>""Продукты""), VLOOKUP(S6,filter('🔒 Доп. информация'!D:H,'🔒 Доп. информация'!C:C=data!$A$3),4,FALSE)+VLOOKUP(S6,filter('🔒 Доп. информация'!D:H,'🔒 Доп. информация'!C:C=data!$A$3),5,FALSE)*AJ6, "&"VLOOKUP(S6,filter('🔒 Доп. информация'!D:H,'🔒 Доп. информация'!C:C=T6),4,FALSE)*ROUNDUP(AF6*AG6*AH6*L6/(120*80*175))/L6) ) *(AE6/2) ,) ,)*0"),0.0) -> 0 | BK6: =IFERROR(__xludf.DUMMYFUNCTION("IF(AU6=data!A$5, IF(AI6<=1,IF(AI6<=0.8,IF(AI6<=0.6,IF(AI6<=0.4,IF(AI6<=0.2,23,26),29),30),32)*VLOOKUP(S6,filter('🔒 Доп. информация'!D:E,'🔒 Доп. информация'!C:C=T6),2,FALSE)/'🔒 Доп. информация'!$K$9, IF(AV6=data!A$8,U6,1)*VLOOKUP(S6,filter('🔒 Доп. инфо"&"рмация'!D:E,'🔒 Доп. информация'!C:C=T6),2,FALSE)+ IF(AV6=data!A$8,U6,1)*VLOOKUP(S6,filter('🔒 Доп. информация'!D:F,'🔒 Доп. информация'!C:C=T6),3,FALSE)*AJ6) ,0)"),631.7789399999999) -> 631.77894 | BL6: =IF($D6,"🔒",) | BM6: =IF($D6,"🔒",) | BN6: =VLOOKUP(T6,'🔒 Доп. информация'!J:P,7,false) -> 50 | BO6: =IF(AV6=data!A$9, (AA6+AO6+AP6+BJ6+BK6+BN6)+H6*AS6, (BJ6+BK6+BN6)+H6*AS6 ) -> 710.82894 | BP6: =AA6+BJ6+BK6 -> 631.77894 | BQ6: =H6*N6 -> 1002.225 | BR6: =BP6+BQ6+AS6*H6+((1-AQ6)/AQ6)*BO6+AL6+H6*J6*1.1 -> 2529.118 | BS6: {=IF(VLOOKUP(AT6,{'▶️ Инструкция'!C:C,'▶️ Инструкция'!Y:Y},2,FALSE)=data!A$15, H6*(1-I6), (H6-BR6)) *VLOOKUP(AT6,{'▶️ Инструкция'!C:C,'▶️ Инструкция'!AD:AD},2,FALSE)/(1+VLOOKUP(AT6,{'▶️ Инструкция'!C:C,'▶️ Инструкция'!AD:AD},2,FALSE))} -> 0 | BT6: {=IF(VLOOKUP(AT6,{'▶️ Инструкция'!C:C,'▶️ Инструкция'!Y:Y},2,FALSE)=data!A$15, H6*(1-I6)-BS6, (H6-BR6-BS6)) * VLOOKUP(AT6,{'▶️ Инструкция'!C:C,'▶️ Инструкция'!R:R},2,FALSE) +BS6} -> 150.479 | BU6: =(G6*AR6)+if(AV6=data!A$9,AO6,AN6)+AP6+BR6+BT6 -> 2679.597 | BV6: =(G6*AR6)+if(AV6=data!A$9,AO6,AN6)+AP6+BT6+G6 -> 710.479 | BW6: =H6-BR6 -> 375.882 | BX6: =BW6-BV6 -> -334.597
A7: =if(D7=true,if(F7=data!A$1,data!A$10,data!A$11),) -> ✅ | B7: =AV7 -> FBO | C7: Название товара | D7: TRUE | E7: Кристина | F7: {=IF(D7=TRUE,IF(IF(BG$3=VLOOKUP(AT7,{'▶️ Инструкция'!C:C,'▶️ Инструкция'!G:G},2,FALSE),BG7,BH7)>VLOOKUP(AT7,{'▶️ Инструкция'!C:C,'▶️ Инструкция'!N:N},2,FALSE),data!A$1,data!A$2),)} -> Срочно закупаем и продаем 💸 | G7: 560 | H7: 2905 | I7: 0.26 | J7: 0 | K7: =IF($D7,"🔒",) -> 🔒 | L7: 0 | M7: Свитеры | N7: =IFERROR(__xludf.DUMMYFUNCTION("ArrayFormula(let(category,VLOOKUP($M7, {'📄 Комиссии'!$C:$C , '📄 Комиссии'!$B:$B}, 2, 0), data,MATCH('🔒 Доп. информация'!$J$15:$J203,TRANSPOSE(SPLIT(INDEX('▶️ Инструкция'!$Q:$Q,MATCH($AT7,'▶️ Инструкция'!$R:$R,0)+2),"", "",FALSE)),0), options,COUNTA( if"&"na( FILTER('🔒 Доп. информация'!$J$15:$J203,('🔒 Доп. информация'!$N$15:$N203=FALSE)*data*('🔒 Доп. информация'!$O$15:$O203=""Опция"")))), commission,VLOOKUP($M7,'📄 Комиссии'!$C:$E,IF($AV7=data!A$8,2,3),0), IF(NOT(ISBLANK($M7)),commission/100+ IFERROR(VL"&"OOKUP($AT7,{'▶️ Инструкция'!$R:$R,'▶️ Инструкция'!$AK:$AK},2,0)+ IF((( category = ""Одежда"")+( category = ""Обувь"" ))*((options+SUM( ifna( FILTER('🔒 Доп. информация'!$M$15:$M203,('🔒 Доп. информация'!$N$15:$N203=FALSE)*data*('🔒 Доп. информация'!$O$15:"&"$O203=""Пакет"")))))>=5), -5% + 2%, IF((options>=1)* (COUNTA( ifna( FILTER('🔒 Доп. информация'!$J$15:$J203,('🔒 Доп. информация'!$N$15:$N203=FALSE)*data*('🔒 Доп. информация'!$O$15:$O203=""Пакет""))))>=1)* (commission>=14.5)* (category<> ""Одежда"")*( c"&"ategory <> ""Обувь"" ),-3% + 2%,0))))))"),0.345) -> 0.345 | O7: =IF($D7,"🔒",) -> 🔒 | Q7: =IF($D7,"🔒",) -> 🔒 | S7: FBS: Маркетплейс: Уральский федеральный округ СГТ | T7: Короб | U7: 1.17 | V7: =IF($D7,"🔒",) -> 🔒 | W7: =IF($D7,"🔒",) -> 🔒 | X7: =IF($D7,"🔒",) -> 🔒 | Y7: =IF($D7,"🔒",) -> 🔒 | Z7: 0 | AA7: =1.7*(1+AJ7)*Z7 -> 0 | AB7: =IF($D7,"🔒",) -> 🔒 | AC7: =IF($D7,"🔒",) -> 🔒 | AD7: =IF($D7,"🔒",) -> 🔒 | AE7: 30 | AF7: 11 | AG7: 31 | AH7: 31 | AI7: =(AF7*AG7*AH7)/1000 -> 10.571 | AJ7: =if(AI7>1,(AI7-1),0) -> 9.571 | AK7: =IF($D7,"🔒",) -> 🔒 | AL7: {=H7*(1-I7)*VLOOKUP(AT7,{'▶️ Инструкция'!C:C,'▶️ Инструкция'!AI:AI},2,false)} -> 64.491 | AM7: =IF($D7,"🔒",) -> 🔒 | AN7: 0 | AO7: 0 | AP7: 150 | AQ7: 0.47 | AR7: 0.003 | AS7: 0 | AT7: ИП Копытина К.В. | AU7: WB | AV7: FBO | AW7: =AS7*H7 -> 0 | AX7: =(1/(AQ7))*H7*AS7 -> 0 | AY7: =AX7/BC7 -> 0 | AZ7: 100 | BA7: =AZ7/H7 -> 0.034423408 | BB7: =H7-AW7 -> 2905 | BC7: =BX7 -> 471.67185 | BD7: =BC7*L7 -> 0 | BE7: =H7*(1-I7)*L7 -> 0 | BF7: =IFERROR(BC7/BV7,) -> 0.54708221 | BG7: =IFERROR(BC7/H7,) -> 0.16236553 | BH7: =IFERROR(if(BW7>0,BC7/BW7,-BC7/BW7),) -> 0.35362194 | BJ7: =IFERROR(__xludf.DUMMYFUNCTION("IF(AU7=data!A$5, IF(AV7=data!A$8, IF(T7=data!A$3, VLOOKUP(S7,filter('🔒 Доп. информация'!D:H,'🔒 Доп. информация'!C:C=T7),4,FALSE)+VLOOKUP(S7,filter('🔒 Доп. информация'!D:H,'🔒 Доп. информация'!C:C=T7),5,FALSE)*AJ7, IF(AND(MAX(AF7:AH7)<80,SUM(AF7:AH7)<=1"&"60,AI7<20,XLOOKUP(M7,'📄 Комиссии'!C:C,'📄 Комиссии'!B:B)<>""Продукты""), VLOOKUP(S7,filter('🔒 Доп. информация'!D:H,'🔒 Доп. информация'!C:C=data!$A$3),4,FALSE)+VLOOKUP(S7,filter('🔒 Доп. информация'!D:H,'🔒 Доп. информация'!C:C=data!$A$3),5,FALSE)*AJ7, "&"VLOOKUP(S7,filter('🔒 Доп. информация'!D:H,'🔒 Доп. информация'!C:C=T7),4,FALSE)*ROUNDUP(AF7*AG7*AH7*L7/(120*80*175))/L7) ) *(AE7/2) ,) ,)*0"),0.0) -> 0 | BK7: =IFERROR(__xludf.DUMMYFUNCTION("IF(AU7=data!A$5, IF(AI7<=1,IF(AI7<=0.8,IF(AI7<=0.6,IF(AI7<=0.4,IF(AI7<=0.2,23,26),29),30),32)*VLOOKUP(S7,filter('🔒 Доп. информация'!D:E,'🔒 Доп. информация'!C:C=T7),2,FALSE)/'🔒 Доп. информация'!$K$9, IF(AV7=data!A$8,U7,1)*VLOOKUP(S7,filter('🔒 Доп. инфо"&"рмация'!D:E,'🔒 Доп. информация'!C:C=T7),2,FALSE)+ IF(AV7=data!A$8,U7,1)*VLOOKUP(S7,filter('🔒 Доп. информация'!D:F,'🔒 Доп. информация'!C:C=T7),3,FALSE)*AJ7) ,0)"),210.59297999999998) -> 210.59298 | BL7: =IF($D7,"🔒",) -> 🔒 | BM7: =IF($D7,"🔒",) -> 🔒 | BN7: =VLOOKUP(T7,'🔒 Доп. информация'!J:P,7,false) -> 50 | BO7: =IF(AV7=data!A$9, (AA7+AO7+AP7+BJ7+BK7+BN7)+H7*AS7, (BJ7+BK7+BN7)+H7*AS7 ) -> 260.59298 | BP7: =AA7+BJ7+BK7 -> 210.59298 | BQ7: =H7*N7 -> 1002.225 | BR7: =BP7+BQ7+AS7*H7+((1-AQ7)/AQ7)*BO7+AL7+H7*J7 -> 1571.1691 | BS7: {=IF(VLOOKUP(AT7,{'▶️ Инструкция'!C:C,'▶️ Инструкция'!Y:Y},2,FALSE)=data!A$15, H7*(1-I7), (H7-BR7)) *VLOOKUP(AT7,{'▶️ Инструкция'!C:C,'▶️ Инструкция'!AD:AD},2,FALSE)/(1+VLOOKUP(AT7,{'▶️ Инструкция'!C:C,'▶️ Инструкция'!AD:AD},2,FALSE))} -> 0 | BT7: {=IF(VLOOKUP(AT7,{'▶️ Инструкция'!C:C,'▶️ Инструкция'!Y:Y},2,FALSE)=data!A$15, H7*(1-I7)-BS7, (H7-BR7-BS7)) * VLOOKUP(AT7,{'▶️ Инструкция'!C:C,'▶️ Инструкция'!R:R},2,FALSE) +BS7} -> 150.479 | BU7: =(G7*AR7)+if(AV7=data!A$9,AO7,AN7)+AP7+BR7+BT7 -> 1873.3281 | BV7: =(G7*AR7)+if(AV7=data!A$9,AO7,AN7)+AP7+BT7+G7 -> 862.159 | BW7: =H7-BR7 -> 1333.8309 | BX7: =BW7-BV7 -> 471.67185
A8: =if(D8=true,if(F8=data!A$1,data!A$10,data!A$11),) -> ✅ | B8: =AV8 -> FBO | C8: Название товара | D8: TRUE | E8: Кристина | F8: {=IF(D8=TRUE,IF(IF(BG$3=VLOOKUP(AT8,{'▶️ Инструкция'!C:C,'▶️ Инструкция'!G:G},2,FALSE),BG8,BH8)>VLOOKUP(AT8,{'▶️ Инструкция'!C:C,'▶️ Инструкция'!N:N},2,FALSE),data!A$1,data!A$2),)} -> Срочно закупаем и продаем 💸 | G8: 0 | H8: 1000 | I8: 0 | J8: 0 | K8: =IF($D8,"🔒",) -> 🔒 | L8: 0 | M8: Лопатки игрушечные | N8: =IFERROR(__xludf.DUMMYFUNCTION("ArrayFormula(let(category,VLOOKUP($M8, {'📄 Комиссии'!$C:$C , '📄 Комиссии'!$B:$B}, 2, 0), data,MATCH('🔒 Доп. информация'!$J$15:$J203,TRANSPOSE(SPLIT(INDEX('▶️ Инструкция'!$Q:$Q,MATCH($AT8,'▶️ Инструкция'!$R:$R,0)+2),"", "",FALSE)),0), options,COUNTA( if"&"na( FILTER('🔒 Доп. информация'!$J$15:$J203,('🔒 Доп. информация'!$N$15:$N203=FALSE)*data*('🔒 Доп. информация'!$O$15:$O203=""Опция"")))), commission,VLOOKUP($M8,'📄 Комиссии'!$C:$E,IF($AV8=data!A$8,2,3),0), IF(NOT(ISBLANK($M8)),commission/100+ IFERROR(VL"&"OOKUP($AT8,{'▶️ Инструкция'!$R:$R,'▶️ Инструкция'!$AK:$AK},2,0)+ IF((( category = ""Одежда"")+( category = ""Обувь"" ))*((options+SUM( ifna( FILTER('🔒 Доп. информация'!$M$15:$M203,('🔒 Доп. информация'!$N$15:$N203=FALSE)*data*('🔒 Доп. информация'!$O$15:"&"$O203=""Пакет"")))))>=5), -5% + 2%, IF((options>=1)* (COUNTA( ifna( FILTER('🔒 Доп. информация'!$J$15:$J203,('🔒 Доп. информация'!$N$15:$N203=FALSE)*data*('🔒 Доп. информация'!$O$15:$O203=""Пакет""))))>=1)* (commission>=14.5)* (category<> ""Одежда"")*( c"&"ategory <> ""Обувь"" ),-3% + 2%,0))))))"),0.285) -> 0.285 | O8: =IF($D8,"🔒",) -> 🔒 | Q8: =IF($D8,"🔒",) -> 🔒 | S8: Макс. из наших | T8: Короб | U8: 1 | V8: =IF($D8,"🔒",) -> 🔒 | W8: =IF($D8,"🔒",) -> 🔒 | X8: =IF($D8,"🔒",) -> 🔒 | Y8: =IF($D8,"🔒",) -> 🔒 | Z8: 0 | AA8: =1.7*(1+AJ8)*Z8 -> 0 | AB8: =IF($D8,"🔒",) -> 🔒 | AC8: =IF($D8,"🔒",) -> 🔒 | AD8: =IF($D8,"🔒",) -> 🔒 | AE8: 60 | AF8: 0 | AG8: 0 | AH8: 0 | AI8: =(AF8*AG8*AH8)/1000 -> 0 | AJ8: =if(AI8>1,(AI8-1),0) -> 0 | AK8: =IF($D8,"🔒",) -> 🔒 | AL8: {=H8*(1-I8)*VLOOKUP(AT8,{'▶️ Инструкция'!C:C,'▶️ Инструкция'!AI:AI},2,false)} -> 30 | AM8: =IF($D8,"🔒",) -> 🔒 | AN8: 0 | AO8: 0 | AP8: 0 | AQ8: 1 | AR8: 0.03 | AS8: 0 | AT8: ИП Копытина К.В. | AU8: WB | AV8: FBO | AW8: =AS8*H8 -> 0 | AX8: =(1/(AQ8))*H8*AS8 -> 0 | AY8: =AX8/BC8 -> 0 | AZ8: 250 | BA8: =AZ8/H8 -> 0.25 | BB8: =H8-AW8 -> 1000 | BC8: =BX8 -> 546 | BD8: =BC8*L8 -> 0 | BE8: =H8*(1-I8)*L8 -> 0 | BF8: =IFERROR(BC8/BV8,) -> 7.8 | BG8: =IFERROR(BC8/H8,) -> 0.546 | BH8: =IFERROR(if(BW8>0,BC8/BW8,-BC8/BW8),) -> 0.88636364 | BJ8: =IFERROR(__xludf.DUMMYFUNCTION("IF(AU8=data!A$5, IF(AV8=data!A$8, IF(T8=data!A$3, VLOOKUP(S8,filter('🔒 Доп. информация'!D:H,'🔒 Доп. информация'!C:C=T8),4,FALSE)+VLOOKUP(S8,filter('🔒 Доп. информация'!D:H,'🔒 Доп. информация'!C:C=T8),5,FALSE)*AJ8, IF(AND(MAX(AF8:AH8)<80,SUM(AF8:AH8)<=1"&"60,AI8<20,XLOOKUP(M8,'📄 Комиссии'!C:C,'📄 Комиссии'!B:B)<>""Продукты""), VLOOKUP(S8,filter('🔒 Доп. информация'!D:H,'🔒 Доп. информация'!C:C=data!$A$3),4,FALSE)+VLOOKUP(S8,filter('🔒 Доп. информация'!D:H,'🔒 Доп. информация'!C:C=data!$A$3),5,FALSE)*AJ8, "&"VLOOKUP(S8,filter('🔒 Доп. информация'!D:H,'🔒 Доп. информация'!C:C=T8),4,FALSE)*ROUNDUP(AF8*AG8*AH8*L8/(120*80*175))/L8) ) *(AE8/2) ,) ,)*0"),0.0) -> 0 | BK8: =IFERROR(__xludf.DUMMYFUNCTION("IF(AU8=data!A$5, IF(AI8<=1,IF(AI8<=0.8,IF(AI8<=0.6,IF(AI8<=0.4,IF(AI8<=0.2,23,26),29),30),32)*VLOOKUP(S8,filter('🔒 Доп. информация'!D:E,'🔒 Доп. информация'!C:C=T8),2,FALSE)/'🔒 Доп. информация'!$K$9, IF(AV8=data!A$8,U8,1)*VLOOKUP(S8,filter('🔒 Доп. инфо"&"рмация'!D:E,'🔒 Доп. информация'!C:C=T8),2,FALSE)+ IF(AV8=data!A$8,U8,1)*VLOOKUP(S8,filter('🔒 Доп. информация'!D:F,'🔒 Доп. информация'!C:C=T8),3,FALSE)*AJ8) ,0)"),69.0) -> 69 | BL8: =IF($D8,"🔒",) -> 🔒 | BM8: =IF($D8,"🔒",) -> 🔒 | BN8: =VLOOKUP(T8,'🔒 Доп. информация'!J:P,7,false) -> 50 | BO8: =IF(AV8=data!A$9, (AA8+AO8+AP8+BJ8+BK8+BN8)+H8*AS8, (BJ8+BK8+BN8)+H8*AS8 ) -> 119 | BP8: =AA8+BJ8+BK8 -> 69 | BQ8: =H8*N8 -> 285 | BR8: =BP8+BQ8+AS8*H8+((1-AQ8)/AQ8)*BO8+AL8+H8*J8*1.1 -> 384 | BS8: {=IF(VLOOKUP(AT8,{'▶️ Инструкция'!C:C,'▶️ Инструкция'!Y:Y},2,FALSE)=data!A$15, H8*(1-I8), (H8-BR8)) *VLOOKUP(AT8,{'▶️ Инструкция'!C:C,'▶️ Инструкция'!AD:AD},2,FALSE)/(1+VLOOKUP(AT8,{'▶️ Инструкция'!C:C,'▶️ Инструкция'!AD:AD},2,FALSE))} -> 0 | BT8: {=IF(VLOOKUP(AT8,{'▶️ Инструкция'!C:C,'▶️ Инструкция'!Y:Y},2,FALSE)=data!A$15, H8*(1-I8)-BS8, (H8-BR8-BS8)) * VLOOKUP(AT8,{'▶️ Инструкция'!C:C,'▶️ Инструкция'!R:R},2,FALSE) +BS8} -> 70 | BU8: =(G8*AR8)+if(AV8=data!A$9,AO8,AN8)+AP8+BR8+BT8 -> 454 | BV8: =(G8*AR8)+if(AV8=data!A$9,AO8,AN8)+AP8+BT8+G8 -> 70 | BW8: =H8-BR8 -> 616 | BX8: =BW8-BV8 -> 546
A9: =if(D9=true,if(F9=data!A$1,data!A$10,data!A$11),) -> ✅ | B9: =AV9 -> FBS | C9: Название товара | D9: TRUE | E9: Кристина | F9: {=IF(D9=TRUE,IF(IF(BG$3=VLOOKUP(AT9,{'▶️ Инструкция'!C:C,'▶️ Инструкция'!G:G},2,FALSE),BG9,BH9)>VLOOKUP(AT9,{'▶️ Инструкция'!C:C,'▶️ Инструкция'!N:N},2,FALSE),data!A$1,data!A$2),)} -> Срочно закупаем и продаем 💸 | G9: 0 | H9: 1000 | I9: 0 | J9: 0 | K9: =IF($D9,"🔒",) -> 🔒 | L9: 0 | M9: Лопатки игрушечные | N9: =IFERROR(__xludf.DUMMYFUNCTION("ArrayFormula(let(category,VLOOKUP($M9, {'📄 Комиссии'!$C:$C , '📄 Комиссии'!$B:$B}, 2, 0), data,MATCH('🔒 Доп. информация'!$J$15:$J203,TRANSPOSE(SPLIT(INDEX('▶️ Инструкция'!$Q:$Q,MATCH($AT9,'▶️ Инструкция'!$R:$R,0)+2),"", "",FALSE)),0), options,COUNTA( if"&"na( FILTER('🔒 Доп. информация'!$J$15:$J203,('🔒 Доп. информация'!$N$15:$N203=FALSE)*data*('🔒 Доп. информация'!$O$15:$O203=""Опция"")))), commission,VLOOKUP($M9,'📄 Комиссии'!$C:$E,IF($AV9=data!A$8,2,3),0), IF(NOT(ISBLANK($M9)),commission/100+ IFERROR(VL"&"OOKUP($AT9,{'▶️ Инструкция'!$R:$R,'▶️ Инструкция'!$AK:$AK},2,0)+ IF((( category = ""Одежда"")+( category = ""Обувь"" ))*((options+SUM( ifna( FILTER('🔒 Доп. информация'!$M$15:$M203,('🔒 Доп. информация'!$N$15:$N203=FALSE)*data*('🔒 Доп. информация'!$O$15:"&"$O203=""Пакет"")))))>=5), -5% + 2%, IF((options>=1)* (COUNTA( ifna( FILTER('🔒 Доп. информация'!$J$15:$J203,('🔒 Доп. информация'!$N$15:$N203=FALSE)*data*('🔒 Доп. информация'!$O$15:$O203=""Пакет""))))>=1)* (commission>=14.5)* (category<> ""Одежда"")*( c"&"ategory <> ""Обувь"" ),-3% + 2%,0))))))"),0.32) -> 0.32 | O9: =IF($D9,"🔒",) -> 🔒 | Q9: =IF($D9,"🔒",) -> 🔒 | S9: СЦ Оренбург Центральная | T9: Короб | U9: 1 | V9: =IF($D9,"🔒",) -> 🔒 | W9: =IF($D9,"🔒",) -> 🔒 | X9: =IF($D9,"🔒",) -> 🔒 | Y9: =IF($D9,"🔒",) -> 🔒 | Z9: 0 | AA9: =1.7*(1+AJ9)*Z9 -> 0 | AB9: =IF($D9,"🔒",) -> 🔒 | AC9: =IF($D9,"🔒",) -> 🔒 | AD9: =IF($D9,"🔒",) -> 🔒 | AE9: 30 | AF9: 0 | AG9: 0 | AH9: 0 | AI9: =(AF9*AG9*AH9)/1000 -> 0 | AJ9: =if(AI9>1,(AI9-1),0) -> 0 | AK9: =IF($D9,"🔒",) -> 🔒 | AL9: {=H9*(1-I9)*VLOOKUP(AT9,{'▶️ Инструкция'!C:C,'▶️ Инструкция'!AI:AI},2,false)} -> 30 | AM9: =IF($D9,"🔒",) -> 🔒 | AN9: 0 | AO9: 0 | AP9: 0 | AQ9: 1 | AR9: 0 | AS9: 0 | AT9: ИП Копытина К.В. | AU9: WB | AV9: FBS | AW9: =AS9*H9 -> 0 | AX9: =(1/(AQ9))*H9*AS9 -> 0 | AY9: =AX9/BC9 -> 0 | AZ9: 250 | BA9: =AZ9/H9 -> 0.25 | BB9: =H9-AW9 -> 1000 | BC9: =BX9 -> 535.15 | BD9: =BC9*L9 -> 0 | BE9: =H9*(1-I9)*L9 -> 0 | BF9: =IFERROR(BC9/BV9,) -> 7.645 | BG9: =IFERROR(BC9/H9,) -> 0.53515 | BH9: =IFERROR(if(BW9>0,BC9/BW9,-BC9/BW9),) -> 0.8843262 | BJ9: =IFERROR(__xludf.DUMMYFUNCTION("IF(AU9=data!A$5, IF(AV9=data!A$8, IF(T9=data!A$3, VLOOKUP(S9,filter('🔒 Доп. информация'!D:H,'🔒 Доп. информация'!C:C=T9),4,FALSE)+VLOOKUP(S9,filter('🔒 Доп. информация'!D:H,'🔒 Доп. информация'!C:C=T9),5,FALSE)*AJ9, IF(AND(MAX(AF9:AH9)<80,SUM(AF9:AH9)<=1"&"60,AI9<20,XLOOKUP(M9,'📄 Комиссии'!C:C,'📄 Комиссии'!B:B)<>""Продукты""), VLOOKUP(S9,filter('🔒 Доп. информация'!D:H,'🔒 Доп. информация'!C:C=data!$A$3),4,FALSE)+VLOOKUP(S9,filter('🔒 Доп. информация'!D:H,'🔒 Доп. информация'!C:C=data!$A$3),5,FALSE)*AJ9, "&"VLOOKUP(S9,filter('🔒 Доп. информация'!D:H,'🔒 Доп. информация'!C:C=T9),4,FALSE)*ROUNDUP(AF9*AG9*AH9*L9/(120*80*175))/L9) ) *(AE9/2) ,) ,)*0"),0.0) -> 0 | BK9: =IFERROR(__xludf.DUMMYFUNCTION("IF(AU9=data!A$5, IF(AI9<=1,IF(AI9<=0.8,IF(AI9<=0.6,IF(AI9<=0.4,IF(AI9<=0.2,23,26),29),30),32)*VLOOKUP(S9,filter('🔒 Доп. информация'!D:E,'🔒 Доп. информация'!C:C=T9),2,FALSE)/'🔒 Доп. информация'!$K$9, IF(AV9=data!A$8,U9,1)*VLOOKUP(S9,filter('🔒 Доп. инфо"&"рмация'!D:E,'🔒 Доп. информация'!C:C=T9),2,FALSE)+ IF(AV9=data!A$8,U9,1)*VLOOKUP(S9,filter('🔒 Доп. информация'!D:F,'🔒 Доп. информация'!C:C=T9),3,FALSE)*AJ9) ,0)"),44.85) -> 44.85 | BL9: =IF($D9,"🔒",) -> 🔒 | BM9: =IF($D9,"🔒",) -> 🔒 | BN9: =VLOOKUP(T9,'🔒 Доп. информация'!J:P,7,false) -> 50 | BO9: =IF(AV9=data!A$9, (AA9+AO9+AP9+BJ9+BK9+BN9)+H9*AS9, (BJ9+BK9+BN9)+H9*AS9 ) -> 94.85 | BP9: =AA9+BJ9+BK9 -> 44.85 | BQ9: =H9*N9 -> 320 | BR9: =BP9+BQ9+AS9*H9+((1-AQ9)/AQ9)*BO9+AL9+H9*J9*1.1 -> 394.85 | BS9: {=IF(VLOOKUP(AT9,{'▶️ Инструкция'!C:C,'▶️ Инструкция'!Y:Y},2,FALSE)=data!A$15, H9*(1-I9), (H9-BR9)) *VLOOKUP(AT9,{'▶️ Инструкция'!C:C,'▶️ Инструкция'!AD:AD},2,FALSE)/(1+VLOOKUP(AT9,{'▶️ Инструкция'!C:C,'▶️ Инструкция'!AD:AD},2,FALSE))} -> 0 | BT9: {=IF(VLOOKUP(AT9,{'▶️ Инструкция'!C:C,'▶️ Инструкция'!Y:Y},2,FALSE)=data!A$15, H9*(1-I9)-BS9, (H9-BR9-BS9)) * VLOOKUP(AT9,{'▶️ Инструкция'!C:C,'▶️ Инструкция'!R:R},2,FALSE) +BS9} -> 70 | BU9: =(G9*AR9)+if(AV9=data!A$9,AO9,AN9)+AP9+BR9+BT9 -> 464.85 | BV9: =(G9*AR9)+if(AV9=data!A$9,AO9,AN9)+AP9+BT9+G9 -> 70 | BW9: =H9-BR9 -> 605.15 | BX9: =BW9-BV9 -> 535.15
A10: =if(D10=true,if(F10=data!A$1,data!A$10,data!A$11),) -> ✅ | B10: =AV10 -> FBO | C10: Название товара | D10: TRUE | E10: Флюза | F10: {=IF(D10=TRUE,IF(IF(BG$3=VLOOKUP(AT10,{'▶️ Инструкция'!C:C,'▶️ Инструкция'!G:G},2,FALSE),BG10,BH10)>VLOOKUP(AT10,{'▶️ Инструкция'!C:C,'▶️ Инструкция'!N:N},2,FALSE),data!A$1,data!A$2),)} -> Срочно закупаем и продаем 💸 | G10: 146 | H10: 650 | I10: 0 | J10: 0 | K10: =IF($D10,"🔒",) -> 🔒 | L10: 0 | M10: Накладные ресницы | N10: =IFERROR(__xludf.DUMMYFUNCTION("ArrayFormula(let(category,VLOOKUP($M10, {'📄 Комиссии'!$C:$C , '📄 Комиссии'!$B:$B}, 2, 0), data,MATCH('🔒 Доп. информация'!$J$15:$J203,TRANSPOSE(SPLIT(INDEX('▶️ Инструкция'!$Q:$Q,MATCH($AT10,'▶️ Инструкция'!$R:$R,0)+2),"", "",FALSE)),0), options,COUNTA( "&"ifna( FILTER('🔒 Доп. информация'!$J$15:$J203,('🔒 Доп. информация'!$N$15:$N203=FALSE)*data*('🔒 Доп. информация'!$O$15:$O203=""Опция"")))), commission,VLOOKUP($M10,'📄 Комиссии'!$C:$E,IF($AV10=data!A$8,2,3),0), IF(NOT(ISBLANK($M10)),commission/100+ IFERR"&"OR(VLOOKUP($AT10,{'▶️ Инструкция'!$R:$R,'▶️ Инструкция'!$AK:$AK},2,0)+ IF((( category = ""Одежда"")+( category = ""Обувь"" ))*((options+SUM( ifna( FILTER('🔒 Доп. информация'!$M$15:$M203,('🔒 Доп. информация'!$N$15:$N203=FALSE)*data*('🔒 Доп. информация'!"&"$O$15:$O203=""Пакет"")))))>=5), -5% + 2%, IF((options>=1)* (COUNTA( ifna( FILTER('🔒 Доп. информация'!$J$15:$J203,('🔒 Доп. информация'!$N$15:$N203=FALSE)*data*('🔒 Доп. информация'!$O$15:$O203=""Пакет""))))>=1)* (commission>=14.5)* (category<> ""Одежда"&""")*( category <> ""Обувь"" ),-3% + 2%,0))))))"),0.325) -> 0.325 | O10: =IF($D10,"🔒",) -> 🔒 | Q10: =IF($D10,"🔒",) -> 🔒 | S10: Электросталь | T10: Короб | U10: 1 | V10: =IF($D10,"🔒",) -> 🔒 | W10: =IF($D10,"🔒",) -> 🔒 | X10: =IF($D10,"🔒",) -> 🔒 | Y10: =IF($D10,"🔒",) -> 🔒 | Z10: 0 | AA10: =1.7*(1+AJ10)*Z10 -> 0 | AB10: =IF($D10,"🔒",) -> 🔒 | AC10: =IF($D10,"🔒",) -> 🔒 | AD10: =IF($D10,"🔒",) -> 🔒 | AE10: 30 | AF10: 3 | AG10: 16 | AH10: 18 | AI10: =(AF10*AG10*AH10)/1000 -> 0.864 | AJ10: =if(AI10>1,(AI10-1),0) -> 0 | AK10: =IF($D10,"🔒",) -> 🔒 | AL10: {=H10*(1-I10)*VLOOKUP(AT10,{'▶️ Инструкция'!C:C,'▶️ Инструкция'!AI:AI},2,false)} -> 13 | AM10: =IF($D10,"🔒",) -> 🔒 | AN10: 0 | AO10: 0 | AP10: 0 | AQ10: 1 | AR10: 0 | AS10: 0.01 | AT10: ип F | AU10: WB | AV10: FBO | AW10: =AS10*H10 -> 6.5 | AX10: =(1/(AQ10))*H10*AS10 -> 6.5 | AY10: =AX10/BC10 -> 0.033704952 | AZ10: 250 | BA10: =AZ10/H10 -> 0.38461538 | BB10: =H10-AW10 -> 643.5 | BC10: =BX10 -> 192.85 | BD10: =BC10*L10 -> 0 | BE10: =H10*(1-I10)*L10 -> 0 | BF10: =IFERROR(BC10/BV10,) -> 1.1212209 | BG10: =IFERROR(BC10/H10,) -> 0.29669231 | BH10: =IFERROR(if(BW10>0,BC10/BW10,-BC10/BW10),) -> 0.52857339 | BJ10: =IFERROR(__xludf.DUMMYFUNCTION("IF(AU10=data!A$5, IF(AV10=data!A$8, IF(T10=data!A$3, VLOOKUP(S10,filter('🔒 Доп. информация'!D:H,'🔒 Доп. информация'!C:C=T10),4,FALSE)+VLOOKUP(S10,filter('🔒 Доп. информация'!D:H,'🔒 Доп. информация'!C:C=T10),5,FALSE)*AJ10, IF(AND(MAX(AF10:AH10)<80,SUM(A"&"F10:AH10)<=160,AI10<20,XLOOKUP(M10,'📄 Комиссии'!C:C,'📄 Комиссии'!B:B)<>""Продукты""), VLOOKUP(S10,filter('🔒 Доп. информация'!D:H,'🔒 Доп. информация'!C:C=data!$A$3),4,FALSE)+VLOOKUP(S10,filter('🔒 Доп. информация'!D:H,'🔒 Доп. информация'!C:C=data!$A$3"&"),5,FALSE)*AJ10, VLOOKUP(S10,filter('🔒 Доп. информация'!D:H,'🔒 Доп. информация'!C:C=T10),4,FALSE)*ROUNDUP(AF10*AG10*AH10*L10/(120*80*175))/L10) ) *(AE10/2) ,) ,)*0"),0.0) -> 0 | BK10: =IFERROR(__xludf.DUMMYFUNCTION("IF(AU10=data!A$5, IF(AI10<=1,IF(AI10<=0.8,IF(AI10<=0.6,IF(AI10<=0.4,IF(AI10<=0.2,23,26),29),30),32)*VLOOKUP(S10,filter('🔒 Доп. информация'!D:E,'🔒 Доп. информация'!C:C=T10),2,FALSE)/'🔒 Доп. информация'!$K$9, IF(AV10=data!A$8,U10,1)*VLOOKUP(S10,filter('"&"🔒 Доп. информация'!D:E,'🔒 Доп. информация'!C:C=T10),2,FALSE)+ IF(AV10=data!A$8,U10,1)*VLOOKUP(S10,filter('🔒 Доп. информация'!D:F,'🔒 Доп. информация'!C:C=T10),3,FALSE)*AJ10) ,0)"),54.4) -> 54.4 | BL10: =IF($D10,"🔒",) -> 🔒 | BM10: =IF($D10,"🔒",) -> 🔒 | BN10: =VLOOKUP(T10,'🔒 Доп. информация'!J:P,7,false) -> 50 | BO10: =IF(AV10=data!A$9, (AA10+AO10+AP10+BJ10+BK10+BN10)+H10*AS10, (BJ10+BK10+BN10)+H10*AS10 ) -> 110.9 | BP10: =AA10+BJ10+BK10 -> 54.4 | BQ10: =H10*N10 -> 211.25 | BR10: =BP10+BQ10+AS10*H10+((1-AQ10)/AQ10)*BO10+AL10+H10*J10*1.1 -> 285.15 | BS10: {=IF(VLOOKUP(AT10,{'▶️ Инструкция'!C:C,'▶️ Инструкция'!Y:Y},2,FALSE)=data!A$15, H10*(1-I10), (H10-BR10)) *VLOOKUP(AT10,{'▶️ Инструкция'!C:C,'▶️ Инструкция'!AD:AD},2,FALSE)/(1+VLOOKUP(AT10,{'▶️ Инструкция'!C:C,'▶️ Инструкция'!AD:AD},2,FALSE))} -> 0 | BT10: {=IF(VLOOKUP(AT10,{'▶️ Инструкция'!C:C,'▶️ Инструкция'!Y:Y},2,FALSE)=data!A$15, H10*(1-I10)-BS10, (H10-BR10-BS10)) * VLOOKUP(AT10,{'▶️ Инструкция'!C:C,'▶️ Инструкция'!R:R},2,FALSE) +BS10} -> 26 | BU10: =(G10*AR10)+if(AV10=data!A$9,AO10,AN10)+AP10+BR10+BT10 -> 311.15 | BV10: =(G10*AR10)+if(AV10=data!A$9,AO10,AN10)+AP10+BT10+G10 -> 172 | BW10: =H10-BR10 -> 364.85 | BX10: =BW10-BV10 -> 192.85
A11: =if(D11=true,if(F11=data!A$1,data!A$10,data!A$11),) -> ✅ | B11: =AV11 -> FBO | C11: ресницы | D11: TRUE | E11: Имя | F11: {=IF(D11=TRUE,IF(IF(BG$3=VLOOKUP(AT11,{'▶️ Инструкция'!C:C,'▶️ Инструкция'!G:G},2,FALSE),BG11,BH11)>VLOOKUP(AT11,{'▶️ Инструкция'!C:C,'▶️ Инструкция'!N:N},2,FALSE),data!A$1,data!A$2),)} -> Срочно закупаем и продаем 💸 | G11: 146 | H11: 600 | I11: 0 | J11: 0 | K11: =IF($D11,"🔒",) -> 🔒 | L11: 3600 | M11: Накладные ресницы | N11: =IFERROR(__xludf.DUMMYFUNCTION("ArrayFormula(let(category,VLOOKUP($M11, {'📄 Комиссии'!$C:$C , '📄 Комиссии'!$B:$B}, 2, 0), data,MATCH('🔒 Доп. информация'!$J$15:$J203,TRANSPOSE(SPLIT(INDEX('▶️ Инструкция'!$Q:$Q,MATCH($AT11,'▶️ Инструкция'!$R:$R,0)+2),"", "",FALSE)),0), options,COUNTA( "&"ifna( FILTER('🔒 Доп. информация'!$J$15:$J203,('🔒 Доп. информация'!$N$15:$N203=FALSE)*data*('🔒 Доп. информация'!$O$15:$O203=""Опция"")))), commission,VLOOKUP($M11,'📄 Комиссии'!$C:$E,IF($AV11=data!A$8,2,3),0), IF(NOT(ISBLANK($M11)),commission/100+ IFERR"&"OR(VLOOKUP($AT11,{'▶️ Инструкция'!$R:$R,'▶️ Инструкция'!$AK:$AK},2,0)+ IF((( category = ""Одежда"")+( category = ""Обувь"" ))*((options+SUM( ifna( FILTER('🔒 Доп. информация'!$M$15:$M203,('🔒 Доп. информация'!$N$15:$N203=FALSE)*data*('🔒 Доп. информация'!"&"$O$15:$O203=""Пакет"")))))>=5), -5% + 2%, IF((options>=1)* (COUNTA( ifna( FILTER('🔒 Доп. информация'!$J$15:$J203,('🔒 Доп. информация'!$N$15:$N203=FALSE)*data*('🔒 Доп. информация'!$O$15:$O203=""Пакет""))))>=1)* (commission>=14.5)* (category<> ""Одежда"&""")*( category <> ""Обувь"" ),-3% + 2%,0))))))"),0.325) -> 0.325 | O11: =IF($D11,"🔒",) -> 🔒 | Q11: =IF($D11,"🔒",) -> 🔒 | S11: Коледино | T11: Короб | U11: 1 | V11: =IF($D11,"🔒",) -> 🔒 | W11: =IF($D11,"🔒",) -> 🔒 | X11: =IF($D11,"🔒",) -> 🔒 | Y11: =IF($D11,"🔒",) -> 🔒 | Z11: 0 | AA11: =1.7*(1+AJ11)*Z11 -> 0 | AB11: =IF($D11,"🔒",) -> 🔒 | AC11: =IF($D11,"🔒",) -> 🔒 | AD11: =IF($D11,"🔒",) -> 🔒 | AE11: 30 | AF11: 3 | AG11: 16 | AH11: 18 | AI11: =(AF11*AG11*AH11)/1000 -> 0.864 | AJ11: =if(AI11>1,(AI11-1),0) -> 0 | AK11: =IF($D11,"🔒",) -> 🔒 | AL11: {=H11*(1-I11)*VLOOKUP(AT11,{'▶️ Инструкция'!C:C,'▶️ Инструкция'!AI:AI},2,false)} -> 12 | AM11: =IF($D11,"🔒",) -> 🔒 | AN11: 0 | AO11: 0 | AP11: 0 | AQ11: 0.95 | AR11: 0.002 | AS11: 0.01 | AT11: ип Samga | AU11: WB | AV11: FBO | AW11: =AS11*H11 -> 6 | AX11: =(1/(AQ11))*H11*AS11 -> 6.3157895 | AY11: =AX11/BC11 -> 0.043142934 | AZ11: 250 | BA11: =AZ11/H11 -> 0.41666667 | BB11: =H11-AW11 -> 594 | BC11: =BX11 -> 146.39221 | BD11: =BC11*L11 -> 527011.96 | BE11: =H11*(1-I11)*L11 -> 2160000 | BF11: =IFERROR(BC11/BV11,) -> 0.85965407 | BG11: =IFERROR(BC11/H11,) -> 0.24398702 | BH11: =IFERROR(if(BW11>0,BC11/BW11,-BC11/BW11),) -> 0.46226558 | BJ11: =IFERROR(__xludf.DUMMYFUNCTION("IF(AU11=data!A$5, IF(AV11=data!A$8, IF(T11=data!A$3, VLOOKUP(S11,filter('🔒 Доп. информация'!D:H,'🔒 Доп. информация'!C:C=T11),4,FALSE)+VLOOKUP(S11,filter('🔒 Доп. информация'!D:H,'🔒 Доп. информация'!C:C=T11),5,FALSE)*AJ11, IF(AND(MAX(AF11:AH11)<80,SUM(A"&"F11:AH11)<=160,AI11<20,XLOOKUP(M11,'📄 Комиссии'!C:C,'📄 Комиссии'!B:B)<>""Продукты""), VLOOKUP(S11,filter('🔒 Доп. информация'!D:H,'🔒 Доп. информация'!C:C=data!$A$3),4,FALSE)+VLOOKUP(S11,filter('🔒 Доп. информация'!D:H,'🔒 Доп. информация'!C:C=data!$A$3"&"),5,FALSE)*AJ11, VLOOKUP(S11,filter('🔒 Доп. информация'!D:H,'🔒 Доп. информация'!C:C=T11),4,FALSE)*ROUNDUP(AF11*AG11*AH11*L11/(120*80*175))/L11) ) *(AE11/2) ,) ,)*0"),0.0) -> 0 | BK11: =IFERROR(__xludf.DUMMYFUNCTION("IF(AU11=data!A$5, IF(AI11<=1,IF(AI11<=0.8,IF(AI11<=0.6,IF(AI11<=0.4,IF(AI11<=0.2,23,26),29),30),32)*VLOOKUP(S11,filter('🔒 Доп. информация'!D:E,'🔒 Доп. информация'!C:C=T11),2,FALSE)/'🔒 Доп. информация'!$K$9, IF(AV11=data!A$8,U11,1)*VLOOKUP(S11,filter('"&"🔒 Доп. информация'!D:E,'🔒 Доп. информация'!C:C=T11),2,FALSE)+ IF(AV11=data!A$8,U11,1)*VLOOKUP(S11,filter('🔒 Доп. информация'!D:F,'🔒 Доп. информация'!C:C=T11),3,FALSE)*AJ11) ,0)"),64.0) -> 64 | BL11: =IF($D11,"🔒",) -> 🔒 | BM11: =IF($D11,"🔒",) -> 🔒 | BN11: =VLOOKUP(T11,'🔒 Доп. информация'!J:P,7,false) -> 50 | BO11: =IF(AV11=data!A$9, (AA11+AO11+AP11+BJ11+BK11+BN11)+H11*AS11, (BJ11+BK11+BN11)+H11*AS11 ) -> 120 | BP11: =AA11+BJ11+BK11 -> 64 | BQ11: =H11*N11 -> 195 | BR11: =BP11+BQ11+AS11*H11+((1-AQ11)/AQ11)*BO11+AL11+H11*J11*1.1 -> 283.31579 | BS11: {=IF(VLOOKUP(AT11,{'▶️ Инструкция'!C:C,'▶️ Инструкция'!Y:Y},2,FALSE)=data!A$15, H11*(1-I11), (H11-BR11)) *VLOOKUP(AT11,{'▶️ Инструкция'!C:C,'▶️ Инструкция'!AD:AD},2,FALSE)/(1+VLOOKUP(AT11,{'▶️ Инструкция'!C:C,'▶️ Инструкция'!AD:AD},2,FALSE))} -> 0 | BT11: {=IF(VLOOKUP(AT11,{'▶️ Инструкция'!C:C,'▶️ Инструкция'!Y:Y},2,FALSE)=data!A$15, H11*(1-I11)-BS11, (H11-BR11-BS11)) * VLOOKUP(AT11,{'▶️ Инструкция'!C:C,'▶️ Инструкция'!R:R},2,FALSE) +BS11} -> 24 | BU11: =(G11*AR11)+if(AV11=data!A$9,AO11,AN11)+AP11+BR11+BT11 -> 307.60779 | BV11: =(G11*AR11)+if(AV11=data!A$9,AO11,AN11)+AP11+BT11+G11 -> 170.292 | BW11: =H11-BR11 -> 316.68421 | BX11: =BW11-BV11 -> 146.39221
A12: =if(D12=true,if(F12=data!A$1,data!A$10,data!A$11),) | B12: =AV12 -> FBS | C12: Название товара | D12: FALSE | E12: Имя | F12: {=IF(D12=TRUE,IF(IF(BG$3=VLOOKUP(AT12,{'▶️ Инструкция'!C:C,'▶️ Инструкция'!G:G},2,FALSE),BG12,BH12)>VLOOKUP(AT12,{'▶️ Инструкция'!C:C,'▶️ Инструкция'!N:N},2,FALSE),data!A$1,data!A$2),)} | G12: 0 | H12: 1000 | I12: 0 | J12: 0 | K12: =IF($D12,"🔒",) | L12: 0 | M12: Лопатки игрушечные | N12: =IFERROR(__xludf.DUMMYFUNCTION("ArrayFormula(let(category,VLOOKUP($M12, {'📄 Комиссии'!$C:$C , '📄 Комиссии'!$B:$B}, 2, 0), data,MATCH('🔒 Доп. информация'!$J$15:$J203,TRANSPOSE(SPLIT(INDEX('▶️ Инструкция'!$Q:$Q,MATCH($AT12,'▶️ Инструкция'!$R:$R,0)+2),"", "",FALSE)),0), options,COUNTA( "&"ifna( FILTER('🔒 Доп. информация'!$J$15:$J203,('🔒 Доп. информация'!$N$15:$N203=FALSE)*data*('🔒 Доп. информация'!$O$15:$O203=""Опция"")))), commission,VLOOKUP($M12,'📄 Комиссии'!$C:$E,IF($AV12=data!A$8,2,3),0), IF(NOT(ISBLANK($M12)),commission/100+ IFERR"&"OR(VLOOKUP($AT12,{'▶️ Инструкция'!$R:$R,'▶️ Инструкция'!$AK:$AK},2,0)+ IF((( category = ""Одежда"")+( category = ""Обувь"" ))*((options+SUM( ifna( FILTER('🔒 Доп. информация'!$M$15:$M203,('🔒 Доп. информация'!$N$15:$N203=FALSE)*data*('🔒 Доп. информация'!"&"$O$15:$O203=""Пакет"")))))>=5), -5% + 2%, IF((options>=1)* (COUNTA( ifna( FILTER('🔒 Доп. информация'!$J$15:$J203,('🔒 Доп. информация'!$N$15:$N203=FALSE)*data*('🔒 Доп. информация'!$O$15:$O203=""Пакет""))))>=1)* (commission>=14.5)* (category<> ""Одежда"&""")*( category <> ""Обувь"" ),-3% + 2%,0))))))"),0.32) -> 0.32 | O12: =IF($D12,"🔒",) | Q12: =IF($D12,"🔒",) | S12: Макс. из наших | T12: Короб | U12: 1 | V12: =IF($D12,"🔒",) | W12: =IF($D12,"🔒",) | X12: =IF($D12,"🔒",) | Y12: =IF($D12,"🔒",) | Z12: 0 | AA12: =1.7*(1+AJ12)*Z12 -> 0 | AB12: =IF($D12,"🔒",) | AC12: =IF($D12,"🔒",) | AD12: =IF($D12,"🔒",) | AE12: 30 | AF12: 0 | AG12: 0 | AH12: 0 | AI12: =(AF12*AG12*AH12)/1000 -> 0 | AJ12: =if(AI12>1,(AI12-1),0) -> 0 | AK12: =IF($D12,"🔒",) | AL12: {=H12*(1-I12)*VLOOKUP(AT12,{'▶️ Инструкция'!C:C,'▶️ Инструкция'!AI:AI},2,false)} -> #N/A | AM12: =IF($D12,"🔒",) | AN12: 0 | AO12: 0 | AP12: 0 | AQ12: 1 | AR12: 0 | AS12: 0 | AT12: 2 Бренд | AU12: WB | AV12: FBS | AW12: =AS12*H12 -> 0 | AX12: =(1/(AQ12))*H12*AS12 -> 0 | AY12: =AX12/BC12 -> #N/A | AZ12: 250 | BA12: =AZ12/H12 -> 0.25 | BB12: =H12-AW12 -> 1000 | BC12: =BX12 -> #N/A | BD12: =BC12*L12 -> #N/A | BE12: =H12*(1-I12)*L12 -> 0 | BF12: =IFERROR(BC12/BV12,) | BG12: =IFERROR(BC12/H12,) | BH12: =IFERROR(if(BW12>0,BC12/BW12,-BC12/BW12),) | BJ12: =IFERROR(__xludf.DUMMYFUNCTION("IF(AU12=data!A$5, IF(AV12=data!A$8, IF(T12=data!A$3, VLOOKUP(S12,filter('🔒 Доп. информация'!D:H,'🔒 Доп. информация'!C:C=T12),4,FALSE)+VLOOKUP(S12,filter('🔒 Доп. информация'!D:H,'🔒 Доп. информация'!C:C=T12),5,FALSE)*AJ12, IF(AND(MAX(AF12:AH12)<80,SUM(A"&"F12:AH12)<=160,AI12<20,XLOOKUP(M12,'📄 Комиссии'!C:C,'📄 Комиссии'!B:B)<>""Продукты""), VLOOKUP(S12,filter('🔒 Доп. информация'!D:H,'🔒 Доп. информация'!C:C=data!$A$3),4,FALSE)+VLOOKUP(S12,filter('🔒 Доп. информация'!D:H,'🔒 Доп. информация'!C:C=data!$A$3"&"),5,FALSE)*AJ12, VLOOKUP(S12,filter('🔒 Доп. информация'!D:H,'🔒 Доп. информация'!C:C=T12),4,FALSE)*ROUNDUP(AF12*AG12*AH12*L12/(120*80*175))/L12) ) *(AE12/2) ,) ,)*0"),0.0) -> 0 | BK12: =IFERROR(__xludf.DUMMYFUNCTION("IF(AU12=data!A$5, IF(AI12<=1,IF(AI12<=0.8,IF(AI12<=0.6,IF(AI12<=0.4,IF(AI12<=0.2,23,26),29),30),32)*VLOOKUP(S12,filter('🔒 Доп. информация'!D:E,'🔒 Доп. информация'!C:C=T12),2,FALSE)/'🔒 Доп. информация'!$K$9, IF(AV12=data!A$8,U12,1)*VLOOKUP(S12,filter('"&"🔒 Доп. информация'!D:E,'🔒 Доп. информация'!C:C=T12),2,FALSE)+ IF(AV12=data!A$8,U12,1)*VLOOKUP(S12,filter('🔒 Доп. информация'!D:F,'🔒 Доп. информация'!C:C=T12),3,FALSE)*AJ12) ,0)"),69.0) -> 69 | BL12: =IF($D12,"🔒",) | BM12: =IF($D12,"🔒",) | BN12: =VLOOKUP(T12,'🔒 Доп. информация'!J:P,7,false) -> 50 | BO12: =IF(AV12=data!A$9, (AA12+AO12+AP12+BJ12+BK12+BN12)+H12*AS12, (BJ12+BK12+BN12)+H12*AS12 ) -> 119 | BP12: =AA12+BJ12+BK12 -> 69 | BQ12: =H12*N12 -> 320 | BR12: =BP12+BQ12+AS12*H12+((1-AQ12)/AQ12)*BO12+AL12+H12*J12*1.1 -> #N/A | BS12: {=IF(VLOOKUP(AT12,{'▶️ Инструкция'!C:C,'▶️ Инструкция'!Y:Y},2,FALSE)=data!A$15, H12*(1-I12), (H12-BR12)) *VLOOKUP(AT12,{'▶️ Инструкция'!C:C,'▶️ Инструкция'!AD:AD},2,FALSE)/(1+VLOOKUP(AT12,{'▶️ Инструкция'!C:C,'▶️ Инструкция'!AD:AD},2,FALSE))} -> #N/A | BT12: {=IF(VLOOKUP(AT12,{'▶️ Инструкция'!C:C,'▶️ Инструкция'!Y:Y},2,FALSE)=data!A$15, H12*(1-I12)-BS12, (H12-BR12-BS12)) * VLOOKUP(AT12,{'▶️ Инструкция'!C:C,'▶️ Инструкция'!R:R},2,FALSE) +BS12} -> #N/A | BU12: =(G12*AR12)+if(AV12=data!A$9,AO12,AN12)+AP12+BR12+BT12 -> #N/A | BV12: =(G12*AR12)+if(AV12=data!A$9,AO12,AN12)+AP12+BT12+G12 -> #N/A | BW12: =H12-BR12 -> #N/A | BX12: =BW12-BV12 -> #N/A
A13: =if(D13=true,if(F13=data!A$1,data!A$10,data!A$11),) | B13: =AV13 -> FBS | C13: Название товара | D13: FALSE | E13: Имя | F13: {=IF(D13=TRUE,IF(IF(BG$3=VLOOKUP(AT13,{'▶️ Инструкция'!C:C,'▶️ Инструкция'!G:G},2,FALSE),BG13,BH13)>VLOOKUP(AT13,{'▶️ Инструкция'!C:C,'▶️ Инструкция'!N:N},2,FALSE),data!A$1,data!A$2),)} | G13: 0 | H13: 1000 | I13: 0 | J13: 0 | K13: =IF($D13,"🔒",) | L13: 0 | M13: Лопатки игрушечные | N13: =IFERROR(__xludf.DUMMYFUNCTION("ArrayFormula(let(category,VLOOKUP($M13, {'📄 Комиссии'!$C:$C , '📄 Комиссии'!$B:$B}, 2, 0), data,MATCH('🔒 Доп. информация'!$J$15:$J203,TRANSPOSE(SPLIT(INDEX('▶️ Инструкция'!$Q:$Q,MATCH($AT13,'▶️ Инструкция'!$R:$R,0)+2),"", "",FALSE)),0), options,COUNTA( "&"ifna( FILTER('🔒 Доп. информация'!$J$15:$J203,('🔒 Доп. информация'!$N$15:$N203=FALSE)*data*('🔒 Доп. информация'!$O$15:$O203=""Опция"")))), commission,VLOOKUP($M13,'📄 Комиссии'!$C:$E,IF($AV13=data!A$8,2,3),0), IF(NOT(ISBLANK($M13)),commission/100+ IFERR"&"OR(VLOOKUP($AT13,{'▶️ Инструкция'!$R:$R,'▶️ Инструкция'!$AK:$AK},2,0)+ IF((( category = ""Одежда"")+( category = ""Обувь"" ))*((options+SUM( ifna( FILTER('🔒 Доп. информация'!$M$15:$M203,('🔒 Доп. информация'!$N$15:$N203=FALSE)*data*('🔒 Доп. информация'!"&"$O$15:$O203=""Пакет"")))))>=5), -5% + 2%, IF((options>=1)* (COUNTA( ifna( FILTER('🔒 Доп. информация'!$J$15:$J203,('🔒 Доп. информация'!$N$15:$N203=FALSE)*data*('🔒 Доп. информация'!$O$15:$O203=""Пакет""))))>=1)* (commission>=14.5)* (category<> ""Одежда"&""")*( category <> ""Обувь"" ),-3% + 2%,0))))))"),0.32) -> 0.32 | O13: =IF($D13,"🔒",) | Q13: =IF($D13,"🔒",) | S13: Макс. из наших | T13: Короб | U13: 1 | V13: =IF($D13,"🔒",) | W13: =IF($D13,"🔒",) | X13: =IF($D13,"🔒",) | Y13: =IF($D13,"🔒",) | Z13: 0 | AA13: =1.7*(1+AJ13)*Z13 -> 0 | AB13: =IF($D13,"🔒",) | AC13: =IF($D13,"🔒",) | AD13: =IF($D13,"🔒",) | AE13: 30 | AF13: 0 | AG13: 0 | AH13: 0 | AI13: =(AF13*AG13*AH13)/1000 -> 0 | AJ13: =if(AI13>1,(AI13-1),0) -> 0 | AK13: =IF($D13,"🔒",) | AL13: {=H13*(1-I13)*VLOOKUP(AT13,{'▶️ Инструкция'!C:C,'▶️ Инструкция'!AI:AI},2,false)} -> #N/A | AM13: =IF($D13,"🔒",) | AN13: 0 | AO13: 0 | AP13: 0 | AQ13: 1 | AR13: 0 | AS13: 0 | AT13: 2 Бренд | AU13: WB | AV13: FBS | AW13: =AS13*H13 -> 0 | AX13: =(1/(AQ13))*H13*AS13 -> 0 | AY13: =AX13/BC13 -> #N/A | AZ13: 250 | BA13: =AZ13/H13 -> 0.25 | BB13: =H13-AW13 -> 1000 | BC13: =BX13 -> #N/A | BD13: =BC13*L13 -> #N/A | BE13: =H13*(1-I13)*L13 -> 0 | BF13: =IFERROR(BC13/BV13,) | BG13: =IFERROR(BC13/H13,) | BH13: =IFERROR(if(BW13>0,BC13/BW13,-BC13/BW13),) | BJ13: =IFERROR(__xludf.DUMMYFUNCTION("IF(AU13=data!A$5, IF(AV13=data!A$8, IF(T13=data!A$3, VLOOKUP(S13,filter('🔒 Доп. информация'!D:H,'🔒 Доп. информация'!C:C=T13),4,FALSE)+VLOOKUP(S13,filter('🔒 Доп. информация'!D:H,'🔒 Доп. информация'!C:C=T13),5,FALSE)*AJ13, IF(AND(MAX(AF13:AH13)<80,SUM(A"&"F13:AH13)<=160,AI13<20,XLOOKUP(M13,'📄 Комиссии'!C:C,'📄 Комиссии'!B:B)<>""Продукты""), VLOOKUP(S13,filter('🔒 Доп. информация'!D:H,'🔒 Доп. информация'!C:C=data!$A$3),4,FALSE)+VLOOKUP(S13,filter('🔒 Доп. информация'!D:H,'🔒 Доп. информация'!C:C=data!$A$3"&"),5,FALSE)*AJ13, VLOOKUP(S13,filter('🔒 Доп. информация'!D:H,'🔒 Доп. информация'!C:C=T13),4,FALSE)*ROUNDUP(AF13*AG13*AH13*L13/(120*80*175))/L13) ) *(AE13/2) ,) ,)*0"),0.0) -> 0 | BK13: =IFERROR(__xludf.DUMMYFUNCTION("IF(AU13=data!A$5, IF(AI13<=1,IF(AI13<=0.8,IF(AI13<=0.6,IF(AI13<=0.4,IF(AI13<=0.2,23,26),29),30),32)*VLOOKUP(S13,filter('🔒 Доп. информация'!D:E,'🔒 Доп. информация'!C:C=T13),2,FALSE)/'🔒 Доп. информация'!$K$9, IF(AV13=data!A$8,U13,1)*VLOOKUP(S13,filter('"&"🔒 Доп. информация'!D:E,'🔒 Доп. информация'!C:C=T13),2,FALSE)+ IF(AV13=data!A$8,U13,1)*VLOOKUP(S13,filter('🔒 Доп. информация'!D:F,'🔒 Доп. информация'!C:C=T13),3,FALSE)*AJ13) ,0)"),69.0) -> 69 | BL13: =IF($D13,"🔒",) | BM13: =IF($D13,"🔒",) | BN13: =VLOOKUP(T13,'🔒 Доп. информация'!J:P,7,false) -> 50 | BO13: =IF(AV13=data!A$9, (AA13+AO13+AP13+BJ13+BK13+BN13)+H13*AS13, (BJ13+BK13+BN13)+H13*AS13 ) -> 119 | BP13: =AA13+BJ13+BK13 -> 69 | BQ13: =H13*N13 -> 320 | BR13: =BP13+BQ13+AS13*H13+((1-AQ13)/AQ13)*BO13+AL13+H13*J13*1.1 -> #N/A | BS13: {=IF(VLOOKUP(AT13,{'▶️ Инструкция'!C:C,'▶️ Инструкция'!Y:Y},2,FALSE)=data!A$15, H13*(1-I13), (H13-BR13)) *VLOOKUP(AT13,{'▶️ Инструкция'!C:C,'▶️ Инструкция'!AD:AD},2,FALSE)/(1+VLOOKUP(AT13,{'▶️ Инструкция'!C:C,'▶️ Инструкция'!AD:AD},2,FALSE))} -> #N/A | BT13: {=IF(VLOOKUP(AT13,{'▶️ Инструкция'!C:C,'▶️ Инструкция'!Y:Y},2,FALSE)=data!A$15, H13*(1-I13)-BS13, (H13-BR13-BS13)) * VLOOKUP(AT13,{'▶️ Инструкция'!C:C,'▶️ Инструкция'!R:R},2,FALSE) +BS13} -> #N/A | BU13: =(G13*AR13)+if(AV13=data!A$9,AO13,AN13)+AP13+BR13+BT13 -> #N/A | BV13: =(G13*AR13)+if(AV13=data!A$9,AO13,AN13)+AP13+BT13+G13 -> #N/A | BW13: =H13-BR13 -> #N/A | BX13: =BW13-BV13 -> #N/A
A14: =if(D14=true,if(F14=data!A$1,data!A$10,data!A$11),) | B14: =AV14 -> FBS | C14: Название товара | D14: FALSE | E14: Имя | F14: {=IF(D14=TRUE,IF(IF(BG$3=VLOOKUP(AT14,{'▶️ Инструкция'!C:C,'▶️ Инструкция'!G:G},2,FALSE),BG14,BH14)>VLOOKUP(AT14,{'▶️ Инструкция'!C:C,'▶️ Инструкция'!N:N},2,FALSE),data!A$1,data!A$2),)} | G14: 0 | H14: 1000 | I14: 0 | J14: 0 | K14: =IF($D14,"🔒",) | L14: 0 | M14: Лопатки игрушечные | N14: =IFERROR(__xludf.DUMMYFUNCTION("ArrayFormula(let(category,VLOOKUP($M14, {'📄 Комиссии'!$C:$C , '📄 Комиссии'!$B:$B}, 2, 0), data,MATCH('🔒 Доп. информация'!$J$15:$J203,TRANSPOSE(SPLIT(INDEX('▶️ Инструкция'!$Q:$Q,MATCH($AT14,'▶️ Инструкция'!$R:$R,0)+2),"", "",FALSE)),0), options,COUNTA( "&"ifna( FILTER('🔒 Доп. информация'!$J$15:$J203,('🔒 Доп. информация'!$N$15:$N203=FALSE)*data*('🔒 Доп. информация'!$O$15:$O203=""Опция"")))), commission,VLOOKUP($M14,'📄 Комиссии'!$C:$E,IF($AV14=data!A$8,2,3),0), IF(NOT(ISBLANK($M14)),commission/100+ IFERR"&"OR(VLOOKUP($AT14,{'▶️ Инструкция'!$R:$R,'▶️ Инструкция'!$AK:$AK},2,0)+ IF((( category = ""Одежда"")+( category = ""Обувь"" ))*((options+SUM( ifna( FILTER('🔒 Доп. информация'!$M$15:$M203,('🔒 Доп. информация'!$N$15:$N203=FALSE)*data*('🔒 Доп. информация'!"&"$O$15:$O203=""Пакет"")))))>=5), -5% + 2%, IF((options>=1)* (COUNTA( ifna( FILTER('🔒 Доп. информация'!$J$15:$J203,('🔒 Доп. информация'!$N$15:$N203=FALSE)*data*('🔒 Доп. информация'!$O$15:$O203=""Пакет""))))>=1)* (commission>=14.5)* (category<> ""Одежда"&""")*( category <> ""Обувь"" ),-3% + 2%,0))))))"),0.32) -> 0.32 | O14: =IF($D14,"🔒",) | Q14: =IF($D14,"🔒",) | S14: Макс. из наших | T14: Короб | U14: 1 | V14: =IF($D14,"🔒",) | W14: =IF($D14,"🔒",) | X14: =IF($D14,"🔒",) | Y14: =IF($D14,"🔒",) | Z14: 0 | AA14: =1.7*(1+AJ14)*Z14 -> 0 | AB14: =IF($D14,"🔒",) | AC14: =IF($D14,"🔒",) | AD14: =IF($D14,"🔒",) | AE14: 30 | AF14: 0 | AG14: 0 | AH14: 0 | AI14: =(AF14*AG14*AH14)/1000 -> 0 | AJ14: =if(AI14>1,(AI14-1),0) -> 0 | AK14: =IF($D14,"🔒",) | AL14: {=H14*(1-I14)*VLOOKUP(AT14,{'▶️ Инструкция'!C:C,'▶️ Инструкция'!AI:AI},2,false)} -> #N/A | AM14: =IF($D14,"🔒",) | AN14: 0 | AO14: 0 | AP14: 0 | AQ14: 1 | AR14: 0 | AS14: 0 | AT14: 2 Бренд | AU14: WB | AV14: FBS | AW14: =AS14*H14 -> 0 | AX14: =(1/(AQ14))*H14*AS14 -> 0 | AY14: =AX14/BC14 -> #N/A | AZ14: 250 | BA14: =AZ14/H14 -> 0.25 | BB14: =H14-AW14 -> 1000 | BC14: =BX14 -> #N/A | BD14: =BC14*L14 -> #N/A | BE14: =H14*(1-I14)*L14 -> 0 | BF14: =IFERROR(BC14/BV14,) | BG14: =IFERROR(BC14/H14,) | BH14: =IFERROR(if(BW14>0,BC14/BW14,-BC14/BW14),) | BJ14: =IFERROR(__xludf.DUMMYFUNCTION("IF(AU14=data!A$5, IF(AV14=data!A$8, IF(T14=data!A$3, VLOOKUP(S14,filter('🔒 Доп. информация'!D:H,'🔒 Доп. информация'!C:C=T14),4,FALSE)+VLOOKUP(S14,filter('🔒 Доп. информация'!D:H,'🔒 Доп. информация'!C:C=T14),5,FALSE)*AJ14, IF(AND(MAX(AF14:AH14)<80,SUM(A"&"F14:AH14)<=160,AI14<20,XLOOKUP(M14,'📄 Комиссии'!C:C,'📄 Комиссии'!B:B)<>""Продукты""), VLOOKUP(S14,filter('🔒 Доп. информация'!D:H,'🔒 Доп. информация'!C:C=data!$A$3),4,FALSE)+VLOOKUP(S14,filter('🔒 Доп. информация'!D:H,'🔒 Доп. информация'!C:C=data!$A$3"&"),5,FALSE)*AJ14, VLOOKUP(S14,filter('🔒 Доп. информация'!D:H,'🔒 Доп. информация'!C:C=T14),4,FALSE)*ROUNDUP(AF14*AG14*AH14*L14/(120*80*175))/L14) ) *(AE14/2) ,) ,)*0"),0.0) -> 0 | BK14: =IFERROR(__xludf.DUMMYFUNCTION("IF(AU14=data!A$5, IF(AI14<=1,IF(AI14<=0.8,IF(AI14<=0.6,IF(AI14<=0.4,IF(AI14<=0.2,23,26),29),30),32)*VLOOKUP(S14,filter('🔒 Доп. информация'!D:E,'🔒 Доп. информация'!C:C=T14),2,FALSE)/'🔒 Доп. информация'!$K$9, IF(AV14=data!A$8,U14,1)*VLOOKUP(S14,filter('"&"🔒 Доп. информация'!D:E,'🔒 Доп. информация'!C:C=T14),2,FALSE)+ IF(AV14=data!A$8,U14,1)*VLOOKUP(S14,filter('🔒 Доп. информация'!D:F,'🔒 Доп. информация'!C:C=T14),3,FALSE)*AJ14) ,0)"),69.0) -> 69 | BL14: =IF($D14,"🔒",) | BM14: =IF($D14,"🔒",) | BN14: =VLOOKUP(T14,'🔒 Доп. информация'!J:P,7,false) -> 50 | BO14: =IF(AV14=data!A$9, (AA14+AO14+AP14+BJ14+BK14+BN14)+H14*AS14, (BJ14+BK14+BN14)+H14*AS14 ) -> 119 | BP14: =AA14+BJ14+BK14 -> 69 | BQ14: =H14*N14 -> 320 | BR14: =BP14+BQ14+AS14*H14+((1-AQ14)/AQ14)*BO14+AL14+H14*J14*1.1 -> #N/A | BS14: {=IF(VLOOKUP(AT14,{'▶️ Инструкция'!C:C,'▶️ Инструкция'!Y:Y},2,FALSE)=data!A$15, H14*(1-I14), (H14-BR14)) *VLOOKUP(AT14,{'▶️ Инструкция'!C:C,'▶️ Инструкция'!AD:AD},2,FALSE)/(1+VLOOKUP(AT14,{'▶️ Инструкция'!C:C,'▶️ Инструкция'!AD:AD},2,FALSE))} -> #N/A | BT14: {=IF(VLOOKUP(AT14,{'▶️ Инструкция'!C:C,'▶️ Инструкция'!Y:Y},2,FALSE)=data!A$15, H14*(1-I14)-BS14, (H14-BR14-BS14)) * VLOOKUP(AT14,{'▶️ Инструкция'!C:C,'▶️ Инструкция'!R:R},2,FALSE) +BS14} -> #N/A | BU14: =(G14*AR14)+if(AV14=data!A$9,AO14,AN14)+AP14+BR14+BT14 -> #N/A | BV14: =(G14*AR14)+if(AV14=data!A$9,AO14,AN14)+AP14+BT14+G14 -> #N/A | BW14: =H14-BR14 -> #N/A | BX14: =BW14-BV14 -> #N/A
A15: =if(D15=true,if(F15=data!A$1,data!A$10,data!A$11),) | B15: =AV15 -> FBS | C15: Название товара | D15: FALSE | E15: Имя | F15: {=IF(D15=TRUE,IF(IF(BG$3=VLOOKUP(AT15,{'▶️ Инструкция'!C:C,'▶️ Инструкция'!G:G},2,FALSE),BG15,BH15)>VLOOKUP(AT15,{'▶️ Инструкция'!C:C,'▶️ Инструкция'!N:N},2,FALSE),data!A$1,data!A$2),)} | G15: 0 | H15: 1000 | I15: 0 | J15: 0 | K15: =IF($D15,"🔒",) | L15: 0 | M15: Лопатки игрушечные | N15: =IFERROR(__xludf.DUMMYFUNCTION("ArrayFormula(let(category,VLOOKUP($M15, {'📄 Комиссии'!$C:$C , '📄 Комиссии'!$B:$B}, 2, 0), data,MATCH('🔒 Доп. информация'!$J$15:$J203,TRANSPOSE(SPLIT(INDEX('▶️ Инструкция'!$Q:$Q,MATCH($AT15,'▶️ Инструкция'!$R:$R,0)+2),"", "",FALSE)),0), options,COUNTA( "&"ifna( FILTER('🔒 Доп. информация'!$J$15:$J203,('🔒 Доп. информация'!$N$15:$N203=FALSE)*data*('🔒 Доп. информация'!$O$15:$O203=""Опция"")))), commission,VLOOKUP($M15,'📄 Комиссии'!$C:$E,IF($AV15=data!A$8,2,3),0), IF(NOT(ISBLANK($M15)),commission/100+ IFERR"&"OR(VLOOKUP($AT15,{'▶️ Инструкция'!$R:$R,'▶️ Инструкция'!$AK:$AK},2,0)+ IF((( category = ""Одежда"")+( category = ""Обувь"" ))*((options+SUM( ifna( FILTER('🔒 Доп. информация'!$M$15:$M203,('🔒 Доп. информация'!$N$15:$N203=FALSE)*data*('🔒 Доп. информация'!"&"$O$15:$O203=""Пакет"")))))>=5), -5% + 2%, IF((options>=1)* (COUNTA( ifna( FILTER('🔒 Доп. информация'!$J$15:$J203,('🔒 Доп. информация'!$N$15:$N203=FALSE)*data*('🔒 Доп. информация'!$O$15:$O203=""Пакет""))))>=1)* (commission>=14.5)* (category<> ""Одежда"&""")*( category <> ""Обувь"" ),-3% + 2%,0))))))"),0.32) -> 0.32 | O15: =IF($D15,"🔒",) | Q15: =IF($D15,"🔒",) | S15: Макс. из наших | T15: Короб | U15: 1 | V15: =IF($D15,"🔒",) | W15: =IF($D15,"🔒",) | X15: =IF($D15,"🔒",) | Y15: =IF($D15,"🔒",) | Z15: 0 | AA15: =1.7*(1+AJ15)*Z15 -> 0 | AB15: =IF($D15,"🔒",) | AC15: =IF($D15,"🔒",) | AD15: =IF($D15,"🔒",) | AE15: 30 | AF15: 0 | AG15: 0 | AH15: 0 | AI15: =(AF15*AG15*AH15)/1000 -> 0 | AJ15: =if(AI15>1,(AI15-1),0) -> 0 | AK15: =IF($D15,"🔒",) | AL15: {=H15*(1-I15)*VLOOKUP(AT15,{'▶️ Инструкция'!C:C,'▶️ Инструкция'!AI:AI},2,false)} -> #N/A | AM15: =IF($D15,"🔒",) | AN15: 0 | AO15: 0 | AP15: 0 | AQ15: 1 | AR15: 0 | AS15: 0 | AT15: ИП Иванов И.И. | AU15: WB | AV15: FBS | AW15: =AS15*H15 -> 0 | AX15: =(1/(AQ15))*H15*AS15 -> 0 | AY15: =AX15/BC15 -> #N/A | AZ15: 250 | BA15: =AZ15/H15 -> 0.25 | BB15: =H15-AW15 -> 1000 | BC15: =BX15 -> #N/A | BD15: =BC15*L15 -> #N/A | BE15: =H15*(1-I15)*L15 -> 0 | BF15: =IFERROR(BC15/BV15,) | BG15: =IFERROR(BC15/H15,) | BH15: =IFERROR(if(BW15>0,BC15/BW15,-BC15/BW15),) | BJ15: =IFERROR(__xludf.DUMMYFUNCTION("IF(AU15=data!A$5, IF(AV15=data!A$8, IF(T15=data!A$3, VLOOKUP(S15,filter('🔒 Доп. информация'!D:H,'🔒 Доп. информация'!C:C=T15),4,FALSE)+VLOOKUP(S15,filter('🔒 Доп. информация'!D:H,'🔒 Доп. информация'!C:C=T15),5,FALSE)*AJ15, IF(AND(MAX(AF15:AH15)<80,SUM(A"&"F15:AH15)<=160,AI15<20,XLOOKUP(M15,'📄 Комиссии'!C:C,'📄 Комиссии'!B:B)<>""Продукты""), VLOOKUP(S15,filter('🔒 Доп. информация'!D:H,'🔒 Доп. информация'!C:C=data!$A$3),4,FALSE)+VLOOKUP(S15,filter('🔒 Доп. информация'!D:H,'🔒 Доп. информация'!C:C=data!$A$3"&"),5,FALSE)*AJ15, VLOOKUP(S15,filter('🔒 Доп. информация'!D:H,'🔒 Доп. информация'!C:C=T15),4,FALSE)*ROUNDUP(AF15*AG15*AH15*L15/(120*80*175))/L15) ) *(AE15/2) ,) ,)*0"),0.0) -> 0 | BK15: =IFERROR(__xludf.DUMMYFUNCTION("IF(AU15=data!A$5, IF(AI15<=1,IF(AI15<=0.8,IF(AI15<=0.6,IF(AI15<=0.4,IF(AI15<=0.2,23,26),29),30),32)*VLOOKUP(S15,filter('🔒 Доп. информация'!D:E,'🔒 Доп. информация'!C:C=T15),2,FALSE)/'🔒 Доп. информация'!$K$9, IF(AV15=data!A$8,U15,1)*VLOOKUP(S15,filter('"&"🔒 Доп. информация'!D:E,'🔒 Доп. информация'!C:C=T15),2,FALSE)+ IF(AV15=data!A$8,U15,1)*VLOOKUP(S15,filter('🔒 Доп. информация'!D:F,'🔒 Доп. информация'!C:C=T15),3,FALSE)*AJ15) ,0)"),69.0) -> 69 | BL15: =IF($D15,"🔒",) | BM15: =IF($D15,"🔒",) | BN15: =VLOOKUP(T15,'🔒 Доп. информация'!J:P,7,false) -> 50 | BO15: =IF(AV15=data!A$9, (AA15+AO15+AP15+BJ15+BK15+BN15)+H15*AS15, (BJ15+BK15+BN15)+H15*AS15 ) -> 119 | BP15: =AA15+BJ15+BK15 -> 69 | BQ15: =H15*N15 -> 320 | BR15: =BP15+BQ15+AS15*H15+((1-AQ15)/AQ15)*BO15+AL15+H15*J15*1.1 -> #N/A | BS15: {=IF(VLOOKUP(AT15,{'▶️ Инструкция'!C:C,'▶️ Инструкция'!Y:Y},2,FALSE)=data!A$15, H15*(1-I15), (H15-BR15)) *VLOOKUP(AT15,{'▶️ Инструкция'!C:C,'▶️ Инструкция'!AD:AD},2,FALSE)/(1+VLOOKUP(AT15,{'▶️ Инструкция'!C:C,'▶️ Инструкция'!AD:AD},2,FALSE))} -> #N/A | BT15: {=IF(VLOOKUP(AT15,{'▶️ Инструкция'!C:C,'▶️ Инструкция'!Y:Y},2,FALSE)=data!A$15, H15*(1-I15)-BS15, (H15-BR15-BS15)) * VLOOKUP(AT15,{'▶️ Инструкция'!C:C,'▶️ Инструкция'!R:R},2,FALSE) +BS15} -> #N/A | BU15: =(G15*AR15)+if(AV15=data!A$9,AO15,AN15)+AP15+BR15+BT15 -> #N/A | BV15: =(G15*AR15)+if(AV15=data!A$9,AO15,AN15)+AP15+BT15+G15 -> #N/A | BW15: =H15-BR15 -> #N/A | BX15: =BW15-BV15 -> #N/A
A16: =if(D16=true,if(F16=data!A$1,data!A$10,data!A$11),) | B16: =AV16 -> FBS | C16: Название товара | D16: FALSE | E16: Имя | F16: {=IF(D16=TRUE,IF(IF(BG$3=VLOOKUP(AT16,{'▶️ Инструкция'!C:C,'▶️ Инструкция'!G:G},2,FALSE),BG16,BH16)>VLOOKUP(AT16,{'▶️ Инструкция'!C:C,'▶️ Инструкция'!N:N},2,FALSE),data!A$1,data!A$2),)} | G16: 0 | H16: 1000 | I16: 0 | J16: 0 | K16: =IF($D16,"🔒",) | L16: 0 | M16: Лопатки игрушечные | N16: =IFERROR(__xludf.DUMMYFUNCTION("ArrayFormula(let(category,VLOOKUP($M16, {'📄 Комиссии'!$C:$C , '📄 Комиссии'!$B:$B}, 2, 0), data,MATCH('🔒 Доп. информация'!$J$15:$J203,TRANSPOSE(SPLIT(INDEX('▶️ Инструкция'!$Q:$Q,MATCH($AT16,'▶️ Инструкция'!$R:$R,0)+2),"", "",FALSE)),0), options,COUNTA( "&"ifna( FILTER('🔒 Доп. информация'!$J$15:$J203,('🔒 Доп. информация'!$N$15:$N203=FALSE)*data*('🔒 Доп. информация'!$O$15:$O203=""Опция"")))), commission,VLOOKUP($M16,'📄 Комиссии'!$C:$E,IF($AV16=data!A$8,2,3),0), IF(NOT(ISBLANK($M16)),commission/100+ IFERR"&"OR(VLOOKUP($AT16,{'▶️ Инструкция'!$R:$R,'▶️ Инструкция'!$AK:$AK},2,0)+ IF((( category = ""Одежда"")+( category = ""Обувь"" ))*((options+SUM( ifna( FILTER('🔒 Доп. информация'!$M$15:$M203,('🔒 Доп. информация'!$N$15:$N203=FALSE)*data*('🔒 Доп. информация'!"&"$O$15:$O203=""Пакет"")))))>=5), -5% + 2%, IF((options>=1)* (COUNTA( ifna( FILTER('🔒 Доп. информация'!$J$15:$J203,('🔒 Доп. информация'!$N$15:$N203=FALSE)*data*('🔒 Доп. информация'!$O$15:$O203=""Пакет""))))>=1)* (commission>=14.5)* (category<> ""Одежда"&""")*( category <> ""Обувь"" ),-3% + 2%,0))))))"),0.32) -> 0.32 | O16: =IF($D16,"🔒",) | Q16: =IF($D16,"🔒",) | S16: Макс. из наших | T16: Короб | U16: 1 | V16: =IF($D16,"🔒",) | W16: =IF($D16,"🔒",) | X16: =IF($D16,"🔒",) | Y16: =IF($D16,"🔒",) | Z16: 0 | AA16: =1.7*(1+AJ16)*Z16 -> 0 | AB16: =IF($D16,"🔒",) | AC16: =IF($D16,"🔒",) | AD16: =IF($D16,"🔒",) | AE16: 30 | AF16: 0 | AG16: 0 | AH16: 0 | AI16: =(AF16*AG16*AH16)/1000 -> 0 | AJ16: =if(AI16>1,(AI16-1),0) -> 0 | AK16: =IF($D16,"🔒",) | AL16: {=H16*(1-I16)*VLOOKUP(AT16,{'▶️ Инструкция'!C:C,'▶️ Инструкция'!AI:AI},2,false)} -> #N/A | AM16: =IF($D16,"🔒",) | AN16: 0 | AO16: 0 | AP16: 0 | AQ16: 1 | AR16: 0 | AS16: 0 | AT16: ИП Иванов И.И. | AU16: WB | AV16: FBS | AW16: =AS16*H16 -> 0 | AX16: =(1/(AQ16))*H16*AS16 -> 0 | AY16: =AX16/BC16 -> #N/A | AZ16: 250 | BA16: =AZ16/H16 -> 0.25 | BB16: =H16-AW16 -> 1000 | BC16: =BX16 -> #N/A | BD16: =BC16*L16 -> #N/A | BE16: =H16*(1-I16)*L16 -> 0 | BF16: =IFERROR(BC16/BV16,) | BG16: =IFERROR(BC16/H16,) | BH16: =IFERROR(if(BW16>0,BC16/BW16,-BC16/BW16),) | BJ16: =IFERROR(__xludf.DUMMYFUNCTION("IF(AU16=data!A$5, IF(AV16=data!A$8, IF(T16=data!A$3, VLOOKUP(S16,filter('🔒 Доп. информация'!D:H,'🔒 Доп. информация'!C:C=T16),4,FALSE)+VLOOKUP(S16,filter('🔒 Доп. информация'!D:H,'🔒 Доп. информация'!C:C=T16),5,FALSE)*AJ16, IF(AND(MAX(AF16:AH16)<80,SUM(A"&"F16:AH16)<=160,AI16<20,XLOOKUP(M16,'📄 Комиссии'!C:C,'📄 Комиссии'!B:B)<>""Продукты""), VLOOKUP(S16,filter('🔒 Доп. информация'!D:H,'🔒 Доп. информация'!C:C=data!$A$3),4,FALSE)+VLOOKUP(S16,filter('🔒 Доп. информация'!D:H,'🔒 Доп. информация'!C:C=data!$A$3"&"),5,FALSE)*AJ16, VLOOKUP(S16,filter('🔒 Доп. информация'!D:H,'🔒 Доп. информация'!C:C=T16),4,FALSE)*ROUNDUP(AF16*AG16*AH16*L16/(120*80*175))/L16) ) *(AE16/2) ,) ,)*0"),0.0) -> 0 | BK16: =IFERROR(__xludf.DUMMYFUNCTION("IF(AU16=data!A$5, IF(AI16<=1,IF(AI16<=0.8,IF(AI16<=0.6,IF(AI16<=0.4,IF(AI16<=0.2,23,26),29),30),32)*VLOOKUP(S16,filter('🔒 Доп. информация'!D:E,'🔒 Доп. информация'!C:C=T16),2,FALSE)/'🔒 Доп. информация'!$K$9, IF(AV16=data!A$8,U16,1)*VLOOKUP(S16,filter('"&"🔒 Доп. информация'!D:E,'🔒 Доп. информация'!C:C=T16),2,FALSE)+ IF(AV16=data!A$8,U16,1)*VLOOKUP(S16,filter('🔒 Доп. информация'!D:F,'🔒 Доп. информация'!C:C=T16),3,FALSE)*AJ16) ,0)"),69.0) -> 69 | BL16: =IF($D16,"🔒",) | BM16: =IF($D16,"🔒",) | BN16: =VLOOKUP(T16,'🔒 Доп. информация'!J:P,7,false) -> 50 | BO16: =IF(AV16=data!A$9, (AA16+AO16+AP16+BJ16+BK16+BN16)+H16*AS16, (BJ16+BK16+BN16)+H16*AS16 ) -> 119 | BP16: =AA16+BJ16+BK16 -> 69 | BQ16: =H16*N16 -> 320 | BR16: =BP16+BQ16+AS16*H16+((1-AQ16)/AQ16)*BO16+AL16+H16*J16*1.1 -> #N/A | BS16: {=IF(VLOOKUP(AT16,{'▶️ Инструкция'!C:C,'▶️ Инструкция'!Y:Y},2,FALSE)=data!A$15, H16*(1-I16), (H16-BR16)) *VLOOKUP(AT16,{'▶️ Инструкция'!C:C,'▶️ Инструкция'!AD:AD},2,FALSE)/(1+VLOOKUP(AT16,{'▶️ Инструкция'!C:C,'▶️ Инструкция'!AD:AD},2,FALSE))} -> #N/A | BT16: {=IF(VLOOKUP(AT16,{'▶️ Инструкция'!C:C,'▶️ Инструкция'!Y:Y},2,FALSE)=data!A$15, H16*(1-I16)-BS16, (H16-BR16-BS16)) * VLOOKUP(AT16,{'▶️ Инструкция'!C:C,'▶️ Инструкция'!R:R},2,FALSE) +BS16} -> #N/A | BU16: =(G16*AR16)+if(AV16=data!A$9,AO16,AN16)+AP16+BR16+BT16 -> #N/A | BV16: =(G16*AR16)+if(AV16=data!A$9,AO16,AN16)+AP16+BT16+G16 -> #N/A | BW16: =H16-BR16 -> #N/A | BX16: =BW16-BV16 -> #N/A
A17: =if(D17=true,if(F17=data!A$1,data!A$10,data!A$11),) | B17: =AV17 -> FBS | C17: Название товара | D17: FALSE | E17: Имя | F17: {=IF(D17=TRUE,IF(IF(BG$3=VLOOKUP(AT17,{'▶️ Инструкция'!C:C,'▶️ Инструкция'!G:G},2,FALSE),BG17,BH17)>VLOOKUP(AT17,{'▶️ Инструкция'!C:C,'▶️ Инструкция'!N:N},2,FALSE),data!A$1,data!A$2),)} | G17: 0 | H17: 1000 | I17: 0 | J17: 0 | K17: =IF($D17,"🔒",) | L17: 0 | M17: Лопатки игрушечные | N17: =IFERROR(__xludf.DUMMYFUNCTION("ArrayFormula(let(category,VLOOKUP($M17, {'📄 Комиссии'!$C:$C , '📄 Комиссии'!$B:$B}, 2, 0), data,MATCH('🔒 Доп. информация'!$J$15:$J203,TRANSPOSE(SPLIT(INDEX('▶️ Инструкция'!$Q:$Q,MATCH($AT17,'▶️ Инструкция'!$R:$R,0)+2),"", "",FALSE)),0), options,COUNTA( "&"ifna( FILTER('🔒 Доп. информация'!$J$15:$J203,('🔒 Доп. информация'!$N$15:$N203=FALSE)*data*('🔒 Доп. информация'!$O$15:$O203=""Опция"")))), commission,VLOOKUP($M17,'📄 Комиссии'!$C:$E,IF($AV17=data!A$8,2,3),0), IF(NOT(ISBLANK($M17)),commission/100+ IFERR"&"OR(VLOOKUP($AT17,{'▶️ Инструкция'!$R:$R,'▶️ Инструкция'!$AK:$AK},2,0)+ IF((( category = ""Одежда"")+( category = ""Обувь"" ))*((options+SUM( ifna( FILTER('🔒 Доп. информация'!$M$15:$M203,('🔒 Доп. информация'!$N$15:$N203=FALSE)*data*('🔒 Доп. информация'!"&"$O$15:$O203=""Пакет"")))))>=5), -5% + 2%, IF((options>=1)* (COUNTA( ifna( FILTER('🔒 Доп. информация'!$J$15:$J203,('🔒 Доп. информация'!$N$15:$N203=FALSE)*data*('🔒 Доп. информация'!$O$15:$O203=""Пакет""))))>=1)* (commission>=14.5)* (category<> ""Одежда"&""")*( category <> ""Обувь"" ),-3% + 2%,0))))))"),0.32) -> 0.32 | O17: =IF($D17,"🔒",) | Q17: =IF($D17,"🔒",) | S17: Макс. из наших | T17: Короб | U17: 1 | V17: =IF($D17,"🔒",) | W17: =IF($D17,"🔒",) | X17: =IF($D17,"🔒",) | Y17: =IF($D17,"🔒",) | Z17: 0 | AA17: =1.7*(1+AJ17)*Z17 -> 0 | AB17: =IF($D17,"🔒",) | AC17: =IF($D17,"🔒",) | AD17: =IF($D17,"🔒",) | AE17: 30 | AF17: 0 | AG17: 0 | AH17: 0 | AI17: =(AF17*AG17*AH17)/1000 -> 0 | AJ17: =if(AI17>1,(AI17-1),0) -> 0 | AK17: =IF($D17,"🔒",) | AL17: {=H17*(1-I17)*VLOOKUP(AT17,{'▶️ Инструкция'!C:C,'▶️ Инструкция'!AI:AI},2,false)} -> #N/A | AM17: =IF($D17,"🔒",) | AN17: 0 | AO17: 0 | AP17: 0 | AQ17: 1 | AR17: 0 | AS17: 0 | AT17: ИП Иванов И.И. | AU17: WB | AV17: FBS | AW17: =AS17*H17 -> 0 | AX17: =(1/(AQ17))*H17*AS17 -> 0 | AY17: =AX17/BC17 -> #N/A | AZ17: 250 | BA17: =AZ17/H17 -> 0.25 | BB17: =H17-AW17 -> 1000 | BC17: =BX17 -> #N/A | BD17: =BC17*L17 -> #N/A | BE17: =H17*(1-I17)*L17 -> 0 | BF17: =IFERROR(BC17/BV17,) | BG17: =IFERROR(BC17/H17,) | BH17: =IFERROR(if(BW17>0,BC17/BW17,-BC17/BW17),) | BJ17: =IFERROR(__xludf.DUMMYFUNCTION("IF(AU17=data!A$5, IF(AV17=data!A$8, IF(T17=data!A$3, VLOOKUP(S17,filter('🔒 Доп. информация'!D:H,'🔒 Доп. информация'!C:C=T17),4,FALSE)+VLOOKUP(S17,filter('🔒 Доп. информация'!D:H,'🔒 Доп. информация'!C:C=T17),5,FALSE)*AJ17, IF(AND(MAX(AF17:AH17)<80,SUM(A"&"F17:AH17)<=160,AI17<20,XLOOKUP(M17,'📄 Комиссии'!C:C,'📄 Комиссии'!B:B)<>""Продукты""), VLOOKUP(S17,filter('🔒 Доп. информация'!D:H,'🔒 Доп. информация'!C:C=data!$A$3),4,FALSE)+VLOOKUP(S17,filter('🔒 Доп. информация'!D:H,'🔒 Доп. информация'!C:C=data!$A$3"&"),5,FALSE)*AJ17, VLOOKUP(S17,filter('🔒 Доп. информация'!D:H,'🔒 Доп. информация'!C:C=T17),4,FALSE)*ROUNDUP(AF17*AG17*AH17*L17/(120*80*175))/L17) ) *(AE17/2) ,) ,)*0"),0.0) -> 0 | BK17: =IFERROR(__xludf.DUMMYFUNCTION("IF(AU17=data!A$5, IF(AI17<=1,IF(AI17<=0.8,IF(AI17<=0.6,IF(AI17<=0.4,IF(AI17<=0.2,23,26),29),30),32)*VLOOKUP(S17,filter('🔒 Доп. информация'!D:E,'🔒 Доп. информация'!C:C=T17),2,FALSE)/'🔒 Доп. информация'!$K$9, IF(AV17=data!A$8,U17,1)*VLOOKUP(S17,filter('"&"🔒 Доп. информация'!D:E,'🔒 Доп. информация'!C:C=T17),2,FALSE)+ IF(AV17=data!A$8,U17,1)*VLOOKUP(S17,filter('🔒 Доп. информация'!D:F,'🔒 Доп. информация'!C:C=T17),3,FALSE)*AJ17) ,0)"),69.0) -> 69 | BL17: =IF($D17,"🔒",) | BM17: =IF($D17,"🔒",) | BN17: =VLOOKUP(T17,'🔒 Доп. информация'!J:P,7,false) -> 50 | BO17: =IF(AV17=data!A$9, (AA17+AO17+AP17+BJ17+BK17+BN17)+H17*AS17, (BJ17+BK17+BN17)+H17*AS17 ) -> 119 | BP17: =AA17+BJ17+BK17 -> 69 | BQ17: =H17*N17 -> 320 | BR17: =BP17+BQ17+AS17*H17+((1-AQ17)/AQ17)*BO17+AL17+H17*J17*1.1 -> #N/A | BS17: {=IF(VLOOKUP(AT17,{'▶️ Инструкция'!C:C,'▶️ Инструкция'!Y:Y},2,FALSE)=data!A$15, H17*(1-I17), (H17-BR17)) *VLOOKUP(AT17,{'▶️ Инструкция'!C:C,'▶️ Инструкция'!AD:AD},2,FALSE)/(1+VLOOKUP(AT17,{'▶️ Инструкция'!C:C,'▶️ Инструкция'!AD:AD},2,FALSE))} -> #N/A | BT17: {=IF(VLOOKUP(AT17,{'▶️ Инструкция'!C:C,'▶️ Инструкция'!Y:Y},2,FALSE)=data!A$15, H17*(1-I17)-BS17, (H17-BR17-BS17)) * VLOOKUP(AT17,{'▶️ Инструкция'!C:C,'▶️ Инструкция'!R:R},2,FALSE) +BS17} -> #N/A | BU17: =(G17*AR17)+if(AV17=data!A$9,AO17,AN17)+AP17+BR17+BT17 -> #N/A | BV17: =(G17*AR17)+if(AV17=data!A$9,AO17,AN17)+AP17+BT17+G17 -> #N/A | BW17: =H17-BR17 -> #N/A | BX17: =BW17-BV17 -> #N/A
A18: =if(D18=true,if(F18=data!A$1,data!A$10,data!A$11),) | B18: =AV18 -> FBS | C18: Название товара | D18: FALSE | E18: Имя | F18: {=IF(D18=TRUE,IF(IF(BG$3=VLOOKUP(AT18,{'▶️ Инструкция'!C:C,'▶️ Инструкция'!G:G},2,FALSE),BG18,BH18)>VLOOKUP(AT18,{'▶️ Инструкция'!C:C,'▶️ Инструкция'!N:N},2,FALSE),data!A$1,data!A$2),)} | G18: 0 | H18: 1000 | I18: 0 | J18: 0 | K18: =IF($D18,"🔒",) | L18: 0 | M18: Лопатки игрушечные | N18: =IFERROR(__xludf.DUMMYFUNCTION("ArrayFormula(let(category,VLOOKUP($M18, {'📄 Комиссии'!$C:$C , '📄 Комиссии'!$B:$B}, 2, 0), data,MATCH('🔒 Доп. информация'!$J$15:$J203,TRANSPOSE(SPLIT(INDEX('▶️ Инструкция'!$Q:$Q,MATCH($AT18,'▶️ Инструкция'!$R:$R,0)+2),"", "",FALSE)),0), options,COUNTA( "&"ifna( FILTER('🔒 Доп. информация'!$J$15:$J203,('🔒 Доп. информация'!$N$15:$N203=FALSE)*data*('🔒 Доп. информация'!$O$15:$O203=""Опция"")))), commission,VLOOKUP($M18,'📄 Комиссии'!$C:$E,IF($AV18=data!A$8,2,3),0), IF(NOT(ISBLANK($M18)),commission/100+ IFERR"&"OR(VLOOKUP($AT18,{'▶️ Инструкция'!$R:$R,'▶️ Инструкция'!$AK:$AK},2,0)+ IF((( category = ""Одежда"")+( category = ""Обувь"" ))*((options+SUM( ifna( FILTER('🔒 Доп. информация'!$M$15:$M203,('🔒 Доп. информация'!$N$15:$N203=FALSE)*data*('🔒 Доп. информация'!"&"$O$15:$O203=""Пакет"")))))>=5), -5% + 2%, IF((options>=1)* (COUNTA( ifna( FILTER('🔒 Доп. информация'!$J$15:$J203,('🔒 Доп. информация'!$N$15:$N203=FALSE)*data*('🔒 Доп. информация'!$O$15:$O203=""Пакет""))))>=1)* (commission>=14.5)* (category<> ""Одежда"&""")*( category <> ""Обувь"" ),-3% + 2%,0))))))"),0.32) -> 0.32 | O18: =IF($D18,"🔒",) | Q18: =IF($D18,"🔒",) | S18: Макс. из наших | T18: Короб | U18: 1 | V18: =IF($D18,"🔒",) | W18: =IF($D18,"🔒",) | X18: =IF($D18,"🔒",) | Y18: =IF($D18,"🔒",) | Z18: 0 | AA18: =1.7*(1+AJ18)*Z18 -> 0 | AB18: =IF($D18,"🔒",) | AC18: =IF($D18,"🔒",) | AD18: =IF($D18,"🔒",) | AE18: 30 | AF18: 0 | AG18: 0 | AH18: 0 | AI18: =(AF18*AG18*AH18)/1000 -> 0 | AJ18: =if(AI18>1,(AI18-1),0) -> 0 | AK18: =IF($D18,"🔒",) | AL18: {=H18*(1-I18)*VLOOKUP(AT18,{'▶️ Инструкция'!C:C,'▶️ Инструкция'!AI:AI},2,false)} -> #N/A | AM18: =IF($D18,"🔒",) | AN18: 0 | AO18: 0 | AP18: 0 | AQ18: 1 | AR18: 0 | AS18: 0 | AT18: ИП Иванов И.И. | AU18: WB | AV18: FBS | AW18: =AS18*H18 -> 0 | AX18: =(1/(AQ18))*H18*AS18 -> 0 | AY18: =AX18/BC18 -> #N/A | AZ18: 250 | BA18: =AZ18/H18 -> 0.25 | BB18: =H18-AW18 -> 1000 | BC18: =BX18 -> #N/A | BD18: =BC18*L18 -> #N/A | BE18: =H18*(1-I18)*L18 -> 0 | BF18: =IFERROR(BC18/BV18,) | BG18: =IFERROR(BC18/H18,) | BH18: =IFERROR(if(BW18>0,BC18/BW18,-BC18/BW18),) | BJ18: =IFERROR(__xludf.DUMMYFUNCTION("IF(AU18=data!A$5, IF(AV18=data!A$8, IF(T18=data!A$3, VLOOKUP(S18,filter('🔒 Доп. информация'!D:H,'🔒 Доп. информация'!C:C=T18),4,FALSE)+VLOOKUP(S18,filter('🔒 Доп. информация'!D:H,'🔒 Доп. информация'!C:C=T18),5,FALSE)*AJ18, IF(AND(MAX(AF18:AH18)<80,SUM(A"&"F18:AH18)<=160,AI18<20,XLOOKUP(M18,'📄 Комиссии'!C:C,'📄 Комиссии'!B:B)<>""Продукты""), VLOOKUP(S18,filter('🔒 Доп. информация'!D:H,'🔒 Доп. информация'!C:C=data!$A$3),4,FALSE)+VLOOKUP(S18,filter('🔒 Доп. информация'!D:H,'🔒 Доп. информация'!C:C=data!$A$3"&"),5,FALSE)*AJ18, VLOOKUP(S18,filter('🔒 Доп. информация'!D:H,'🔒 Доп. информация'!C:C=T18),4,FALSE)*ROUNDUP(AF18*AG18*AH18*L18/(120*80*175))/L18) ) *(AE18/2) ,) ,)*0"),0.0) -> 0 | BK18: =IFERROR(__xludf.DUMMYFUNCTION("IF(AU18=data!A$5, IF(AI18<=1,IF(AI18<=0.8,IF(AI18<=0.6,IF(AI18<=0.4,IF(AI18<=0.2,23,26),29),30),32)*VLOOKUP(S18,filter('🔒 Доп. информация'!D:E,'🔒 Доп. информация'!C:C=T18),2,FALSE)/'🔒 Доп. информация'!$K$9, IF(AV18=data!A$8,U18,1)*VLOOKUP(S18,filter('"&"🔒 Доп. информация'!D:E,'🔒 Доп. информация'!C:C=T18),2,FALSE)+ IF(AV18=data!A$8,U18,1)*VLOOKUP(S18,filter('🔒 Доп. информация'!D:F,'🔒 Доп. информация'!C:C=T18),3,FALSE)*AJ18) ,0)"),69.0) -> 69 | BL18: =IF($D18,"🔒",) | BM18: =IF($D18,"🔒",) | BN18: =VLOOKUP(T18,'🔒 Доп. информация'!J:P,7,false) -> 50 | BO18: =IF(AV18=data!A$9, (AA18+AO18+AP18+BJ18+BK18+BN18)+H18*AS18, (BJ18+BK18+BN18)+H18*AS18 ) -> 119 | BP18: =AA18+BJ18+BK18 -> 69 | BQ18: =H18*N18 -> 320 | BR18: =BP18+BQ18+AS18*H18+((1-AQ18)/AQ18)*BO18+AL18+H18*J18*1.1 -> #N/A | BS18: {=IF(VLOOKUP(AT18,{'▶️ Инструкция'!C:C,'▶️ Инструкция'!Y:Y},2,FALSE)=data!A$15, H18*(1-I18), (H18-BR18)) *VLOOKUP(AT18,{'▶️ Инструкция'!C:C,'▶️ Инструкция'!AD:AD},2,FALSE)/(1+VLOOKUP(AT18,{'▶️ Инструкция'!C:C,'▶️ Инструкция'!AD:AD},2,FALSE))} -> #N/A | BT18: {=IF(VLOOKUP(AT18,{'▶️ Инструкция'!C:C,'▶️ Инструкция'!Y:Y},2,FALSE)=data!A$15, H18*(1-I18)-BS18, (H18-BR18-BS18)) * VLOOKUP(AT18,{'▶️ Инструкция'!C:C,'▶️ Инструкция'!R:R},2,FALSE) +BS18} -> #N/A | BU18: =(G18*AR18)+if(AV18=data!A$9,AO18,AN18)+AP18+BR18+BT18 -> #N/A | BV18: =(G18*AR18)+if(AV18=data!A$9,AO18,AN18)+AP18+BT18+G18 -> #N/A | BW18: =H18-BR18 -> #N/A | BX18: =BW18-BV18 -> #N/A
A19: =if(D19=true,if(F19=data!A$1,data!A$10,data!A$11),) | B19: =AV19 -> FBS | C19: Название товара | D19: FALSE | E19: Имя | F19: {=IF(D19=TRUE,IF(IF(BG$3=VLOOKUP(AT19,{'▶️ Инструкция'!C:C,'▶️ Инструкция'!G:G},2,FALSE),BG19,BH19)>VLOOKUP(AT19,{'▶️ Инструкция'!C:C,'▶️ Инструкция'!N:N},2,FALSE),data!A$1,data!A$2),)} | G19: 0 | H19: 1000 | I19: 0 | J19: 0 | K19: =IF($D19,"🔒",) | L19: 0 | M19: Лопатки игрушечные | N19: =IFERROR(__xludf.DUMMYFUNCTION("ArrayFormula(let(category,VLOOKUP($M19, {'📄 Комиссии'!$C:$C , '📄 Комиссии'!$B:$B}, 2, 0), data,MATCH('🔒 Доп. информация'!$J$15:$J203,TRANSPOSE(SPLIT(INDEX('▶️ Инструкция'!$Q:$Q,MATCH($AT19,'▶️ Инструкция'!$R:$R,0)+2),"", "",FALSE)),0), options,COUNTA( "&"ifna( FILTER('🔒 Доп. информация'!$J$15:$J203,('🔒 Доп. информация'!$N$15:$N203=FALSE)*data*('🔒 Доп. информация'!$O$15:$O203=""Опция"")))), commission,VLOOKUP($M19,'📄 Комиссии'!$C:$E,IF($AV19=data!A$8,2,3),0), IF(NOT(ISBLANK($M19)),commission/100+ IFERR"&"OR(VLOOKUP($AT19,{'▶️ Инструкция'!$R:$R,'▶️ Инструкция'!$AK:$AK},2,0)+ IF((( category = ""Одежда"")+( category = ""Обувь"" ))*((options+SUM( ifna( FILTER('🔒 Доп. информация'!$M$15:$M203,('🔒 Доп. информация'!$N$15:$N203=FALSE)*data*('🔒 Доп. информация'!"&"$O$15:$O203=""Пакет"")))))>=5), -5% + 2%, IF((options>=1)* (COUNTA( ifna( FILTER('🔒 Доп. информация'!$J$15:$J203,('🔒 Доп. информация'!$N$15:$N203=FALSE)*data*('🔒 Доп. информация'!$O$15:$O203=""Пакет""))))>=1)* (commission>=14.5)* (category<> ""Одежда"&""")*( category <> ""Обувь"" ),-3% + 2%,0))))))"),0.32) -> 0.32 | O19: =IF($D19,"🔒",) | Q19: =IF($D19,"🔒",) | S19: Макс. из наших | T19: Короб | U19: 1 | V19: =IF($D19,"🔒",) | W19: =IF($D19,"🔒",) | X19: =IF($D19,"🔒",) | Y19: =IF($D19,"🔒",) | Z19: 0 | AA19: =1.7*(1+AJ19)*Z19 -> 0 | AB19: =IF($D19,"🔒",) | AC19: =IF($D19,"🔒",) | AD19: =IF($D19,"🔒",) | AE19: 30 | AF19: 0 | AG19: 0 | AH19: 0 | AI19: =(AF19*AG19*AH19)/1000 -> 0 | AJ19: =if(AI19>1,(AI19-1),0) -> 0 | AK19: =IF($D19,"🔒",) | AL19: {=H19*(1-I19)*VLOOKUP(AT19,{'▶️ Инструкция'!C:C,'▶️ Инструкция'!AI:AI},2,false)} -> #N/A | AM19: =IF($D19,"🔒",) | AN19: 0 | AO19: 0 | AP19: 0 | AQ19: 1 | AR19: 0 | AS19: 0 | AT19: ИП Иванов И.И. | AU19: WB | AV19: FBS | AW19: =AS19*H19 -> 0 | AX19: =(1/(AQ19))*H19*AS19 -> 0 | AY19: =AX19/BC19 -> #N/A | AZ19: 250 | BA19: =AZ19/H19 -> 0.25 | BB19: =H19-AW19 -> 1000 | BC19: =BX19 -> #N/A | BD19: =BC19*L19 -> #N/A | BE19: =H19*(1-I19)*L19 -> 0 | BF19: =IFERROR(BC19/BV19,) | BG19: =IFERROR(BC19/H19,) | BH19: =IFERROR(if(BW19>0,BC19/BW19,-BC19/BW19),) | BJ19: =IFERROR(__xludf.DUMMYFUNCTION("IF(AU19=data!A$5, IF(AV19=data!A$8, IF(T19=data!A$3, VLOOKUP(S19,filter('🔒 Доп. информация'!D:H,'🔒 Доп. информация'!C:C=T19),4,FALSE)+VLOOKUP(S19,filter('🔒 Доп. информация'!D:H,'🔒 Доп. информация'!C:C=T19),5,FALSE)*AJ19, IF(AND(MAX(AF19:AH19)<80,SUM(A"&"F19:AH19)<=160,AI19<20,XLOOKUP(M19,'📄 Комиссии'!C:C,'📄 Комиссии'!B:B)<>""Продукты""), VLOOKUP(S19,filter('🔒 Доп. информация'!D:H,'🔒 Доп. информация'!C:C=data!$A$3),4,FALSE)+VLOOKUP(S19,filter('🔒 Доп. информация'!D:H,'🔒 Доп. информация'!C:C=data!$A$3"&"),5,FALSE)*AJ19, VLOOKUP(S19,filter('🔒 Доп. информация'!D:H,'🔒 Доп. информация'!C:C=T19),4,FALSE)*ROUNDUP(AF19*AG19*AH19*L19/(120*80*175))/L19) ) *(AE19/2) ,) ,)*0"),0.0) -> 0 | BK19: =IFERROR(__xludf.DUMMYFUNCTION("IF(AU19=data!A$5, IF(AI19<=1,IF(AI19<=0.8,IF(AI19<=0.6,IF(AI19<=0.4,IF(AI19<=0.2,23,26),29),30),32)*VLOOKUP(S19,filter('🔒 Доп. информация'!D:E,'🔒 Доп. информация'!C:C=T19),2,FALSE)/'🔒 Доп. информация'!$K$9, IF(AV19=data!A$8,U19,1)*VLOOKUP(S19,filter('"&"🔒 Доп. информация'!D:E,'🔒 Доп. информация'!C:C=T19),2,FALSE)+ IF(AV19=data!A$8,U19,1)*VLOOKUP(S19,filter('🔒 Доп. информация'!D:F,'🔒 Доп. информация'!C:C=T19),3,FALSE)*AJ19) ,0)"),69.0) -> 69 | BL19: =IF($D19,"🔒",) | BM19: =IF($D19,"🔒",) | BN19: =VLOOKUP(T19,'🔒 Доп. информация'!J:P,7,false) -> 50 | BO19: =IF(AV19=data!A$9, (AA19+AO19+AP19+BJ19+BK19+BN19)+H19*AS19, (BJ19+BK19+BN19)+H19*AS19 ) -> 119 | BP19: =AA19+BJ19+BK19 -> 69 | BQ19: =H19*N19 -> 320 | BR19: =BP19+BQ19+AS19*H19+((1-AQ19)/AQ19)*BO19+AL19+H19*J19*1.1 -> #N/A | BS19: {=IF(VLOOKUP(AT19,{'▶️ Инструкция'!C:C,'▶️ Инструкция'!Y:Y},2,FALSE)=data!A$15, H19*(1-I19), (H19-BR19)) *VLOOKUP(AT19,{'▶️ Инструкция'!C:C,'▶️ Инструкция'!AD:AD},2,FALSE)/(1+VLOOKUP(AT19,{'▶️ Инструкция'!C:C,'▶️ Инструкция'!AD:AD},2,FALSE))} -> #N/A | BT19: {=IF(VLOOKUP(AT19,{'▶️ Инструкция'!C:C,'▶️ Инструкция'!Y:Y},2,FALSE)=data!A$15, H19*(1-I19)-BS19, (H19-BR19-BS19)) * VLOOKUP(AT19,{'▶️ Инструкция'!C:C,'▶️ Инструкция'!R:R},2,FALSE) +BS19} -> #N/A | BU19: =(G19*AR19)+if(AV19=data!A$9,AO19,AN19)+AP19+BR19+BT19 -> #N/A | BV19: =(G19*AR19)+if(AV19=data!A$9,AO19,AN19)+AP19+BT19+G19 -> #N/A | BW19: =H19-BR19 -> #N/A | BX19: =BW19-BV19 -> #N/A
A20: =if(D20=true,if(F20=data!A$1,data!A$10,data!A$11),) | B20: =AV20 -> FBS | C20: Название товара | D20: FALSE | E20: Имя | F20: {=IF(D20=TRUE,IF(IF(BG$3=VLOOKUP(AT20,{'▶️ Инструкция'!C:C,'▶️ Инструкция'!G:G},2,FALSE),BG20,BH20)>VLOOKUP(AT20,{'▶️ Инструкция'!C:C,'▶️ Инструкция'!N:N},2,FALSE),data!A$1,data!A$2),)} | G20: 0 | H20: 1000 | I20: 0 | J20: 0 | K20: =IF($D20,"🔒",) | L20: 0 | M20: Лопатки игрушечные | N20: =IFERROR(__xludf.DUMMYFUNCTION("ArrayFormula(let(category,VLOOKUP($M20, {'📄 Комиссии'!$C:$C , '📄 Комиссии'!$B:$B}, 2, 0), data,MATCH('🔒 Доп. информация'!$J$15:$J203,TRANSPOSE(SPLIT(INDEX('▶️ Инструкция'!$Q:$Q,MATCH($AT20,'▶️ Инструкция'!$R:$R,0)+2),"", "",FALSE)),0), options,COUNTA( "&"ifna( FILTER('🔒 Доп. информация'!$J$15:$J203,('🔒 Доп. информация'!$N$15:$N203=FALSE)*data*('🔒 Доп. информация'!$O$15:$O203=""Опция"")))), commission,VLOOKUP($M20,'📄 Комиссии'!$C:$E,IF($AV20=data!A$8,2,3),0), IF(NOT(ISBLANK($M20)),commission/100+ IFERR"&"OR(VLOOKUP($AT20,{'▶️ Инструкция'!$R:$R,'▶️ Инструкция'!$AK:$AK},2,0)+ IF((( category = ""Одежда"")+( category = ""Обувь"" ))*((options+SUM( ifna( FILTER('🔒 Доп. информация'!$M$15:$M203,('🔒 Доп. информация'!$N$15:$N203=FALSE)*data*('🔒 Доп. информация'!"&"$O$15:$O203=""Пакет"")))))>=5), -5% + 2%, IF((options>=1)* (COUNTA( ifna( FILTER('🔒 Доп. информация'!$J$15:$J203,('🔒 Доп. информация'!$N$15:$N203=FALSE)*data*('🔒 Доп. информация'!$O$15:$O203=""Пакет""))))>=1)* (commission>=14.5)* (category<> ""Одежда"&""")*( category <> ""Обувь"" ),-3% + 2%,0))))))"),0.32) -> 0.32 | O20: =IF($D20,"🔒",) | Q20: =IF($D20,"🔒",) | S20: Макс. из наших | T20: Короб | U20: 1 | V20: =IF($D20,"🔒",) | W20: =IF($D20,"🔒",) | X20: =IF($D20,"🔒",) | Y20: =IF($D20,"🔒",) | Z20: 0 | AA20: =1.7*(1+AJ20)*Z20 -> 0 | AB20: =IF($D20,"🔒",) | AC20: =IF($D20,"🔒",) | AD20: =IF($D20,"🔒",) | AE20: 30 | AF20: 0 | AG20: 0 | AH20: 0 | AI20: =(AF20*AG20*AH20)/1000 -> 0 | AJ20: =if(AI20>1,(AI20-1),0) -> 0 | AK20: =IF($D20,"🔒",) | AL20: {=H20*(1-I20)*VLOOKUP(AT20,{'▶️ Инструкция'!C:C,'▶️ Инструкция'!AI:AI},2,false)} -> #N/A | AM20: =IF($D20,"🔒",) | AN20: 0 | AO20: 0 | AP20: 0 | AQ20: 1 | AR20: 0 | AS20: 0 | AT20: ИП Иванов И.И. | AU20: WB | AV20: FBS | AW20: =AS20*H20 -> 0 | AX20: =(1/(AQ20))*H20*AS20 -> 0 | AY20: =AX20/BC20 -> #N/A | AZ20: 250 | BA20: =AZ20/H20 -> 0.25 | BB20: =H20-AW20 -> 1000 | BC20: =BX20 -> #N/A | BD20: =BC20*L20 -> #N/A | BE20: =H20*(1-I20)*L20 -> 0 | BF20: =IFERROR(BC20/BV20,) | BG20: =IFERROR(BC20/H20,) | BH20: =IFERROR(if(BW20>0,BC20/BW20,-BC20/BW20),) | BJ20: =IFERROR(__xludf.DUMMYFUNCTION("IF(AU20=data!A$5, IF(AV20=data!A$8, IF(T20=data!A$3, VLOOKUP(S20,filter('🔒 Доп. информация'!D:H,'🔒 Доп. информация'!C:C=T20),4,FALSE)+VLOOKUP(S20,filter('🔒 Доп. информация'!D:H,'🔒 Доп. информация'!C:C=T20),5,FALSE)*AJ20, IF(AND(MAX(AF20:AH20)<80,SUM(A"&"F20:AH20)<=160,AI20<20,XLOOKUP(M20,'📄 Комиссии'!C:C,'📄 Комиссии'!B:B)<>""Продукты""), VLOOKUP(S20,filter('🔒 Доп. информация'!D:H,'🔒 Доп. информация'!C:C=data!$A$3),4,FALSE)+VLOOKUP(S20,filter('🔒 Доп. информация'!D:H,'🔒 Доп. информация'!C:C=data!$A$3"&"),5,FALSE)*AJ20, VLOOKUP(S20,filter('🔒 Доп. информация'!D:H,'🔒 Доп. информация'!C:C=T20),4,FALSE)*ROUNDUP(AF20*AG20*AH20*L20/(120*80*175))/L20) ) *(AE20/2) ,) ,)*0"),0.0) -> 0 | BK20: =IFERROR(__xludf.DUMMYFUNCTION("IF(AU20=data!A$5, IF(AI20<=1,IF(AI20<=0.8,IF(AI20<=0.6,IF(AI20<=0.4,IF(AI20<=0.2,23,26),29),30),32)*VLOOKUP(S20,filter('🔒 Доп. информация'!D:E,'🔒 Доп. информация'!C:C=T20),2,FALSE)/'🔒 Доп. информация'!$K$9, IF(AV20=data!A$8,U20,1)*VLOOKUP(S20,filter('"&"🔒 Доп. информация'!D:E,'🔒 Доп. информация'!C:C=T20),2,FALSE)+ IF(AV20=data!A$8,U20,1)*VLOOKUP(S20,filter('🔒 Доп. информация'!D:F,'🔒 Доп. информация'!C:C=T20),3,FALSE)*AJ20) ,0)"),69.0) -> 69 | BL20: =IF($D20,"🔒",) | BM20: =IF($D20,"🔒",) | BN20: =VLOOKUP(T20,'🔒 Доп. информация'!J:P,7,false) -> 50 | BO20: =IF(AV20=data!A$9, (AA20+AO20+AP20+BJ20+BK20+BN20)+H20*AS20, (BJ20+BK20+BN20)+H20*AS20 ) -> 119 | BP20: =AA20+BJ20+BK20 -> 69 | BQ20: =H20*N20 -> 320 | BR20: =BP20+BQ20+AS20*H20+((1-AQ20)/AQ20)*BO20+AL20+H20*J20*1.1 -> #N/A | BS20: {=IF(VLOOKUP(AT20,{'▶️ Инструкция'!C:C,'▶️ Инструкция'!Y:Y},2,FALSE)=data!A$15, H20*(1-I20), (H20-BR20)) *VLOOKUP(AT20,{'▶️ Инструкция'!C:C,'▶️ Инструкция'!AD:AD},2,FALSE)/(1+VLOOKUP(AT20,{'▶️ Инструкция'!C:C,'▶️ Инструкция'!AD:AD},2,FALSE))} -> #N/A | BT20: {=IF(VLOOKUP(AT20,{'▶️ Инструкция'!C:C,'▶️ Инструкция'!Y:Y},2,FALSE)=data!A$15, H20*(1-I20)-BS20, (H20-BR20-BS20)) * VLOOKUP(AT20,{'▶️ Инструкция'!C:C,'▶️ Инструкция'!R:R},2,FALSE) +BS20} -> #N/A | BU20: =(G20*AR20)+if(AV20=data!A$9,AO20,AN20)+AP20+BR20+BT20 -> #N/A | BV20: =(G20*AR20)+if(AV20=data!A$9,AO20,AN20)+AP20+BT20+G20 -> #N/A | BW20: =H20-BR20 -> #N/A | BX20: =BW20-BV20 -> #N/A
A21: =if(D21=true,if(F21=data!A$1,data!A$10,data!A$11),) | B21: =AV21 -> FBS | C21: Название товара | D21: FALSE | E21: Имя | F21: {=IF(D21=TRUE,IF(IF(BG$3=VLOOKUP(AT21,{'▶️ Инструкция'!C:C,'▶️ Инструкция'!G:G},2,FALSE),BG21,BH21)>VLOOKUP(AT21,{'▶️ Инструкция'!C:C,'▶️ Инструкция'!N:N},2,FALSE),data!A$1,data!A$2),)} | G21: 0 | H21: 1000 | I21: 0 | J21: 0 | K21: =IF($D21,"🔒",) | L21: 0 | M21: Лопатки игрушечные | N21: =IFERROR(__xludf.DUMMYFUNCTION("ArrayFormula(let(category,VLOOKUP($M21, {'📄 Комиссии'!$C:$C , '📄 Комиссии'!$B:$B}, 2, 0), data,MATCH('🔒 Доп. информация'!$J$15:$J203,TRANSPOSE(SPLIT(INDEX('▶️ Инструкция'!$Q:$Q,MATCH($AT21,'▶️ Инструкция'!$R:$R,0)+2),"", "",FALSE)),0), options,COUNTA( "&"ifna( FILTER('🔒 Доп. информация'!$J$15:$J203,('🔒 Доп. информация'!$N$15:$N203=FALSE)*data*('🔒 Доп. информация'!$O$15:$O203=""Опция"")))), commission,VLOOKUP($M21,'📄 Комиссии'!$C:$E,IF($AV21=data!A$8,2,3),0), IF(NOT(ISBLANK($M21)),commission/100+ IFERR"&"OR(VLOOKUP($AT21,{'▶️ Инструкция'!$R:$R,'▶️ Инструкция'!$AK:$AK},2,0)+ IF((( category = ""Одежда"")+( category = ""Обувь"" ))*((options+SUM( ifna( FILTER('🔒 Доп. информация'!$M$15:$M203,('🔒 Доп. информация'!$N$15:$N203=FALSE)*data*('🔒 Доп. информация'!"&"$O$15:$O203=""Пакет"")))))>=5), -5% + 2%, IF((options>=1)* (COUNTA( ifna( FILTER('🔒 Доп. информация'!$J$15:$J203,('🔒 Доп. информация'!$N$15:$N203=FALSE)*data*('🔒 Доп. информация'!$O$15:$O203=""Пакет""))))>=1)* (commission>=14.5)* (category<> ""Одежда"&""")*( category <> ""Обувь"" ),-3% + 2%,0))))))"),0.32) -> 0.32 | O21: =IF($D21,"🔒",) | Q21: =IF($D21,"🔒",) | S21: Макс. из наших | T21: Короб | U21: 1 | V21: =IF($D21,"🔒",) | W21: =IF($D21,"🔒",) | X21: =IF($D21,"🔒",) | Y21: =IF($D21,"🔒",) | Z21: 0 | AA21: =1.7*(1+AJ21)*Z21 -> 0 | AB21: =IF($D21,"🔒",) | AC21: =IF($D21,"🔒",) | AD21: =IF($D21,"🔒",) | AE21: 30 | AF21: 0 | AG21: 0 | AH21: 0 | AI21: =(AF21*AG21*AH21)/1000 -> 0 | AJ21: =if(AI21>1,(AI21-1),0) -> 0 | AK21: =IF($D21,"🔒",) | AL21: {=H21*(1-I21)*VLOOKUP(AT21,{'▶️ Инструкция'!C:C,'▶️ Инструкция'!AI:AI},2,false)} -> #N/A | AM21: =IF($D21,"🔒",) | AN21: 0 | AO21: 0 | AP21: 0 | AQ21: 1 | AR21: 0 | AS21: 0 | AT21: ИП Иванов И.И. | AU21: WB | AV21: FBS | AW21: =AS21*H21 -> 0 | AX21: =(1/(AQ21))*H21*AS21 -> 0 | AY21: =AX21/BC21 -> #N/A | AZ21: 250 | BA21: =AZ21/H21 -> 0.25 | BB21: =H21-AW21 -> 1000 | BC21: =BX21 -> #N/A | BD21: =BC21*L21 -> #N/A | BE21: =H21*(1-I21)*L21 -> 0 | BF21: =IFERROR(BC21/BV21,) | BG21: =IFERROR(BC21/H21,) | BH21: =IFERROR(if(BW21>0,BC21/BW21,-BC21/BW21),) | BJ21: =IFERROR(__xludf.DUMMYFUNCTION("IF(AU21=data!A$5, IF(AV21=data!A$8, IF(T21=data!A$3, VLOOKUP(S21,filter('🔒 Доп. информация'!D:H,'🔒 Доп. информация'!C:C=T21),4,FALSE)+VLOOKUP(S21,filter('🔒 Доп. информация'!D:H,'🔒 Доп. информация'!C:C=T21),5,FALSE)*AJ21, IF(AND(MAX(AF21:AH21)<80,SUM(A"&"F21:AH21)<=160,AI21<20,XLOOKUP(M21,'📄 Комиссии'!C:C,'📄 Комиссии'!B:B)<>""Продукты""), VLOOKUP(S21,filter('🔒 Доп. информация'!D:H,'🔒 Доп. информация'!C:C=data!$A$3),4,FALSE)+VLOOKUP(S21,filter('🔒 Доп. информация'!D:H,'🔒 Доп. информация'!C:C=data!$A$3"&"),5,FALSE)*AJ21, VLOOKUP(S21,filter('🔒 Доп. информация'!D:H,'🔒 Доп. информация'!C:C=T21),4,FALSE)*ROUNDUP(AF21*AG21*AH21*L21/(120*80*175))/L21) ) *(AE21/2) ,) ,)*0"),0.0) -> 0 | BK21: =IFERROR(__xludf.DUMMYFUNCTION("IF(AU21=data!A$5, IF(AI21<=1,IF(AI21<=0.8,IF(AI21<=0.6,IF(AI21<=0.4,IF(AI21<=0.2,23,26),29),30),32)*VLOOKUP(S21,filter('🔒 Доп. информация'!D:E,'🔒 Доп. информация'!C:C=T21),2,FALSE)/'🔒 Доп. информация'!$K$9, IF(AV21=data!A$8,U21,1)*VLOOKUP(S21,filter('"&"🔒 Доп. информация'!D:E,'🔒 Доп. информация'!C:C=T21),2,FALSE)+ IF(AV21=data!A$8,U21,1)*VLOOKUP(S21,filter('🔒 Доп. информация'!D:F,'🔒 Доп. информация'!C:C=T21),3,FALSE)*AJ21) ,0)"),69.0) -> 69 | BL21: =IF($D21,"🔒",) | BM21: =IF($D21,"🔒",) | BN21: =VLOOKUP(T21,'🔒 Доп. информация'!J:P,7,false) -> 50 | BO21: =IF(AV21=data!A$9, (AA21+AO21+AP21+BJ21+BK21+BN21)+H21*AS21, (BJ21+BK21+BN21)+H21*AS21 ) -> 119 | BP21: =AA21+BJ21+BK21 -> 69 | BQ21: =H21*N21 -> 320 | BR21: =BP21+BQ21+AS21*H21+((1-AQ21)/AQ21)*BO21+AL21+H21*J21*1.1 -> #N/A | BS21: {=IF(VLOOKUP(AT21,{'▶️ Инструкция'!C:C,'▶️ Инструкция'!Y:Y},2,FALSE)=data!A$15, H21*(1-I21), (H21-BR21)) *VLOOKUP(AT21,{'▶️ Инструкция'!C:C,'▶️ Инструкция'!AD:AD},2,FALSE)/(1+VLOOKUP(AT21,{'▶️ Инструкция'!C:C,'▶️ Инструкция'!AD:AD},2,FALSE))} -> #N/A | BT21: {=IF(VLOOKUP(AT21,{'▶️ Инструкция'!C:C,'▶️ Инструкция'!Y:Y},2,FALSE)=data!A$15, H21*(1-I21)-BS21, (H21-BR21-BS21)) * VLOOKUP(AT21,{'▶️ Инструкция'!C:C,'▶️ Инструкция'!R:R},2,FALSE) +BS21} -> #N/A | BU21: =(G21*AR21)+if(AV21=data!A$9,AO21,AN21)+AP21+BR21+BT21 -> #N/A | BV21: =(G21*AR21)+if(AV21=data!A$9,AO21,AN21)+AP21+BT21+G21 -> #N/A | BW21: =H21-BR21 -> #N/A | BX21: =BW21-BV21 -> #N/A
A22: =if(D22=true,if(F22=data!A$1,data!A$10,data!A$11),) | B22: =AV22 -> FBS | C22: Название товара | D22: FALSE | E22: Имя | F22: {=IF(D22=TRUE,IF(IF(BG$3=VLOOKUP(AT22,{'▶️ Инструкция'!C:C,'▶️ Инструкция'!G:G},2,FALSE),BG22,BH22)>VLOOKUP(AT22,{'▶️ Инструкция'!C:C,'▶️ Инструкция'!N:N},2,FALSE),data!A$1,data!A$2),)} | G22: 0 | H22: 1000 | I22: 0 | J22: 0 | K22: =IF($D22,"🔒",) | L22: 0 | M22: Лопатки игрушечные | N22: =IFERROR(__xludf.DUMMYFUNCTION("ArrayFormula(let(category,VLOOKUP($M22, {'📄 Комиссии'!$C:$C , '📄 Комиссии'!$B:$B}, 2, 0), data,MATCH('🔒 Доп. информация'!$J$15:$J203,TRANSPOSE(SPLIT(INDEX('▶️ Инструкция'!$Q:$Q,MATCH($AT22,'▶️ Инструкция'!$R:$R,0)+2),"", "",FALSE)),0), options,COUNTA( "&"ifna( FILTER('🔒 Доп. информация'!$J$15:$J203,('🔒 Доп. информация'!$N$15:$N203=FALSE)*data*('🔒 Доп. информация'!$O$15:$O203=""Опция"")))), commission,VLOOKUP($M22,'📄 Комиссии'!$C:$E,IF($AV22=data!A$8,2,3),0), IF(NOT(ISBLANK($M22)),commission/100+ IFERR"&"OR(VLOOKUP($AT22,{'▶️ Инструкция'!$R:$R,'▶️ Инструкция'!$AK:$AK},2,0)+ IF((( category = ""Одежда"")+( category = ""Обувь"" ))*((options+SUM( ifna( FILTER('🔒 Доп. информация'!$M$15:$M203,('🔒 Доп. информация'!$N$15:$N203=FALSE)*data*('🔒 Доп. информация'!"&"$O$15:$O203=""Пакет"")))))>=5), -5% + 2%, IF((options>=1)* (COUNTA( ifna( FILTER('🔒 Доп. информация'!$J$15:$J203,('🔒 Доп. информация'!$N$15:$N203=FALSE)*data*('🔒 Доп. информация'!$O$15:$O203=""Пакет""))))>=1)* (commission>=14.5)* (category<> ""Одежда"&""")*( category <> ""Обувь"" ),-3% + 2%,0))))))"),0.32) -> 0.32 | O22: =IF($D22,"🔒",) | Q22: =IF($D22,"🔒",) | S22: Макс. из наших | T22: Короб | U22: 1 | V22: =IF($D22,"🔒",) | W22: =IF($D22,"🔒",) | X22: =IF($D22,"🔒",) | Y22: =IF($D22,"🔒",) | Z22: 0 | AA22: =1.7*(1+AJ22)*Z22 -> 0 | AB22: =IF($D22,"🔒",) | AC22: =IF($D22,"🔒",) | AD22: =IF($D22,"🔒",) | AE22: 30 | AF22: 0 | AG22: 0 | AH22: 0 | AI22: =(AF22*AG22*AH22)/1000 -> 0 | AJ22: =if(AI22>1,(AI22-1),0) -> 0 | AK22: =IF($D22,"🔒",) | AL22: {=H22*(1-I22)*VLOOKUP(AT22,{'▶️ Инструкция'!C:C,'▶️ Инструкция'!AI:AI},2,false)} -> #N/A | AM22: =IF($D22,"🔒",) | AN22: 0 | AO22: 0 | AP22: 0 | AQ22: 1 | AR22: 0 | AS22: 0 | AT22: ИП Иванов И.И. | AU22: WB | AV22: FBS | AW22: =AS22*H22 -> 0 | AX22: =(1/(AQ22))*H22*AS22 -> 0 | AY22: =AX22/BC22 -> #N/A | AZ22: 250 | BA22: =AZ22/H22 -> 0.25 | BB22: =H22-AW22 -> 1000 | BC22: =BX22 -> #N/A | BD22: =BC22*L22 -> #N/A | BE22: =H22*(1-I22)*L22 -> 0 | BF22: =IFERROR(BC22/BV22,) | BG22: =IFERROR(BC22/H22,) | BH22: =IFERROR(if(BW22>0,BC22/BW22,-BC22/BW22),) | BJ22: =IFERROR(__xludf.DUMMYFUNCTION("IF(AU22=data!A$5, IF(AV22=data!A$8, IF(T22=data!A$3, VLOOKUP(S22,filter('🔒 Доп. информация'!D:H,'🔒 Доп. информация'!C:C=T22),4,FALSE)+VLOOKUP(S22,filter('🔒 Доп. информация'!D:H,'🔒 Доп. информация'!C:C=T22),5,FALSE)*AJ22, IF(AND(MAX(AF22:AH22)<80,SUM(A"&"F22:AH22)<=160,AI22<20,XLOOKUP(M22,'📄 Комиссии'!C:C,'📄 Комиссии'!B:B)<>""Продукты""), VLOOKUP(S22,filter('🔒 Доп. информация'!D:H,'🔒 Доп. информация'!C:C=data!$A$3),4,FALSE)+VLOOKUP(S22,filter('🔒 Доп. информация'!D:H,'🔒 Доп. информация'!C:C=data!$A$3"&"),5,FALSE)*AJ22, VLOOKUP(S22,filter('🔒 Доп. информация'!D:H,'🔒 Доп. информация'!C:C=T22),4,FALSE)*ROUNDUP(AF22*AG22*AH22*L22/(120*80*175))/L22) ) *(AE22/2) ,) ,)*0"),0.0) -> 0 | BK22: =IFERROR(__xludf.DUMMYFUNCTION("IF(AU22=data!A$5, IF(AI22<=1,IF(AI22<=0.8,IF(AI22<=0.6,IF(AI22<=0.4,IF(AI22<=0.2,23,26),29),30),32)*VLOOKUP(S22,filter('🔒 Доп. информация'!D:E,'🔒 Доп. информация'!C:C=T22),2,FALSE)/'🔒 Доп. информация'!$K$9, IF(AV22=data!A$8,U22,1)*VLOOKUP(S22,filter('"&"🔒 Доп. информация'!D:E,'🔒 Доп. информация'!C:C=T22),2,FALSE)+ IF(AV22=data!A$8,U22,1)*VLOOKUP(S22,filter('🔒 Доп. информация'!D:F,'🔒 Доп. информация'!C:C=T22),3,FALSE)*AJ22) ,0)"),69.0) -> 69 | BL22: =IF($D22,"🔒",) | BM22: =IF($D22,"🔒",) | BN22: =VLOOKUP(T22,'🔒 Доп. информация'!J:P,7,false) -> 50 | BO22: =IF(AV22=data!A$9, (AA22+AO22+AP22+BJ22+BK22+BN22)+H22*AS22, (BJ22+BK22+BN22)+H22*AS22 ) -> 119 | BP22: =AA22+BJ22+BK22 -> 69 | BQ22: =H22*N22 -> 320 | BR22: =BP22+BQ22+AS22*H22+((1-AQ22)/AQ22)*BO22+AL22+H22*J22*1.1 -> #N/A | BS22: {=IF(VLOOKUP(AT22,{'▶️ Инструкция'!C:C,'▶️ Инструкция'!Y:Y},2,FALSE)=data!A$15, H22*(1-I22), (H22-BR22)) *VLOOKUP(AT22,{'▶️ Инструкция'!C:C,'▶️ Инструкция'!AD:AD},2,FALSE)/(1+VLOOKUP(AT22,{'▶️ Инструкция'!C:C,'▶️ Инструкция'!AD:AD},2,FALSE))} -> #N/A | BT22: {=IF(VLOOKUP(AT22,{'▶️ Инструкция'!C:C,'▶️ Инструкция'!Y:Y},2,FALSE)=data!A$15, H22*(1-I22)-BS22, (H22-BR22-BS22)) * VLOOKUP(AT22,{'▶️ Инструкция'!C:C,'▶️ Инструкция'!R:R},2,FALSE) +BS22} -> #N/A | BU22: =(G22*AR22)+if(AV22=data!A$9,AO22,AN22)+AP22+BR22+BT22 -> #N/A | BV22: =(G22*AR22)+if(AV22=data!A$9,AO22,AN22)+AP22+BT22+G22 -> #N/A | BW22: =H22-BR22 -> #N/A | BX22: =BW22-BV22 -> #N/A
A23: =if(D23=true,if(F23=data!A$1,data!A$10,data!A$11),) | B23: =AV23 -> FBS | C23: Название товара | D23: FALSE | E23: Имя | F23: {=IF(D23=TRUE,IF(IF(BG$3=VLOOKUP(AT23,{'▶️ Инструкция'!C:C,'▶️ Инструкция'!G:G},2,FALSE),BG23,BH23)>VLOOKUP(AT23,{'▶️ Инструкция'!C:C,'▶️ Инструкция'!N:N},2,FALSE),data!A$1,data!A$2),)} | G23: 0 | H23: 1000 | I23: 0 | J23: 0 | K23: =IF($D23,"🔒",) | L23: 0 | M23: Лопатки игрушечные | N23: =IFERROR(__xludf.DUMMYFUNCTION("ArrayFormula(let(category,VLOOKUP($M23, {'📄 Комиссии'!$C:$C , '📄 Комиссии'!$B:$B}, 2, 0), data,MATCH('🔒 Доп. информация'!$J$15:$J203,TRANSPOSE(SPLIT(INDEX('▶️ Инструкция'!$Q:$Q,MATCH($AT23,'▶️ Инструкция'!$R:$R,0)+2),"", "",FALSE)),0), options,COUNTA( "&"ifna( FILTER('🔒 Доп. информация'!$J$15:$J203,('🔒 Доп. информация'!$N$15:$N203=FALSE)*data*('🔒 Доп. информация'!$O$15:$O203=""Опция"")))), commission,VLOOKUP($M23,'📄 Комиссии'!$C:$E,IF($AV23=data!A$8,2,3),0), IF(NOT(ISBLANK($M23)),commission/100+ IFERR"&"OR(VLOOKUP($AT23,{'▶️ Инструкция'!$R:$R,'▶️ Инструкция'!$AK:$AK},2,0)+ IF((( category = ""Одежда"")+( category = ""Обувь"" ))*((options+SUM( ifna( FILTER('🔒 Доп. информация'!$M$15:$M203,('🔒 Доп. информация'!$N$15:$N203=FALSE)*data*('🔒 Доп. информация'!"&"$O$15:$O203=""Пакет"")))))>=5), -5% + 2%, IF((options>=1)* (COUNTA( ifna( FILTER('🔒 Доп. информация'!$J$15:$J203,('🔒 Доп. информация'!$N$15:$N203=FALSE)*data*('🔒 Доп. информация'!$O$15:$O203=""Пакет""))))>=1)* (commission>=14.5)* (category<> ""Одежда"&""")*( category <> ""Обувь"" ),-3% + 2%,0))))))"),0.32) -> 0.32 | O23: =IF($D23,"🔒",) | Q23: =IF($D23,"🔒",) | S23: Макс. из наших | T23: Короб | U23: 1 | V23: =IF($D23,"🔒",) | W23: =IF($D23,"🔒",) | X23: =IF($D23,"🔒",) | Y23: =IF($D23,"🔒",) | Z23: 0 | AA23: =1.7*(1+AJ23)*Z23 -> 0 | AB23: =IF($D23,"🔒",) | AC23: =IF($D23,"🔒",) | AD23: =IF($D23,"🔒",) | AE23: 30 | AF23: 0 | AG23: 0 | AH23: 0 | AI23: =(AF23*AG23*AH23)/1000 -> 0 | AJ23: =if(AI23>1,(AI23-1),0) -> 0 | AK23: =IF($D23,"🔒",) | AL23: {=H23*(1-I23)*VLOOKUP(AT23,{'▶️ Инструкция'!C:C,'▶️ Инструкция'!AI:AI},2,false)} -> #N/A | AM23: =IF($D23,"🔒",) | AN23: 0 | AO23: 0 | AP23: 0 | AQ23: 1 | AR23: 0 | AS23: 0 | AT23: ИП Иванов И.И. | AU23: WB | AV23: FBS | AW23: =AS23*H23 -> 0 | AX23: =(1/(AQ23))*H23*AS23 -> 0 | AY23: =AX23/BC23 -> #N/A | AZ23: 250 | BA23: =AZ23/H23 -> 0.25 | BB23: =H23-AW23 -> 1000 | BC23: =BX23 -> #N/A | BD23: =BC23*L23 -> #N/A | BE23: =H23*(1-I23)*L23 -> 0 | BF23: =IFERROR(BC23/BV23,) | BG23: =IFERROR(BC23/H23,) | BH23: =IFERROR(if(BW23>0,BC23/BW23,-BC23/BW23),) | BJ23: =IFERROR(__xludf.DUMMYFUNCTION("IF(AU23=data!A$5, IF(AV23=data!A$8, IF(T23=data!A$3, VLOOKUP(S23,filter('🔒 Доп. информация'!D:H,'🔒 Доп. информация'!C:C=T23),4,FALSE)+VLOOKUP(S23,filter('🔒 Доп. информация'!D:H,'🔒 Доп. информация'!C:C=T23),5,FALSE)*AJ23, IF(AND(MAX(AF23:AH23)<80,SUM(A"&"F23:AH23)<=160,AI23<20,XLOOKUP(M23,'📄 Комиссии'!C:C,'📄 Комиссии'!B:B)<>""Продукты""), VLOOKUP(S23,filter('🔒 Доп. информация'!D:H,'🔒 Доп. информация'!C:C=data!$A$3),4,FALSE)+VLOOKUP(S23,filter('🔒 Доп. информация'!D:H,'🔒 Доп. информация'!C:C=data!$A$3"&"),5,FALSE)*AJ23, VLOOKUP(S23,filter('🔒 Доп. информация'!D:H,'🔒 Доп. информация'!C:C=T23),4,FALSE)*ROUNDUP(AF23*AG23*AH23*L23/(120*80*175))/L23) ) *(AE23/2) ,) ,)*0"),0.0) -> 0 | BK23: =IFERROR(__xludf.DUMMYFUNCTION("IF(AU23=data!A$5, IF(AI23<=1,IF(AI23<=0.8,IF(AI23<=0.6,IF(AI23<=0.4,IF(AI23<=0.2,23,26),29),30),32)*VLOOKUP(S23,filter('🔒 Доп. информация'!D:E,'🔒 Доп. информация'!C:C=T23),2,FALSE)/'🔒 Доп. информация'!$K$9, IF(AV23=data!A$8,U23,1)*VLOOKUP(S23,filter('"&"🔒 Доп. информация'!D:E,'🔒 Доп. информация'!C:C=T23),2,FALSE)+ IF(AV23=data!A$8,U23,1)*VLOOKUP(S23,filter('🔒 Доп. информация'!D:F,'🔒 Доп. информация'!C:C=T23),3,FALSE)*AJ23) ,0)"),69.0) -> 69 | BL23: =IF($D23,"🔒",) | BM23: =IF($D23,"🔒",) | BN23: =VLOOKUP(T23,'🔒 Доп. информация'!J:P,7,false) -> 50 | BO23: =IF(AV23=data!A$9, (AA23+AO23+AP23+BJ23+BK23+BN23)+H23*AS23, (BJ23+BK23+BN23)+H23*AS23 ) -> 119 | BP23: =AA23+BJ23+BK23 -> 69 | BQ23: =H23*N23 -> 320 | BR23: =BP23+BQ23+AS23*H23+((1-AQ23)/AQ23)*BO23+AL23+H23*J23*1.1 -> #N/A | BS23: {=IF(VLOOKUP(AT23,{'▶️ Инструкция'!C:C,'▶️ Инструкция'!Y:Y},2,FALSE)=data!A$15, H23*(1-I23), (H23-BR23)) *VLOOKUP(AT23,{'▶️ Инструкция'!C:C,'▶️ Инструкция'!AD:AD},2,FALSE)/(1+VLOOKUP(AT23,{'▶️ Инструкция'!C:C,'▶️ Инструкция'!AD:AD},2,FALSE))} -> #N/A | BT23: {=IF(VLOOKUP(AT23,{'▶️ Инструкция'!C:C,'▶️ Инструкция'!Y:Y},2,FALSE)=data!A$15, H23*(1-I23)-BS23, (H23-BR23-BS23)) * VLOOKUP(AT23,{'▶️ Инструкция'!C:C,'▶️ Инструкция'!R:R},2,FALSE) +BS23} -> #N/A | BU23: =(G23*AR23)+if(AV23=data!A$9,AO23,AN23)+AP23+BR23+BT23 -> #N/A | BV23: =(G23*AR23)+if(AV23=data!A$9,AO23,AN23)+AP23+BT23+G23 -> #N/A | BW23: =H23-BR23 -> #N/A | BX23: =BW23-BV23 -> #N/A
A24: =if(D24=true,if(F24=data!A$1,data!A$10,data!A$11),) | B24: =AV24 -> FBS | C24: Название товара | D24: FALSE | E24: Имя | F24: {=IF(D24=TRUE,IF(IF(BG$3=VLOOKUP(AT24,{'▶️ Инструкция'!C:C,'▶️ Инструкция'!G:G},2,FALSE),BG24,BH24)>VLOOKUP(AT24,{'▶️ Инструкция'!C:C,'▶️ Инструкция'!N:N},2,FALSE),data!A$1,data!A$2),)} | G24: 0 | H24: 1000 | I24: 0 | J24: 0 | K24: =IF($D24,"🔒",) | L24: 0 | M24: Лопатки игрушечные | N24: =IFERROR(__xludf.DUMMYFUNCTION("ArrayFormula(let(category,VLOOKUP($M24, {'📄 Комиссии'!$C:$C , '📄 Комиссии'!$B:$B}, 2, 0), data,MATCH('🔒 Доп. информация'!$J$15:$J203,TRANSPOSE(SPLIT(INDEX('▶️ Инструкция'!$Q:$Q,MATCH($AT24,'▶️ Инструкция'!$R:$R,0)+2),"", "",FALSE)),0), options,COUNTA( "&"ifna( FILTER('🔒 Доп. информация'!$J$15:$J203,('🔒 Доп. информация'!$N$15:$N203=FALSE)*data*('🔒 Доп. информация'!$O$15:$O203=""Опция"")))), commission,VLOOKUP($M24,'📄 Комиссии'!$C:$E,IF($AV24=data!A$8,2,3),0), IF(NOT(ISBLANK($M24)),commission/100+ IFERR"&"OR(VLOOKUP($AT24,{'▶️ Инструкция'!$R:$R,'▶️ Инструкция'!$AK:$AK},2,0)+ IF((( category = ""Одежда"")+( category = ""Обувь"" ))*((options+SUM( ifna( FILTER('🔒 Доп. информация'!$M$15:$M203,('🔒 Доп. информация'!$N$15:$N203=FALSE)*data*('🔒 Доп. информация'!"&"$O$15:$O203=""Пакет"")))))>=5), -5% + 2%, IF((options>=1)* (COUNTA( ifna( FILTER('🔒 Доп. информация'!$J$15:$J203,('🔒 Доп. информация'!$N$15:$N203=FALSE)*data*('🔒 Доп. информация'!$O$15:$O203=""Пакет""))))>=1)* (commission>=14.5)* (category<> ""Одежда"&""")*( category <> ""Обувь"" ),-3% + 2%,0))))))"),0.32) -> 0.32 | O24: =IF($D24,"🔒",) | Q24: =IF($D24,"🔒",) | S24: Макс. из наших | T24: Короб | U24: 1 | V24: =IF($D24,"🔒",) | W24: =IF($D24,"🔒",) | X24: =IF($D24,"🔒",) | Y24: =IF($D24,"🔒",) | Z24: 0 | AA24: =1.7*(1+AJ24)*Z24 -> 0 | AB24: =IF($D24,"🔒",) | AC24: =IF($D24,"🔒",) | AD24: =IF($D24,"🔒",) | AE24: 30 | AF24: 0 | AG24: 0 | AH24: 0 | AI24: =(AF24*AG24*AH24)/1000 -> 0 | AJ24: =if(AI24>1,(AI24-1),0) -> 0 | AK24: =IF($D24,"🔒",) | AL24: {=H24*(1-I24)*VLOOKUP(AT24,{'▶️ Инструкция'!C:C,'▶️ Инструкция'!AI:AI},2,false)} -> #N/A | AM24: =IF($D24,"🔒",) | AN24: 0 | AO24: 0 | AP24: 0 | AQ24: 1 | AR24: 0 | AS24: 0 | AT24: ИП Иванов И.И. | AU24: WB | AV24: FBS | AW24: =AS24*H24 -> 0 | AX24: =(1/(AQ24))*H24*AS24 -> 0 | AY24: =AX24/BC24 -> #N/A | AZ24: 250 | BA24: =AZ24/H24 -> 0.25 | BB24: =H24-AW24 -> 1000 | BC24: =BX24 -> #N/A | BD24: =BC24*L24 -> #N/A | BE24: =H24*(1-I24)*L24 -> 0 | BF24: =IFERROR(BC24/BV24,) | BG24: =IFERROR(BC24/H24,) | BH24: =IFERROR(if(BW24>0,BC24/BW24,-BC24/BW24),) | BJ24: =IFERROR(__xludf.DUMMYFUNCTION("IF(AU24=data!A$5, IF(AV24=data!A$8, IF(T24=data!A$3, VLOOKUP(S24,filter('🔒 Доп. информация'!D:H,'🔒 Доп. информация'!C:C=T24),4,FALSE)+VLOOKUP(S24,filter('🔒 Доп. информация'!D:H,'🔒 Доп. информация'!C:C=T24),5,FALSE)*AJ24, IF(AND(MAX(AF24:AH24)<80,SUM(A"&"F24:AH24)<=160,AI24<20,XLOOKUP(M24,'📄 Комиссии'!C:C,'📄 Комиссии'!B:B)<>""Продукты""), VLOOKUP(S24,filter('🔒 Доп. информация'!D:H,'🔒 Доп. информация'!C:C=data!$A$3),4,FALSE)+VLOOKUP(S24,filter('🔒 Доп. информация'!D:H,'🔒 Доп. информация'!C:C=data!$A$3"&"),5,FALSE)*AJ24, VLOOKUP(S24,filter('🔒 Доп. информация'!D:H,'🔒 Доп. информация'!C:C=T24),4,FALSE)*ROUNDUP(AF24*AG24*AH24*L24/(120*80*175))/L24) ) *(AE24/2) ,) ,)*0"),0.0) -> 0 | BK24: =IFERROR(__xludf.DUMMYFUNCTION("IF(AU24=data!A$5, IF(AI24<=1,IF(AI24<=0.8,IF(AI24<=0.6,IF(AI24<=0.4,IF(AI24<=0.2,23,26),29),30),32)*VLOOKUP(S24,filter('🔒 Доп. информация'!D:E,'🔒 Доп. информация'!C:C=T24),2,FALSE)/'🔒 Доп. информация'!$K$9, IF(AV24=data!A$8,U24,1)*VLOOKUP(S24,filter('"&"🔒 Доп. информация'!D:E,'🔒 Доп. информация'!C:C=T24),2,FALSE)+ IF(AV24=data!A$8,U24,1)*VLOOKUP(S24,filter('🔒 Доп. информация'!D:F,'🔒 Доп. информация'!C:C=T24),3,FALSE)*AJ24) ,0)"),69.0) -> 69 | BL24: =IF($D24,"🔒",) | BM24: =IF($D24,"🔒",) | BN24: =VLOOKUP(T24,'🔒 Доп. информация'!J:P,7,false) -> 50 | BO24: =IF(AV24=data!A$9, (AA24+AO24+AP24+BJ24+BK24+BN24)+H24*AS24, (BJ24+BK24+BN24)+H24*AS24 ) -> 119 | BP24: =AA24+BJ24+BK24 -> 69 | BQ24: =H24*N24 -> 320 | BR24: =BP24+BQ24+AS24*H24+((1-AQ24)/AQ24)*BO24+AL24+H24*J24*1.1 -> #N/A | BS24: {=IF(VLOOKUP(AT24,{'▶️ Инструкция'!C:C,'▶️ Инструкция'!Y:Y},2,FALSE)=data!A$15, H24*(1-I24), (H24-BR24)) *VLOOKUP(AT24,{'▶️ Инструкция'!C:C,'▶️ Инструкция'!AD:AD},2,FALSE)/(1+VLOOKUP(AT24,{'▶️ Инструкция'!C:C,'▶️ Инструкция'!AD:AD},2,FALSE))} -> #N/A | BT24: {=IF(VLOOKUP(AT24,{'▶️ Инструкция'!C:C,'▶️ Инструкция'!Y:Y},2,FALSE)=data!A$15, H24*(1-I24)-BS24, (H24-BR24-BS24)) * VLOOKUP(AT24,{'▶️ Инструкция'!C:C,'▶️ Инструкция'!R:R},2,FALSE) +BS24} -> #N/A | BU24: =(G24*AR24)+if(AV24=data!A$9,AO24,AN24)+AP24+BR24+BT24 -> #N/A | BV24: =(G24*AR24)+if(AV24=data!A$9,AO24,AN24)+AP24+BT24+G24 -> #N/A | BW24: =H24-BR24 -> #N/A | BX24: =BW24-BV24 -> #N/A
A25: =if(D25=true,if(F25=data!A$1,data!A$10,data!A$11),) | B25: =AV25 -> FBS | C25: Название товара | D25: FALSE | E25: Имя | F25: {=IF(D25=TRUE,IF(IF(BG$3=VLOOKUP(AT25,{'▶️ Инструкция'!C:C,'▶️ Инструкция'!G:G},2,FALSE),BG25,BH25)>VLOOKUP(AT25,{'▶️ Инструкция'!C:C,'▶️ Инструкция'!N:N},2,FALSE),data!A$1,data!A$2),)} | G25: 0 | H25: 1000 | I25: 0 | J25: 0 | K25: =IF($D25,"🔒",) | L25: 0 | M25: Лопатки игрушечные | N25: =IFERROR(__xludf.DUMMYFUNCTION("ArrayFormula(let(category,VLOOKUP($M25, {'📄 Комиссии'!$C:$C , '📄 Комиссии'!$B:$B}, 2, 0), data,MATCH('🔒 Доп. информация'!$J$15:$J203,TRANSPOSE(SPLIT(INDEX('▶️ Инструкция'!$Q:$Q,MATCH($AT25,'▶️ Инструкция'!$R:$R,0)+2),"", "",FALSE)),0), options,COUNTA( "&"ifna( FILTER('🔒 Доп. информация'!$J$15:$J203,('🔒 Доп. информация'!$N$15:$N203=FALSE)*data*('🔒 Доп. информация'!$O$15:$O203=""Опция"")))), commission,VLOOKUP($M25,'📄 Комиссии'!$C:$E,IF($AV25=data!A$8,2,3),0), IF(NOT(ISBLANK($M25)),commission/100+ IFERR"&"OR(VLOOKUP($AT25,{'▶️ Инструкция'!$R:$R,'▶️ Инструкция'!$AK:$AK},2,0)+ IF((( category = ""Одежда"")+( category = ""Обувь"" ))*((options+SUM( ifna( FILTER('🔒 Доп. информация'!$M$15:$M203,('🔒 Доп. информация'!$N$15:$N203=FALSE)*data*('🔒 Доп. информация'!"&"$O$15:$O203=""Пакет"")))))>=5), -5% + 2%, IF((options>=1)* (COUNTA( ifna( FILTER('🔒 Доп. информация'!$J$15:$J203,('🔒 Доп. информация'!$N$15:$N203=FALSE)*data*('🔒 Доп. информация'!$O$15:$O203=""Пакет""))))>=1)* (commission>=14.5)* (category<> ""Одежда"&""")*( category <> ""Обувь"" ),-3% + 2%,0))))))"),0.32) -> 0.32 | O25: =IF($D25,"🔒",) | Q25: =IF($D25,"🔒",) | S25: Макс. из наших | T25: Короб | U25: 1 | V25: =IF($D25,"🔒",) | W25: =IF($D25,"🔒",) | X25: =IF($D25,"🔒",) | Y25: =IF($D25,"🔒",) | Z25: 0 | AA25: =1.7*(1+AJ25)*Z25 -> 0 | AB25: =IF($D25,"🔒",) | AC25: =IF($D25,"🔒",) | AD25: =IF($D25,"🔒",) | AE25: 30 | AF25: 0 | AG25: 0 | AH25: 0 | AI25: =(AF25*AG25*AH25)/1000 -> 0 | AJ25: =if(AI25>1,(AI25-1),0) -> 0 | AK25: =IF($D25,"🔒",) | AL25: {=H25*(1-I25)*VLOOKUP(AT25,{'▶️ Инструкция'!C:C,'▶️ Инструкция'!AI:AI},2,false)} -> #N/A | AM25: =IF($D25,"🔒",) | AN25: 0 | AO25: 0 | AP25: 0 | AQ25: 1 | AR25: 0 | AS25: 0 | AT25: ИП Иванов И.И. | AU25: WB | AV25: FBS | AW25: =AS25*H25 -> 0 | AX25: =(1/(AQ25))*H25*AS25 -> 0 | AY25: =AX25/BC25 -> #N/A | AZ25: 250 | BA25: =AZ25/H25 -> 0.25 | BB25: =H25-AW25 -> 1000 | BC25: =BX25 -> #N/A | BD25: =BC25*L25 -> #N/A | BE25: =H25*(1-I25)*L25 -> 0 | BF25: =IFERROR(BC25/BV25,) | BG25: =IFERROR(BC25/H25,) | BH25: =IFERROR(if(BW25>0,BC25/BW25,-BC25/BW25),) | BJ25: =IFERROR(__xludf.DUMMYFUNCTION("IF(AU25=data!A$5, IF(AV25=data!A$8, IF(T25=data!A$3, VLOOKUP(S25,filter('🔒 Доп. информация'!D:H,'🔒 Доп. информация'!C:C=T25),4,FALSE)+VLOOKUP(S25,filter('🔒 Доп. информация'!D:H,'🔒 Доп. информация'!C:C=T25),5,FALSE)*AJ25, IF(AND(MAX(AF25:AH25)<80,SUM(A"&"F25:AH25)<=160,AI25<20,XLOOKUP(M25,'📄 Комиссии'!C:C,'📄 Комиссии'!B:B)<>""Продукты""), VLOOKUP(S25,filter('🔒 Доп. информация'!D:H,'🔒 Доп. информация'!C:C=data!$A$3),4,FALSE)+VLOOKUP(S25,filter('🔒 Доп. информация'!D:H,'🔒 Доп. информация'!C:C=data!$A$3"&"),5,FALSE)*AJ25, VLOOKUP(S25,filter('🔒 Доп. информация'!D:H,'🔒 Доп. информация'!C:C=T25),4,FALSE)*ROUNDUP(AF25*AG25*AH25*L25/(120*80*175))/L25) ) *(AE25/2) ,) ,)*0"),0.0) -> 0 | BK25: =IFERROR(__xludf.DUMMYFUNCTION("IF(AU25=data!A$5, IF(AI25<=1,IF(AI25<=0.8,IF(AI25<=0.6,IF(AI25<=0.4,IF(AI25<=0.2,23,26),29),30),32)*VLOOKUP(S25,filter('🔒 Доп. информация'!D:E,'🔒 Доп. информация'!C:C=T25),2,FALSE)/'🔒 Доп. информация'!$K$9, IF(AV25=data!A$8,U25,1)*VLOOKUP(S25,filter('"&"🔒 Доп. информация'!D:E,'🔒 Доп. информация'!C:C=T25),2,FALSE)+ IF(AV25=data!A$8,U25,1)*VLOOKUP(S25,filter('🔒 Доп. информация'!D:F,'🔒 Доп. информация'!C:C=T25),3,FALSE)*AJ25) ,0)"),69.0) -> 69 | BL25: =IF($D25,"🔒",) | BM25: =IF($D25,"🔒",) | BN25: =VLOOKUP(T25,'🔒 Доп. информация'!J:P,7,false) -> 50 | BO25: =IF(AV25=data!A$9, (AA25+AO25+AP25+BJ25+BK25+BN25)+H25*AS25, (BJ25+BK25+BN25)+H25*AS25 ) -> 119 | BP25: =AA25+BJ25+BK25 -> 69 | BQ25: =H25*N25 -> 320 | BR25: =BP25+BQ25+AS25*H25+((1-AQ25)/AQ25)*BO25+AL25+H25*J25*1.1 -> #N/A | BS25: {=IF(VLOOKUP(AT25,{'▶️ Инструкция'!C:C,'▶️ Инструкция'!Y:Y},2,FALSE)=data!A$15, H25*(1-I25), (H25-BR25)) *VLOOKUP(AT25,{'▶️ Инструкция'!C:C,'▶️ Инструкция'!AD:AD},2,FALSE)/(1+VLOOKUP(AT25,{'▶️ Инструкция'!C:C,'▶️ Инструкция'!AD:AD},2,FALSE))} -> #N/A | BT25: {=IF(VLOOKUP(AT25,{'▶️ Инструкция'!C:C,'▶️ Инструкция'!Y:Y},2,FALSE)=data!A$15, H25*(1-I25)-BS25, (H25-BR25-BS25)) * VLOOKUP(AT25,{'▶️ Инструкция'!C:C,'▶️ Инструкция'!R:R},2,FALSE) +BS25} -> #N/A | BU25: =(G25*AR25)+if(AV25=data!A$9,AO25,AN25)+AP25+BR25+BT25 -> #N/A | BV25: =(G25*AR25)+if(AV25=data!A$9,AO25,AN25)+AP25+BT25+G25 -> #N/A | BW25: =H25-BR25 -> #N/A | BX25: =BW25-BV25 -> #N/A
A26: =if(D26=true,if(F26=data!A$1,data!A$10,data!A$11),) | B26: =AV26 -> FBS | C26: Название товара | D26: FALSE | E26: Имя | F26: {=IF(D26=TRUE,IF(IF(BG$3=VLOOKUP(AT26,{'▶️ Инструкция'!C:C,'▶️ Инструкция'!G:G},2,FALSE),BG26,BH26)>VLOOKUP(AT26,{'▶️ Инструкция'!C:C,'▶️ Инструкция'!N:N},2,FALSE),data!A$1,data!A$2),)} | G26: 0 | H26: 1000 | I26: 0 | J26: 0 | K26: =IF($D26,"🔒",) | L26: 0 | M26: Лопатки игрушечные | N26: =IFERROR(__xludf.DUMMYFUNCTION("ArrayFormula(let(category,VLOOKUP($M26, {'📄 Комиссии'!$C:$C , '📄 Комиссии'!$B:$B}, 2, 0), data,MATCH('🔒 Доп. информация'!$J$15:$J203,TRANSPOSE(SPLIT(INDEX('▶️ Инструкция'!$Q:$Q,MATCH($AT26,'▶️ Инструкция'!$R:$R,0)+2),"", "",FALSE)),0), options,COUNTA( "&"ifna( FILTER('🔒 Доп. информация'!$J$15:$J203,('🔒 Доп. информация'!$N$15:$N203=FALSE)*data*('🔒 Доп. информация'!$O$15:$O203=""Опция"")))), commission,VLOOKUP($M26,'📄 Комиссии'!$C:$E,IF($AV26=data!A$8,2,3),0), IF(NOT(ISBLANK($M26)),commission/100+ IFERR"&"OR(VLOOKUP($AT26,{'▶️ Инструкция'!$R:$R,'▶️ Инструкция'!$AK:$AK},2,0)+ IF((( category = ""Одежда"")+( category = ""Обувь"" ))*((options+SUM( ifna( FILTER('🔒 Доп. информация'!$M$15:$M203,('🔒 Доп. информация'!$N$15:$N203=FALSE)*data*('🔒 Доп. информация'!"&"$O$15:$O203=""Пакет"")))))>=5), -5% + 2%, IF((options>=1)* (COUNTA( ifna( FILTER('🔒 Доп. информация'!$J$15:$J203,('🔒 Доп. информация'!$N$15:$N203=FALSE)*data*('🔒 Доп. информация'!$O$15:$O203=""Пакет""))))>=1)* (commission>=14.5)* (category<> ""Одежда"&""")*( category <> ""Обувь"" ),-3% + 2%,0))))))"),0.32) -> 0.32 | O26: =IF($D26,"🔒",) | Q26: =IF($D26,"🔒",) | S26: Макс. из наших | T26: Короб | U26: 1 | V26: =IF($D26,"🔒",) | W26: =IF($D26,"🔒",) | X26: =IF($D26,"🔒",) | Y26: =IF($D26,"🔒",) | Z26: 0 | AA26: =1.7*(1+AJ26)*Z26 -> 0 | AB26: =IF($D26,"🔒",) | AC26: =IF($D26,"🔒",) | AD26: =IF($D26,"🔒",) | AE26: 30 | AF26: 0 | AG26: 0 | AH26: 0 | AI26: =(AF26*AG26*AH26)/1000 -> 0 | AJ26: =if(AI26>1,(AI26-1),0) -> 0 | AK26: =IF($D26,"🔒",) | AL26: {=H26*(1-I26)*VLOOKUP(AT26,{'▶️ Инструкция'!C:C,'▶️ Инструкция'!AI:AI},2,false)} -> #N/A | AM26: =IF($D26,"🔒",) | AN26: 0 | AO26: 0 | AP26: 0 | AQ26: 1 | AR26: 0 | AS26: 0 | AT26: ИП Иванов И.И. | AU26: WB | AV26: FBS | AW26: =AS26*H26 -> 0 | AX26: =(1/(AQ26))*H26*AS26 -> 0 | AY26: =AX26/BC26 -> #N/A | AZ26: 250 | BA26: =AZ26/H26 -> 0.25 | BB26: =H26-AW26 -> 1000 | BC26: =BX26 -> #N/A | BD26: =BC26*L26 -> #N/A | BE26: =H26*(1-I26)*L26 -> 0 | BF26: =IFERROR(BC26/BV26,) | BG26: =IFERROR(BC26/H26,) | BH26: =IFERROR(if(BW26>0,BC26/BW26,-BC26/BW26),) | BJ26: =IFERROR(__xludf.DUMMYFUNCTION("IF(AU26=data!A$5, IF(AV26=data!A$8, IF(T26=data!A$3, VLOOKUP(S26,filter('🔒 Доп. информация'!D:H,'🔒 Доп. информация'!C:C=T26),4,FALSE)+VLOOKUP(S26,filter('🔒 Доп. информация'!D:H,'🔒 Доп. информация'!C:C=T26),5,FALSE)*AJ26, IF(AND(MAX(AF26:AH26)<80,SUM(A"&"F26:AH26)<=160,AI26<20,XLOOKUP(M26,'📄 Комиссии'!C:C,'📄 Комиссии'!B:B)<>""Продукты""), VLOOKUP(S26,filter('🔒 Доп. информация'!D:H,'🔒 Доп. информация'!C:C=data!$A$3),4,FALSE)+VLOOKUP(S26,filter('🔒 Доп. информация'!D:H,'🔒 Доп. информация'!C:C=data!$A$3"&"),5,FALSE)*AJ26, VLOOKUP(S26,filter('🔒 Доп. информация'!D:H,'🔒 Доп. информация'!C:C=T26),4,FALSE)*ROUNDUP(AF26*AG26*AH26*L26/(120*80*175))/L26) ) *(AE26/2) ,) ,)*0"),0.0) -> 0 | BK26: =IFERROR(__xludf.DUMMYFUNCTION("IF(AU26=data!A$5, IF(AI26<=1,IF(AI26<=0.8,IF(AI26<=0.6,IF(AI26<=0.4,IF(AI26<=0.2,23,26),29),30),32)*VLOOKUP(S26,filter('🔒 Доп. информация'!D:E,'🔒 Доп. информация'!C:C=T26),2,FALSE)/'🔒 Доп. информация'!$K$9, IF(AV26=data!A$8,U26,1)*VLOOKUP(S26,filter('"&"🔒 Доп. информация'!D:E,'🔒 Доп. информация'!C:C=T26),2,FALSE)+ IF(AV26=data!A$8,U26,1)*VLOOKUP(S26,filter('🔒 Доп. информация'!D:F,'🔒 Доп. информация'!C:C=T26),3,FALSE)*AJ26) ,0)"),69.0) -> 69 | BL26: =IF($D26,"🔒",) | BM26: =IF($D26,"🔒",) | BN26: =VLOOKUP(T26,'🔒 Доп. информация'!J:P,7,false) -> 50 | BO26: =IF(AV26=data!A$9, (AA26+AO26+AP26+BJ26+BK26+BN26)+H26*AS26, (BJ26+BK26+BN26)+H26*AS26 ) -> 119 | BP26: =AA26+BJ26+BK26 -> 69 | BQ26: =H26*N26 -> 320 | BR26: =BP26+BQ26+AS26*H26+((1-AQ26)/AQ26)*BO26+AL26+H26*J26*1.1 -> #N/A | BS26: {=IF(VLOOKUP(AT26,{'▶️ Инструкция'!C:C,'▶️ Инструкция'!Y:Y},2,FALSE)=data!A$15, H26*(1-I26), (H26-BR26)) *VLOOKUP(AT26,{'▶️ Инструкция'!C:C,'▶️ Инструкция'!AD:AD},2,FALSE)/(1+VLOOKUP(AT26,{'▶️ Инструкция'!C:C,'▶️ Инструкция'!AD:AD},2,FALSE))} -> #N/A | BT26: {=IF(VLOOKUP(AT26,{'▶️ Инструкция'!C:C,'▶️ Инструкция'!Y:Y},2,FALSE)=data!A$15, H26*(1-I26)-BS26, (H26-BR26-BS26)) * VLOOKUP(AT26,{'▶️ Инструкция'!C:C,'▶️ Инструкция'!R:R},2,FALSE) +BS26} -> #N/A | BU26: =(G26*AR26)+if(AV26=data!A$9,AO26,AN26)+AP26+BR26+BT26 -> #N/A | BV26: =(G26*AR26)+if(AV26=data!A$9,AO26,AN26)+AP26+BT26+G26 -> #N/A | BW26: =H26-BR26 -> #N/A | BX26: =BW26-BV26 -> #N/A
A27: =if(D27=true,if(F27=data!A$1,data!A$10,data!A$11),) | B27: =AV27 -> FBS | C27: Название товара | D27: FALSE | E27: Имя | F27: {=IF(D27=TRUE,IF(IF(BG$3=VLOOKUP(AT27,{'▶️ Инструкция'!C:C,'▶️ Инструкция'!G:G},2,FALSE),BG27,BH27)>VLOOKUP(AT27,{'▶️ Инструкция'!C:C,'▶️ Инструкция'!N:N},2,FALSE),data!A$1,data!A$2),)} | G27: 0 | H27: 1000 | I27: 0 | J27: 0 | K27: =IF($D27,"🔒",) | L27: 0 | M27: Лопатки игрушечные | N27: =IFERROR(__xludf.DUMMYFUNCTION("ArrayFormula(let(category,VLOOKUP($M27, {'📄 Комиссии'!$C:$C , '📄 Комиссии'!$B:$B}, 2, 0), data,MATCH('🔒 Доп. информация'!$J$15:$J203,TRANSPOSE(SPLIT(INDEX('▶️ Инструкция'!$Q:$Q,MATCH($AT27,'▶️ Инструкция'!$R:$R,0)+2),"", "",FALSE)),0), options,COUNTA( "&"ifna( FILTER('🔒 Доп. информация'!$J$15:$J203,('🔒 Доп. информация'!$N$15:$N203=FALSE)*data*('🔒 Доп. информация'!$O$15:$O203=""Опция"")))), commission,VLOOKUP($M27,'📄 Комиссии'!$C:$E,IF($AV27=data!A$8,2,3),0), IF(NOT(ISBLANK($M27)),commission/100+ IFERR"&"OR(VLOOKUP($AT27,{'▶️ Инструкция'!$R:$R,'▶️ Инструкция'!$AK:$AK},2,0)+ IF((( category = ""Одежда"")+( category = ""Обувь"" ))*((options+SUM( ifna( FILTER('🔒 Доп. информация'!$M$15:$M203,('🔒 Доп. информация'!$N$15:$N203=FALSE)*data*('🔒 Доп. информация'!"&"$O$15:$O203=""Пакет"")))))>=5), -5% + 2%, IF((options>=1)* (COUNTA( ifna( FILTER('🔒 Доп. информация'!$J$15:$J203,('🔒 Доп. информация'!$N$15:$N203=FALSE)*data*('🔒 Доп. информация'!$O$15:$O203=""Пакет""))))>=1)* (commission>=14.5)* (category<> ""Одежда"&""")*( category <> ""Обувь"" ),-3% + 2%,0))))))"),0.32) -> 0.32 | O27: =IF($D27,"🔒",) | Q27: =IF($D27,"🔒",) | S27: Макс. из наших | T27: Короб | U27: 1 | V27: =IF($D27,"🔒",) | W27: =IF($D27,"🔒",) | X27: =IF($D27,"🔒",) | Y27: =IF($D27,"🔒",) | Z27: 0 | AA27: =1.7*(1+AJ27)*Z27 -> 0 | AB27: =IF($D27,"🔒",) | AC27: =IF($D27,"🔒",) | AD27: =IF($D27,"🔒",) | AE27: 30 | AF27: 0 | AG27: 0 | AH27: 0 | AI27: =(AF27*AG27*AH27)/1000 -> 0 | AJ27: =if(AI27>1,(AI27-1),0) -> 0 | AK27: =IF($D27,"🔒",) | AL27: {=H27*(1-I27)*VLOOKUP(AT27,{'▶️ Инструкция'!C:C,'▶️ Инструкция'!AI:AI},2,false)} -> #N/A | AM27: =IF($D27,"🔒",) | AN27: 0 | AO27: 0 | AP27: 0 | AQ27: 1 | AR27: 0 | AS27: 0 | AT27: ИП Иванов И.И. | AU27: WB | AV27: FBS | AW27: =AS27*H27 -> 0 | AX27: =(1/(AQ27))*H27*AS27 -> 0 | AY27: =AX27/BC27 -> #N/A | AZ27: 250 | BA27: =AZ27/H27 -> 0.25 | BB27: =H27-AW27 -> 1000 | BC27: =BX27 -> #N/A | BD27: =BC27*L27 -> #N/A | BE27: =H27*(1-I27)*L27 -> 0 | BF27: =IFERROR(BC27/BV27,) | BG27: =IFERROR(BC27/H27,) | BH27: =IFERROR(if(BW27>0,BC27/BW27,-BC27/BW27),) | BJ27: =IFERROR(__xludf.DUMMYFUNCTION("IF(AU27=data!A$5, IF(AV27=data!A$8, IF(T27=data!A$3, VLOOKUP(S27,filter('🔒 Доп. информация'!D:H,'🔒 Доп. информация'!C:C=T27),4,FALSE)+VLOOKUP(S27,filter('🔒 Доп. информация'!D:H,'🔒 Доп. информация'!C:C=T27),5,FALSE)*AJ27, IF(AND(MAX(AF27:AH27)<80,SUM(A"&"F27:AH27)<=160,AI27<20,XLOOKUP(M27,'📄 Комиссии'!C:C,'📄 Комиссии'!B:B)<>""Продукты""), VLOOKUP(S27,filter('🔒 Доп. информация'!D:H,'🔒 Доп. информация'!C:C=data!$A$3),4,FALSE)+VLOOKUP(S27,filter('🔒 Доп. информация'!D:H,'🔒 Доп. информация'!C:C=data!$A$3"&"),5,FALSE)*AJ27, VLOOKUP(S27,filter('🔒 Доп. информация'!D:H,'🔒 Доп. информация'!C:C=T27),4,FALSE)*ROUNDUP(AF27*AG27*AH27*L27/(120*80*175))/L27) ) *(AE27/2) ,) ,)*0"),0.0) -> 0 | BK27: =IFERROR(__xludf.DUMMYFUNCTION("IF(AU27=data!A$5, IF(AI27<=1,IF(AI27<=0.8,IF(AI27<=0.6,IF(AI27<=0.4,IF(AI27<=0.2,23,26),29),30),32)*VLOOKUP(S27,filter('🔒 Доп. информация'!D:E,'🔒 Доп. информация'!C:C=T27),2,FALSE)/'🔒 Доп. информация'!$K$9, IF(AV27=data!A$8,U27,1)*VLOOKUP(S27,filter('"&"🔒 Доп. информация'!D:E,'🔒 Доп. информация'!C:C=T27),2,FALSE)+ IF(AV27=data!A$8,U27,1)*VLOOKUP(S27,filter('🔒 Доп. информация'!D:F,'🔒 Доп. информация'!C:C=T27),3,FALSE)*AJ27) ,0)"),69.0) -> 69 | BL27: =IF($D27,"🔒",) | BM27: =IF($D27,"🔒",) | BN27: =VLOOKUP(T27,'🔒 Доп. информация'!J:P,7,false) -> 50 | BO27: =IF(AV27=data!A$9, (AA27+AO27+AP27+BJ27+BK27+BN27)+H27*AS27, (BJ27+BK27+BN27)+H27*AS27 ) -> 119 | BP27: =AA27+BJ27+BK27 -> 69 | BQ27: =H27*N27 -> 320 | BR27: =BP27+BQ27+AS27*H27+((1-AQ27)/AQ27)*BO27+AL27+H27*J27*1.1 -> #N/A | BS27: {=IF(VLOOKUP(AT27,{'▶️ Инструкция'!C:C,'▶️ Инструкция'!Y:Y},2,FALSE)=data!A$15, H27*(1-I27), (H27-BR27)) *VLOOKUP(AT27,{'▶️ Инструкция'!C:C,'▶️ Инструкция'!AD:AD},2,FALSE)/(1+VLOOKUP(AT27,{'▶️ Инструкция'!C:C,'▶️ Инструкция'!AD:AD},2,FALSE))} -> #N/A | BT27: {=IF(VLOOKUP(AT27,{'▶️ Инструкция'!C:C,'▶️ Инструкция'!Y:Y},2,FALSE)=data!A$15, H27*(1-I27)-BS27, (H27-BR27-BS27)) * VLOOKUP(AT27,{'▶️ Инструкция'!C:C,'▶️ Инструкция'!R:R},2,FALSE) +BS27} -> #N/A | BU27: =(G27*AR27)+if(AV27=data!A$9,AO27,AN27)+AP27+BR27+BT27 -> #N/A | BV27: =(G27*AR27)+if(AV27=data!A$9,AO27,AN27)+AP27+BT27+G27 -> #N/A | BW27: =H27-BR27 -> #N/A | BX27: =BW27-BV27 -> #N/A
A28: =if(D28=true,if(F28=data!A$1,data!A$10,data!A$11),) | B28: =AV28 -> FBS | C28: Название товара | D28: FALSE | E28: Имя | F28: {=IF(D28=TRUE,IF(IF(BG$3=VLOOKUP(AT28,{'▶️ Инструкция'!C:C,'▶️ Инструкция'!G:G},2,FALSE),BG28,BH28)>VLOOKUP(AT28,{'▶️ Инструкция'!C:C,'▶️ Инструкция'!N:N},2,FALSE),data!A$1,data!A$2),)} | G28: 0 | H28: 1000 | I28: 0 | J28: 0 | K28: =IF($D28,"🔒",) | L28: 0 | M28: Лопатки игрушечные | N28: =IFERROR(__xludf.DUMMYFUNCTION("ArrayFormula(let(category,VLOOKUP($M28, {'📄 Комиссии'!$C:$C , '📄 Комиссии'!$B:$B}, 2, 0), data,MATCH('🔒 Доп. информация'!$J$15:$J203,TRANSPOSE(SPLIT(INDEX('▶️ Инструкция'!$Q:$Q,MATCH($AT28,'▶️ Инструкция'!$R:$R,0)+2),"", "",FALSE)),0), options,COUNTA( "&"ifna( FILTER('🔒 Доп. информация'!$J$15:$J203,('🔒 Доп. информация'!$N$15:$N203=FALSE)*data*('🔒 Доп. информация'!$O$15:$O203=""Опция"")))), commission,VLOOKUP($M28,'📄 Комиссии'!$C:$E,IF($AV28=data!A$8,2,3),0), IF(NOT(ISBLANK($M28)),commission/100+ IFERR"&"OR(VLOOKUP($AT28,{'▶️ Инструкция'!$R:$R,'▶️ Инструкция'!$AK:$AK},2,0)+ IF((( category = ""Одежда"")+( category = ""Обувь"" ))*((options+SUM( ifna( FILTER('🔒 Доп. информация'!$M$15:$M203,('🔒 Доп. информация'!$N$15:$N203=FALSE)*data*('🔒 Доп. информация'!"&"$O$15:$O203=""Пакет"")))))>=5), -5% + 2%, IF((options>=1)* (COUNTA( ifna( FILTER('🔒 Доп. информация'!$J$15:$J203,('🔒 Доп. информация'!$N$15:$N203=FALSE)*data*('🔒 Доп. информация'!$O$15:$O203=""Пакет""))))>=1)* (commission>=14.5)* (category<> ""Одежда"&""")*( category <> ""Обувь"" ),-3% + 2%,0))))))"),0.32) -> 0.32 | O28: =IF($D28,"🔒",) | Q28: =IF($D28,"🔒",) | S28: Макс. из наших | T28: Короб | U28: 1 | V28: =IF($D28,"🔒",) | W28: =IF($D28,"🔒",) | X28: =IF($D28,"🔒",) | Y28: =IF($D28,"🔒",) | Z28: 0 | AA28: =1.7*(1+AJ28)*Z28 -> 0 | AB28: =IF($D28,"🔒",) | AC28: =IF($D28,"🔒",) | AD28: =IF($D28,"🔒",) | AE28: 30 | AF28: 0 | AG28: 0 | AH28: 0 | AI28: =(AF28*AG28*AH28)/1000 -> 0 | AJ28: =if(AI28>1,(AI28-1),0) -> 0 | AK28: =IF($D28,"🔒",) | AL28: {=H28*(1-I28)*VLOOKUP(AT28,{'▶️ Инструкция'!C:C,'▶️ Инструкция'!AI:AI},2,false)} -> #N/A | AM28: =IF($D28,"🔒",) | AN28: 0 | AO28: 0 | AP28: 0 | AQ28: 1 | AR28: 0 | AS28: 0 | AT28: ИП Иванов И.И. | AU28: WB | AV28: FBS | AW28: =AS28*H28 -> 0 | AX28: =(1/(AQ28))*H28*AS28 -> 0 | AY28: =AX28/BC28 -> #N/A | AZ28: 250 | BA28: =AZ28/H28 -> 0.25 | BB28: =H28-AW28 -> 1000 | BC28: =BX28 -> #N/A | BD28: =BC28*L28 -> #N/A | BE28: =H28*(1-I28)*L28 -> 0 | BF28: =IFERROR(BC28/BV28,) | BG28: =IFERROR(BC28/H28,) | BH28: =IFERROR(if(BW28>0,BC28/BW28,-BC28/BW28),) | BJ28: =IFERROR(__xludf.DUMMYFUNCTION("IF(AU28=data!A$5, IF(AV28=data!A$8, IF(T28=data!A$3, VLOOKUP(S28,filter('🔒 Доп. информация'!D:H,'🔒 Доп. информация'!C:C=T28),4,FALSE)+VLOOKUP(S28,filter('🔒 Доп. информация'!D:H,'🔒 Доп. информация'!C:C=T28),5,FALSE)*AJ28, IF(AND(MAX(AF28:AH28)<80,SUM(A"&"F28:AH28)<=160,AI28<20,XLOOKUP(M28,'📄 Комиссии'!C:C,'📄 Комиссии'!B:B)<>""Продукты""), VLOOKUP(S28,filter('🔒 Доп. информация'!D:H,'🔒 Доп. информация'!C:C=data!$A$3),4,FALSE)+VLOOKUP(S28,filter('🔒 Доп. информация'!D:H,'🔒 Доп. информация'!C:C=data!$A$3"&"),5,FALSE)*AJ28, VLOOKUP(S28,filter('🔒 Доп. информация'!D:H,'🔒 Доп. информация'!C:C=T28),4,FALSE)*ROUNDUP(AF28*AG28*AH28*L28/(120*80*175))/L28) ) *(AE28/2) ,) ,)*0"),0.0) -> 0 | BK28: =IFERROR(__xludf.DUMMYFUNCTION("IF(AU28=data!A$5, IF(AI28<=1,IF(AI28<=0.8,IF(AI28<=0.6,IF(AI28<=0.4,IF(AI28<=0.2,23,26),29),30),32)*VLOOKUP(S28,filter('🔒 Доп. информация'!D:E,'🔒 Доп. информация'!C:C=T28),2,FALSE)/'🔒 Доп. информация'!$K$9, IF(AV28=data!A$8,U28,1)*VLOOKUP(S28,filter('"&"🔒 Доп. информация'!D:E,'🔒 Доп. информация'!C:C=T28),2,FALSE)+ IF(AV28=data!A$8,U28,1)*VLOOKUP(S28,filter('🔒 Доп. информация'!D:F,'🔒 Доп. информация'!C:C=T28),3,FALSE)*AJ28) ,0)"),69.0) -> 69 | BL28: =IF($D28,"🔒",) | BM28: =IF($D28,"🔒",) | BN28: =VLOOKUP(T28,'🔒 Доп. информация'!J:P,7,false) -> 50 | BO28: =IF(AV28=data!A$9, (AA28+AO28+AP28+BJ28+BK28+BN28)+H28*AS28, (BJ28+BK28+BN28)+H28*AS28 ) -> 119 | BP28: =AA28+BJ28+BK28 -> 69 | BQ28: =H28*N28 -> 320 | BR28: =BP28+BQ28+AS28*H28+((1-AQ28)/AQ28)*BO28+AL28+H28*J28*1.1 -> #N/A | BS28: {=IF(VLOOKUP(AT28,{'▶️ Инструкция'!C:C,'▶️ Инструкция'!Y:Y},2,FALSE)=data!A$15, H28*(1-I28), (H28-BR28)) *VLOOKUP(AT28,{'▶️ Инструкция'!C:C,'▶️ Инструкция'!AD:AD},2,FALSE)/(1+VLOOKUP(AT28,{'▶️ Инструкция'!C:C,'▶️ Инструкция'!AD:AD},2,FALSE))} -> #N/A | BT28: {=IF(VLOOKUP(AT28,{'▶️ Инструкция'!C:C,'▶️ Инструкция'!Y:Y},2,FALSE)=data!A$15, H28*(1-I28)-BS28, (H28-BR28-BS28)) * VLOOKUP(AT28,{'▶️ Инструкция'!C:C,'▶️ Инструкция'!R:R},2,FALSE) +BS28} -> #N/A | BU28: =(G28*AR28)+if(AV28=data!A$9,AO28,AN28)+AP28+BR28+BT28 -> #N/A | BV28: =(G28*AR28)+if(AV28=data!A$9,AO28,AN28)+AP28+BT28+G28 -> #N/A | BW28: =H28-BR28 -> #N/A | BX28: =BW28-BV28 -> #N/A
A29: =if(D29=true,if(F29=data!A$1,data!A$10,data!A$11),) | B29: =AV29 -> FBS | C29: Название товара | D29: FALSE | E29: Имя | F29: {=IF(D29=TRUE,IF(IF(BG$3=VLOOKUP(AT29,{'▶️ Инструкция'!C:C,'▶️ Инструкция'!G:G},2,FALSE),BG29,BH29)>VLOOKUP(AT29,{'▶️ Инструкция'!C:C,'▶️ Инструкция'!N:N},2,FALSE),data!A$1,data!A$2),)} | G29: 0 | H29: 1000 | I29: 0 | J29: 0 | K29: =IF($D29,"🔒",) | L29: 0 | M29: Лопатки игрушечные | N29: =IFERROR(__xludf.DUMMYFUNCTION("ArrayFormula(let(category,VLOOKUP($M29, {'📄 Комиссии'!$C:$C , '📄 Комиссии'!$B:$B}, 2, 0), data,MATCH('🔒 Доп. информация'!$J$15:$J203,TRANSPOSE(SPLIT(INDEX('▶️ Инструкция'!$Q:$Q,MATCH($AT29,'▶️ Инструкция'!$R:$R,0)+2),"", "",FALSE)),0), options,COUNTA( "&"ifna( FILTER('🔒 Доп. информация'!$J$15:$J203,('🔒 Доп. информация'!$N$15:$N203=FALSE)*data*('🔒 Доп. информация'!$O$15:$O203=""Опция"")))), commission,VLOOKUP($M29,'📄 Комиссии'!$C:$E,IF($AV29=data!A$8,2,3),0), IF(NOT(ISBLANK($M29)),commission/100+ IFERR"&"OR(VLOOKUP($AT29,{'▶️ Инструкция'!$R:$R,'▶️ Инструкция'!$AK:$AK},2,0)+ IF((( category = ""Одежда"")+( category = ""Обувь"" ))*((options+SUM( ifna( FILTER('🔒 Доп. информация'!$M$15:$M203,('🔒 Доп. информация'!$N$15:$N203=FALSE)*data*('🔒 Доп. информация'!"&"$O$15:$O203=""Пакет"")))))>=5), -5% + 2%, IF((options>=1)* (COUNTA( ifna( FILTER('🔒 Доп. информация'!$J$15:$J203,('🔒 Доп. информация'!$N$15:$N203=FALSE)*data*('🔒 Доп. информация'!$O$15:$O203=""Пакет""))))>=1)* (commission>=14.5)* (category<> ""Одежда"&""")*( category <> ""Обувь"" ),-3% + 2%,0))))))"),0.32) -> 0.32 | O29: =IF($D29,"🔒",) | Q29: =IF($D29,"🔒",) | S29: Макс. из наших | T29: Короб | U29: 1 | V29: =IF($D29,"🔒",) | W29: =IF($D29,"🔒",) | X29: =IF($D29,"🔒",) | Y29: =IF($D29,"🔒",) | Z29: 0 | AA29: =1.7*(1+AJ29)*Z29 -> 0 | AB29: =IF($D29,"🔒",) | AC29: =IF($D29,"🔒",) | AD29: =IF($D29,"🔒",) | AE29: 30 | AF29: 0 | AG29: 0 | AH29: 0 | AI29: =(AF29*AG29*AH29)/1000 -> 0 | AJ29: =if(AI29>1,(AI29-1),0) -> 0 | AK29: =IF($D29,"🔒",) | AL29: {=H29*(1-I29)*VLOOKUP(AT29,{'▶️ Инструкция'!C:C,'▶️ Инструкция'!AI:AI},2,false)} -> #N/A | AM29: =IF($D29,"🔒",) | AN29: 0 | AO29: 0 | AP29: 0 | AQ29: 1 | AR29: 0 | AS29: 0 | AT29: ИП Иванов И.И. | AU29: WB | AV29: FBS | AW29: =AS29*H29 -> 0 | AX29: =(1/(AQ29))*H29*AS29 -> 0 | AY29: =AX29/BC29 -> #N/A | AZ29: 250 | BA29: =AZ29/H29 -> 0.25 | BB29: =H29-AW29 -> 1000 | BC29: =BX29 -> #N/A | BD29: =BC29*L29 -> #N/A | BE29: =H29*(1-I29)*L29 -> 0 | BF29: =IFERROR(BC29/BV29,) | BG29: =IFERROR(BC29/H29,) | BH29: =IFERROR(if(BW29>0,BC29/BW29,-BC29/BW29),) | BJ29: =IFERROR(__xludf.DUMMYFUNCTION("IF(AU29=data!A$5, IF(AV29=data!A$8, IF(T29=data!A$3, VLOOKUP(S29,filter('🔒 Доп. информация'!D:H,'🔒 Доп. информация'!C:C=T29),4,FALSE)+VLOOKUP(S29,filter('🔒 Доп. информация'!D:H,'🔒 Доп. информация'!C:C=T29),5,FALSE)*AJ29, IF(AND(MAX(AF29:AH29)<80,SUM(A"&"F29:AH29)<=160,AI29<20,XLOOKUP(M29,'📄 Комиссии'!C:C,'📄 Комиссии'!B:B)<>""Продукты""), VLOOKUP(S29,filter('🔒 Доп. информация'!D:H,'🔒 Доп. информация'!C:C=data!$A$3),4,FALSE)+VLOOKUP(S29,filter('🔒 Доп. информация'!D:H,'🔒 Доп. информация'!C:C=data!$A$3"&"),5,FALSE)*AJ29, VLOOKUP(S29,filter('🔒 Доп. информация'!D:H,'🔒 Доп. информация'!C:C=T29),4,FALSE)*ROUNDUP(AF29*AG29*AH29*L29/(120*80*175))/L29) ) *(AE29/2) ,) ,)*0"),0.0) -> 0 | BK29: =IFERROR(__xludf.DUMMYFUNCTION("IF(AU29=data!A$5, IF(AI29<=1,IF(AI29<=0.8,IF(AI29<=0.6,IF(AI29<=0.4,IF(AI29<=0.2,23,26),29),30),32)*VLOOKUP(S29,filter('🔒 Доп. информация'!D:E,'🔒 Доп. информация'!C:C=T29),2,FALSE)/'🔒 Доп. информация'!$K$9, IF(AV29=data!A$8,U29,1)*VLOOKUP(S29,filter('"&"🔒 Доп. информация'!D:E,'🔒 Доп. информация'!C:C=T29),2,FALSE)+ IF(AV29=data!A$8,U29,1)*VLOOKUP(S29,filter('🔒 Доп. информация'!D:F,'🔒 Доп. информация'!C:C=T29),3,FALSE)*AJ29) ,0)"),69.0) -> 69 | BL29: =IF($D29,"🔒",) | BM29: =IF($D29,"🔒",) | BN29: =VLOOKUP(T29,'🔒 Доп. информация'!J:P,7,false) -> 50 | BO29: =IF(AV29=data!A$9, (AA29+AO29+AP29+BJ29+BK29+BN29)+H29*AS29, (BJ29+BK29+BN29)+H29*AS29 ) -> 119 | BP29: =AA29+BJ29+BK29 -> 69 | BQ29: =H29*N29 -> 320 | BR29: =BP29+BQ29+AS29*H29+((1-AQ29)/AQ29)*BO29+AL29+H29*J29*1.1 -> #N/A | BS29: {=IF(VLOOKUP(AT29,{'▶️ Инструкция'!C:C,'▶️ Инструкция'!Y:Y},2,FALSE)=data!A$15, H29*(1-I29), (H29-BR29)) *VLOOKUP(AT29,{'▶️ Инструкция'!C:C,'▶️ Инструкция'!AD:AD},2,FALSE)/(1+VLOOKUP(AT29,{'▶️ Инструкция'!C:C,'▶️ Инструкция'!AD:AD},2,FALSE))} -> #N/A | BT29: {=IF(VLOOKUP(AT29,{'▶️ Инструкция'!C:C,'▶️ Инструкция'!Y:Y},2,FALSE)=data!A$15, H29*(1-I29)-BS29, (H29-BR29-BS29)) * VLOOKUP(AT29,{'▶️ Инструкция'!C:C,'▶️ Инструкция'!R:R},2,FALSE) +BS29} -> #N/A | BU29: =(G29*AR29)+if(AV29=data!A$9,AO29,AN29)+AP29+BR29+BT29 -> #N/A | BV29: =(G29*AR29)+if(AV29=data!A$9,AO29,AN29)+AP29+BT29+G29 -> #N/A | BW29: =H29-BR29 -> #N/A | BX29: =BW29-BV29 -> #N/A
A30: =if(D30=true,if(F30=data!A$1,data!A$10,data!A$11),) | B30: =AV30 -> FBS | C30: Название товара | D30: FALSE | E30: Имя | F30: {=IF(D30=TRUE,IF(IF(BG$3=VLOOKUP(AT30,{'▶️ Инструкция'!C:C,'▶️ Инструкция'!G:G},2,FALSE),BG30,BH30)>VLOOKUP(AT30,{'▶️ Инструкция'!C:C,'▶️ Инструкция'!N:N},2,FALSE),data!A$1,data!A$2),)} | G30: 0 | H30: 1000 | I30: 0 | J30: 0 | K30: =IF($D30,"🔒",) | L30: 0 | M30: Лопатки игрушечные | N30: =IFERROR(__xludf.DUMMYFUNCTION("ArrayFormula(let(category,VLOOKUP($M30, {'📄 Комиссии'!$C:$C , '📄 Комиссии'!$B:$B}, 2, 0), data,MATCH('🔒 Доп. информация'!$J$15:$J203,TRANSPOSE(SPLIT(INDEX('▶️ Инструкция'!$Q:$Q,MATCH($AT30,'▶️ Инструкция'!$R:$R,0)+2),"", "",FALSE)),0), options,COUNTA( "&"ifna( FILTER('🔒 Доп. информация'!$J$15:$J203,('🔒 Доп. информация'!$N$15:$N203=FALSE)*data*('🔒 Доп. информация'!$O$15:$O203=""Опция"")))), commission,VLOOKUP($M30,'📄 Комиссии'!$C:$E,IF($AV30=data!A$8,2,3),0), IF(NOT(ISBLANK($M30)),commission/100+ IFERR"&"OR(VLOOKUP($AT30,{'▶️ Инструкция'!$R:$R,'▶️ Инструкция'!$AK:$AK},2,0)+ IF((( category = ""Одежда"")+( category = ""Обувь"" ))*((options+SUM( ifna( FILTER('🔒 Доп. информация'!$M$15:$M203,('🔒 Доп. информация'!$N$15:$N203=FALSE)*data*('🔒 Доп. информация'!"&"$O$15:$O203=""Пакет"")))))>=5), -5% + 2%, IF((options>=1)* (COUNTA( ifna( FILTER('🔒 Доп. информация'!$J$15:$J203,('🔒 Доп. информация'!$N$15:$N203=FALSE)*data*('🔒 Доп. информация'!$O$15:$O203=""Пакет""))))>=1)* (commission>=14.5)* (category<> ""Одежда"&""")*( category <> ""Обувь"" ),-3% + 2%,0))))))"),0.32) -> 0.32 | O30: =IF($D30,"🔒",) | Q30: =IF($D30,"🔒",) | S30: Макс. из наших | T30: Короб | U30: 1 | V30: =IF($D30,"🔒",) | W30: =IF($D30,"🔒",) | X30: =IF($D30,"🔒",) | Y30: =IF($D30,"🔒",) | Z30: 0 | AA30: =1.7*(1+AJ30)*Z30 -> 0 | AB30: =IF($D30,"🔒",) | AC30: =IF($D30,"🔒",) | AD30: =IF($D30,"🔒",) | AE30: 30 | AF30: 0 | AG30: 0 | AH30: 0 | AI30: =(AF30*AG30*AH30)/1000 -> 0 | AJ30: =if(AI30>1,(AI30-1),0) -> 0 | AK30: =IF($D30,"🔒",) | AL30: {=H30*(1-I30)*VLOOKUP(AT30,{'▶️ Инструкция'!C:C,'▶️ Инструкция'!AI:AI},2,false)} -> #N/A | AM30: =IF($D30,"🔒",) | AN30: 0 | AO30: 0 | AP30: 0 | AQ30: 1 | AR30: 0 | AS30: 0 | AT30: ИП Иванов И.И. | AU30: WB | AV30: FBS | AW30: =AS30*H30 -> 0 | AX30: =(1/(AQ30))*H30*AS30 -> 0 | AY30: =AX30/BC30 -> #N/A | AZ30: 250 | BA30: =AZ30/H30 -> 0.25 | BB30: =H30-AW30 -> 1000 | BC30: =BX30 -> #N/A | BD30: =BC30*L30 -> #N/A | BE30: =H30*(1-I30)*L30 -> 0 | BF30: =IFERROR(BC30/BV30,) | BG30: =IFERROR(BC30/H30,) | BH30: =IFERROR(if(BW30>0,BC30/BW30,-BC30/BW30),) | BJ30: =IFERROR(__xludf.DUMMYFUNCTION("IF(AU30=data!A$5, IF(AV30=data!A$8, IF(T30=data!A$3, VLOOKUP(S30,filter('🔒 Доп. информация'!D:H,'🔒 Доп. информация'!C:C=T30),4,FALSE)+VLOOKUP(S30,filter('🔒 Доп. информация'!D:H,'🔒 Доп. информация'!C:C=T30),5,FALSE)*AJ30, IF(AND(MAX(AF30:AH30)<80,SUM(A"&"F30:AH30)<=160,AI30<20,XLOOKUP(M30,'📄 Комиссии'!C:C,'📄 Комиссии'!B:B)<>""Продукты""), VLOOKUP(S30,filter('🔒 Доп. информация'!D:H,'🔒 Доп. информация'!C:C=data!$A$3),4,FALSE)+VLOOKUP(S30,filter('🔒 Доп. информация'!D:H,'🔒 Доп. информация'!C:C=data!$A$3"&"),5,FALSE)*AJ30, VLOOKUP(S30,filter('🔒 Доп. информация'!D:H,'🔒 Доп. информация'!C:C=T30),4,FALSE)*ROUNDUP(AF30*AG30*AH30*L30/(120*80*175))/L30) ) *(AE30/2) ,) ,)*0"),0.0) -> 0 | BK30: =IFERROR(__xludf.DUMMYFUNCTION("IF(AU30=data!A$5, IF(AI30<=1,IF(AI30<=0.8,IF(AI30<=0.6,IF(AI30<=0.4,IF(AI30<=0.2,23,26),29),30),32)*VLOOKUP(S30,filter('🔒 Доп. информация'!D:E,'🔒 Доп. информация'!C:C=T30),2,FALSE)/'🔒 Доп. информация'!$K$9, IF(AV30=data!A$8,U30,1)*VLOOKUP(S30,filter('"&"🔒 Доп. информация'!D:E,'🔒 Доп. информация'!C:C=T30),2,FALSE)+ IF(AV30=data!A$8,U30,1)*VLOOKUP(S30,filter('🔒 Доп. информация'!D:F,'🔒 Доп. информация'!C:C=T30),3,FALSE)*AJ30) ,0)"),69.0) -> 69 | BL30: =IF($D30,"🔒",) | BM30: =IF($D30,"🔒",) | BN30: =VLOOKUP(T30,'🔒 Доп. информация'!J:P,7,false) -> 50 | BO30: =IF(AV30=data!A$9, (AA30+AO30+AP30+BJ30+BK30+BN30)+H30*AS30, (BJ30+BK30+BN30)+H30*AS30 ) -> 119 | BP30: =AA30+BJ30+BK30 -> 69 | BQ30: =H30*N30 -> 320 | BR30: =BP30+BQ30+AS30*H30+((1-AQ30)/AQ30)*BO30+AL30+H30*J30*1.1 -> #N/A | BS30: {=IF(VLOOKUP(AT30,{'▶️ Инструкция'!C:C,'▶️ Инструкция'!Y:Y},2,FALSE)=data!A$15, H30*(1-I30), (H30-BR30)) *VLOOKUP(AT30,{'▶️ Инструкция'!C:C,'▶️ Инструкция'!AD:AD},2,FALSE)/(1+VLOOKUP(AT30,{'▶️ Инструкция'!C:C,'▶️ Инструкция'!AD:AD},2,FALSE))} -> #N/A | BT30: {=IF(VLOOKUP(AT30,{'▶️ Инструкция'!C:C,'▶️ Инструкция'!Y:Y},2,FALSE)=data!A$15, H30*(1-I30)-BS30, (H30-BR30-BS30)) * VLOOKUP(AT30,{'▶️ Инструкция'!C:C,'▶️ Инструкция'!R:R},2,FALSE) +BS30} -> #N/A | BU30: =(G30*AR30)+if(AV30=data!A$9,AO30,AN30)+AP30+BR30+BT30 -> #N/A | BV30: =(G30*AR30)+if(AV30=data!A$9,AO30,AN30)+AP30+BT30+G30 -> #N/A | BW30: =H30-BR30 -> #N/A | BX30: =BW30-BV30 -> #N/A
A31: =if(D31=true,if(F31=data!A$1,data!A$10,data!A$11),) | B31: =AV31 -> FBS | C31: Название товара | D31: FALSE | E31: Имя | F31: {=IF(D31=TRUE,IF(IF(BG$3=VLOOKUP(AT31,{'▶️ Инструкция'!C:C,'▶️ Инструкция'!G:G},2,FALSE),BG31,BH31)>VLOOKUP(AT31,{'▶️ Инструкция'!C:C,'▶️ Инструкция'!N:N},2,FALSE),data!A$1,data!A$2),)} | G31: 0 | H31: 1000 | I31: 0 | J31: 0 | K31: =IF($D31,"🔒",) | L31: 0 | M31: Лопатки игрушечные | N31: =IFERROR(__xludf.DUMMYFUNCTION("ArrayFormula(let(category,VLOOKUP($M31, {'📄 Комиссии'!$C:$C , '📄 Комиссии'!$B:$B}, 2, 0), data,MATCH('🔒 Доп. информация'!$J$15:$J203,TRANSPOSE(SPLIT(INDEX('▶️ Инструкция'!$Q:$Q,MATCH($AT31,'▶️ Инструкция'!$R:$R,0)+2),"", "",FALSE)),0), options,COUNTA( "&"ifna( FILTER('🔒 Доп. информация'!$J$15:$J203,('🔒 Доп. информация'!$N$15:$N203=FALSE)*data*('🔒 Доп. информация'!$O$15:$O203=""Опция"")))), commission,VLOOKUP($M31,'📄 Комиссии'!$C:$E,IF($AV31=data!A$8,2,3),0), IF(NOT(ISBLANK($M31)),commission/100+ IFERR"&"OR(VLOOKUP($AT31,{'▶️ Инструкция'!$R:$R,'▶️ Инструкция'!$AK:$AK},2,0)+ IF((( category = ""Одежда"")+( category = ""Обувь"" ))*((options+SUM( ifna( FILTER('🔒 Доп. информация'!$M$15:$M203,('🔒 Доп. информация'!$N$15:$N203=FALSE)*data*('🔒 Доп. информация'!"&"$O$15:$O203=""Пакет"")))))>=5), -5% + 2%, IF((options>=1)* (COUNTA( ifna( FILTER('🔒 Доп. информация'!$J$15:$J203,('🔒 Доп. информация'!$N$15:$N203=FALSE)*data*('🔒 Доп. информация'!$O$15:$O203=""Пакет""))))>=1)* (commission>=14.5)* (category<> ""Одежда"&""")*( category <> ""Обувь"" ),-3% + 2%,0))))))"),0.32) -> 0.32 | O31: =IF($D31,"🔒",) | Q31: =IF($D31,"🔒",) | S31: Макс. из наших | T31: Короб | U31: 1 | V31: =IF($D31,"🔒",) | W31: =IF($D31,"🔒",) | X31: =IF($D31,"🔒",) | Y31: =IF($D31,"🔒",) | Z31: 0 | AA31: =1.7*(1+AJ31)*Z31 -> 0 | AB31: =IF($D31,"🔒",) | AC31: =IF($D31,"🔒",) | AD31: =IF($D31,"🔒",) | AE31: 30 | AF31: 0 | AG31: 0 | AH31: 0 | AI31: =(AF31*AG31*AH31)/1000 -> 0 | AJ31: =if(AI31>1,(AI31-1),0) -> 0 | AK31: =IF($D31,"🔒",) | AL31: {=H31*(1-I31)*VLOOKUP(AT31,{'▶️ Инструкция'!C:C,'▶️ Инструкция'!AI:AI},2,false)} -> #N/A | AM31: =IF($D31,"🔒",) | AN31: 0 | AO31: 0 | AP31: 0 | AQ31: 1 | AR31: 0 | AS31: 0 | AT31: ИП Иванов И.И. | AU31: WB | AV31: FBS | AW31: =AS31*H31 -> 0 | AX31: =(1/(AQ31))*H31*AS31 -> 0 | AY31: =AX31/BC31 -> #N/A | AZ31: 250 | BA31: =AZ31/H31 -> 0.25 | BB31: =H31-AW31 -> 1000 | BC31: =BX31 -> #N/A | BD31: =BC31*L31 -> #N/A | BE31: =H31*(1-I31)*L31 -> 0 | BF31: =IFERROR(BC31/BV31,) | BG31: =IFERROR(BC31/H31,) | BH31: =IFERROR(if(BW31>0,BC31/BW31,-BC31/BW31),) | BJ31: =IFERROR(__xludf.DUMMYFUNCTION("IF(AU31=data!A$5, IF(AV31=data!A$8, IF(T31=data!A$3, VLOOKUP(S31,filter('🔒 Доп. информация'!D:H,'🔒 Доп. информация'!C:C=T31),4,FALSE)+VLOOKUP(S31,filter('🔒 Доп. информация'!D:H,'🔒 Доп. информация'!C:C=T31),5,FALSE)*AJ31, IF(AND(MAX(AF31:AH31)<80,SUM(A"&"F31:AH31)<=160,AI31<20,XLOOKUP(M31,'📄 Комиссии'!C:C,'📄 Комиссии'!B:B)<>""Продукты""), VLOOKUP(S31,filter('🔒 Доп. информация'!D:H,'🔒 Доп. информация'!C:C=data!$A$3),4,FALSE)+VLOOKUP(S31,filter('🔒 Доп. информация'!D:H,'🔒 Доп. информация'!C:C=data!$A$3"&"),5,FALSE)*AJ31, VLOOKUP(S31,filter('🔒 Доп. информация'!D:H,'🔒 Доп. информация'!C:C=T31),4,FALSE)*ROUNDUP(AF31*AG31*AH31*L31/(120*80*175))/L31) ) *(AE31/2) ,) ,)*0"),0.0) -> 0 | BK31: =IFERROR(__xludf.DUMMYFUNCTION("IF(AU31=data!A$5, IF(AI31<=1,IF(AI31<=0.8,IF(AI31<=0.6,IF(AI31<=0.4,IF(AI31<=0.2,23,26),29),30),32)*VLOOKUP(S31,filter('🔒 Доп. информация'!D:E,'🔒 Доп. информация'!C:C=T31),2,FALSE)/'🔒 Доп. информация'!$K$9, IF(AV31=data!A$8,U31,1)*VLOOKUP(S31,filter('"&"🔒 Доп. информация'!D:E,'🔒 Доп. информация'!C:C=T31),2,FALSE)+ IF(AV31=data!A$8,U31,1)*VLOOKUP(S31,filter('🔒 Доп. информация'!D:F,'🔒 Доп. информация'!C:C=T31),3,FALSE)*AJ31) ,0)"),69.0) -> 69 | BL31: =IF($D31,"🔒",) | BM31: =IF($D31,"🔒",) | BN31: =VLOOKUP(T31,'🔒 Доп. информация'!J:P,7,false) -> 50 | BO31: =IF(AV31=data!A$9, (AA31+AO31+AP31+BJ31+BK31+BN31)+H31*AS31, (BJ31+BK31+BN31)+H31*AS31 ) -> 119 | BP31: =AA31+BJ31+BK31 -> 69 | BQ31: =H31*N31 -> 320 | BR31: =BP31+BQ31+AS31*H31+((1-AQ31)/AQ31)*BO31+AL31+H31*J31*1.1 -> #N/A | BS31: {=IF(VLOOKUP(AT31,{'▶️ Инструкция'!C:C,'▶️ Инструкция'!Y:Y},2,FALSE)=data!A$15, H31*(1-I31), (H31-BR31)) *VLOOKUP(AT31,{'▶️ Инструкция'!C:C,'▶️ Инструкция'!AD:AD},2,FALSE)/(1+VLOOKUP(AT31,{'▶️ Инструкция'!C:C,'▶️ Инструкция'!AD:AD},2,FALSE))} -> #N/A | BT31: {=IF(VLOOKUP(AT31,{'▶️ Инструкция'!C:C,'▶️ Инструкция'!Y:Y},2,FALSE)=data!A$15, H31*(1-I31)-BS31, (H31-BR31-BS31)) * VLOOKUP(AT31,{'▶️ Инструкция'!C:C,'▶️ Инструкция'!R:R},2,FALSE) +BS31} -> #N/A | BU31: =(G31*AR31)+if(AV31=data!A$9,AO31,AN31)+AP31+BR31+BT31 -> #N/A | BV31: =(G31*AR31)+if(AV31=data!A$9,AO31,AN31)+AP31+BT31+G31 -> #N/A | BW31: =H31-BR31 -> #N/A | BX31: =BW31-BV31 -> #N/A
A32: =if(D32=true,if(F32=data!A$1,data!A$10,data!A$11),) | B32: =AV32 -> FBS | C32: Название товара | D32: FALSE | E32: Имя | F32: {=IF(D32=TRUE,IF(IF(BG$3=VLOOKUP(AT32,{'▶️ Инструкция'!C:C,'▶️ Инструкция'!G:G},2,FALSE),BG32,BH32)>VLOOKUP(AT32,{'▶️ Инструкция'!C:C,'▶️ Инструкция'!N:N},2,FALSE),data!A$1,data!A$2),)} | G32: 0 | H32: 1000 | I32: 0 | J32: 0 | K32: =IF($D32,"🔒",) | L32: 0 | M32: Лопатки игрушечные | N32: =IFERROR(__xludf.DUMMYFUNCTION("ArrayFormula(let(category,VLOOKUP($M32, {'📄 Комиссии'!$C:$C , '📄 Комиссии'!$B:$B}, 2, 0), data,MATCH('🔒 Доп. информация'!$J$15:$J203,TRANSPOSE(SPLIT(INDEX('▶️ Инструкция'!$Q:$Q,MATCH($AT32,'▶️ Инструкция'!$R:$R,0)+2),"", "",FALSE)),0), options,COUNTA( "&"ifna( FILTER('🔒 Доп. информация'!$J$15:$J203,('🔒 Доп. информация'!$N$15:$N203=FALSE)*data*('🔒 Доп. информация'!$O$15:$O203=""Опция"")))), commission,VLOOKUP($M32,'📄 Комиссии'!$C:$E,IF($AV32=data!A$8,2,3),0), IF(NOT(ISBLANK($M32)),commission/100+ IFERR"&"OR(VLOOKUP($AT32,{'▶️ Инструкция'!$R:$R,'▶️ Инструкция'!$AK:$AK},2,0)+ IF((( category = ""Одежда"")+( category = ""Обувь"" ))*((options+SUM( ifna( FILTER('🔒 Доп. информация'!$M$15:$M203,('🔒 Доп. информация'!$N$15:$N203=FALSE)*data*('🔒 Доп. информация'!"&"$O$15:$O203=""Пакет"")))))>=5), -5% + 2%, IF((options>=1)* (COUNTA( ifna( FILTER('🔒 Доп. информация'!$J$15:$J203,('🔒 Доп. информация'!$N$15:$N203=FALSE)*data*('🔒 Доп. информация'!$O$15:$O203=""Пакет""))))>=1)* (commission>=14.5)* (category<> ""Одежда"&""")*( category <> ""Обувь"" ),-3% + 2%,0))))))"),0.32) -> 0.32 | O32: =IF($D32,"🔒",) | Q32: =IF($D32,"🔒",) | S32: Макс. из наших | T32: Короб | U32: 1 | V32: =IF($D32,"🔒",) | W32: =IF($D32,"🔒",) | X32: =IF($D32,"🔒",) | Y32: =IF($D32,"🔒",) | Z32: 0 | AA32: =1.7*(1+AJ32)*Z32 -> 0 | AB32: =IF($D32,"🔒",) | AC32: =IF($D32,"🔒",) | AD32: =IF($D32,"🔒",) | AE32: 30 | AF32: 0 | AG32: 0 | AH32: 0 | AI32: =(AF32*AG32*AH32)/1000 -> 0 | AJ32: =if(AI32>1,(AI32-1),0) -> 0 | AK32: =IF($D32,"🔒",) | AL32: {=H32*(1-I32)*VLOOKUP(AT32,{'▶️ Инструкция'!C:C,'▶️ Инструкция'!AI:AI},2,false)} -> #N/A | AM32: =IF($D32,"🔒",) | AN32: 0 | AO32: 0 | AP32: 0 | AQ32: 1 | AR32: 0 | AS32: 0 | AT32: ИП Иванов И.И. | AU32: WB | AV32: FBS | AW32: =AS32*H32 -> 0 | AX32: =(1/(AQ32))*H32*AS32 -> 0 | AY32: =AX32/BC32 -> #N/A | AZ32: 250 | BA32: =AZ32/H32 -> 0.25 | BB32: =H32-AW32 -> 1000 | BC32: =BX32 -> #N/A | BD32: =BC32*L32 -> #N/A | BE32: =H32*(1-I32)*L32 -> 0 | BF32: =IFERROR(BC32/BV32,) | BG32: =IFERROR(BC32/H32,) | BH32: =IFERROR(if(BW32>0,BC32/BW32,-BC32/BW32),) | BJ32: =IFERROR(__xludf.DUMMYFUNCTION("IF(AU32=data!A$5, IF(AV32=data!A$8, IF(T32=data!A$3, VLOOKUP(S32,filter('🔒 Доп. информация'!D:H,'🔒 Доп. информация'!C:C=T32),4,FALSE)+VLOOKUP(S32,filter('🔒 Доп. информация'!D:H,'🔒 Доп. информация'!C:C=T32),5,FALSE)*AJ32, IF(AND(MAX(AF32:AH32)<80,SUM(A"&"F32:AH32)<=160,AI32<20,XLOOKUP(M32,'📄 Комиссии'!C:C,'📄 Комиссии'!B:B)<>""Продукты""), VLOOKUP(S32,filter('🔒 Доп. информация'!D:H,'🔒 Доп. информация'!C:C=data!$A$3),4,FALSE)+VLOOKUP(S32,filter('🔒 Доп. информация'!D:H,'🔒 Доп. информация'!C:C=data!$A$3"&"),5,FALSE)*AJ32, VLOOKUP(S32,filter('🔒 Доп. информация'!D:H,'🔒 Доп. информация'!C:C=T32),4,FALSE)*ROUNDUP(AF32*AG32*AH32*L32/(120*80*175))/L32) ) *(AE32/2) ,) ,)*0"),0.0) -> 0 | BK32: =IFERROR(__xludf.DUMMYFUNCTION("IF(AU32=data!A$5, IF(AI32<=1,IF(AI32<=0.8,IF(AI32<=0.6,IF(AI32<=0.4,IF(AI32<=0.2,23,26),29),30),32)*VLOOKUP(S32,filter('🔒 Доп. информация'!D:E,'🔒 Доп. информация'!C:C=T32),2,FALSE)/'🔒 Доп. информация'!$K$9, IF(AV32=data!A$8,U32,1)*VLOOKUP(S32,filter('"&"🔒 Доп. информация'!D:E,'🔒 Доп. информация'!C:C=T32),2,FALSE)+ IF(AV32=data!A$8,U32,1)*VLOOKUP(S32,filter('🔒 Доп. информация'!D:F,'🔒 Доп. информация'!C:C=T32),3,FALSE)*AJ32) ,0)"),69.0) -> 69 | BL32: =IF($D32,"🔒",) | BM32: =IF($D32,"🔒",) | BN32: =VLOOKUP(T32,'🔒 Доп. информация'!J:P,7,false) -> 50 | BO32: =IF(AV32=data!A$9, (AA32+AO32+AP32+BJ32+BK32+BN32)+H32*AS32, (BJ32+BK32+BN32)+H32*AS32 ) -> 119 | BP32: =AA32+BJ32+BK32 -> 69 | BQ32: =H32*N32 -> 320 | BR32: =BP32+BQ32+AS32*H32+((1-AQ32)/AQ32)*BO32+AL32+H32*J32*1.1 -> #N/A | BS32: {=IF(VLOOKUP(AT32,{'▶️ Инструкция'!C:C,'▶️ Инструкция'!Y:Y},2,FALSE)=data!A$15, H32*(1-I32), (H32-BR32)) *VLOOKUP(AT32,{'▶️ Инструкция'!C:C,'▶️ Инструкция'!AD:AD},2,FALSE)/(1+VLOOKUP(AT32,{'▶️ Инструкция'!C:C,'▶️ Инструкция'!AD:AD},2,FALSE))} -> #N/A | BT32: {=IF(VLOOKUP(AT32,{'▶️ Инструкция'!C:C,'▶️ Инструкция'!Y:Y},2,FALSE)=data!A$15, H32*(1-I32)-BS32, (H32-BR32-BS32)) * VLOOKUP(AT32,{'▶️ Инструкция'!C:C,'▶️ Инструкция'!R:R},2,FALSE) +BS32} -> #N/A | BU32: =(G32*AR32)+if(AV32=data!A$9,AO32,AN32)+AP32+BR32+BT32 -> #N/A | BV32: =(G32*AR32)+if(AV32=data!A$9,AO32,AN32)+AP32+BT32+G32 -> #N/A | BW32: =H32-BR32 -> #N/A | BX32: =BW32-BV32 -> #N/A
A33: =if(D33=true,if(F33=data!A$1,data!A$10,data!A$11),) | B33: =AV33 -> FBS | C33: Название товара | D33: FALSE | E33: Имя | F33: {=IF(D33=TRUE,IF(IF(BG$3=VLOOKUP(AT33,{'▶️ Инструкция'!C:C,'▶️ Инструкция'!G:G},2,FALSE),BG33,BH33)>VLOOKUP(AT33,{'▶️ Инструкция'!C:C,'▶️ Инструкция'!N:N},2,FALSE),data!A$1,data!A$2),)} | G33: 0 | H33: 1000 | I33: 0 | J33: 0 | K33: =IF($D33,"🔒",) | L33: 0 | M33: Лопатки игрушечные | N33: =IFERROR(__xludf.DUMMYFUNCTION("ArrayFormula(let(category,VLOOKUP($M33, {'📄 Комиссии'!$C:$C , '📄 Комиссии'!$B:$B}, 2, 0), data,MATCH('🔒 Доп. информация'!$J$15:$J203,TRANSPOSE(SPLIT(INDEX('▶️ Инструкция'!$Q:$Q,MATCH($AT33,'▶️ Инструкция'!$R:$R,0)+2),"", "",FALSE)),0), options,COUNTA( "&"ifna( FILTER('🔒 Доп. информация'!$J$15:$J203,('🔒 Доп. информация'!$N$15:$N203=FALSE)*data*('🔒 Доп. информация'!$O$15:$O203=""Опция"")))), commission,VLOOKUP($M33,'📄 Комиссии'!$C:$E,IF($AV33=data!A$8,2,3),0), IF(NOT(ISBLANK($M33)),commission/100+ IFERR"&"OR(VLOOKUP($AT33,{'▶️ Инструкция'!$R:$R,'▶️ Инструкция'!$AK:$AK},2,0)+ IF((( category = ""Одежда"")+( category = ""Обувь"" ))*((options+SUM( ifna( FILTER('🔒 Доп. информация'!$M$15:$M203,('🔒 Доп. информация'!$N$15:$N203=FALSE)*data*('🔒 Доп. информация'!"&"$O$15:$O203=""Пакет"")))))>=5), -5% + 2%, IF((options>=1)* (COUNTA( ifna( FILTER('🔒 Доп. информация'!$J$15:$J203,('🔒 Доп. информация'!$N$15:$N203=FALSE)*data*('🔒 Доп. информация'!$O$15:$O203=""Пакет""))))>=1)* (commission>=14.5)* (category<> ""Одежда"&""")*( category <> ""Обувь"" ),-3% + 2%,0))))))"),0.32) -> 0.32 | O33: =IF($D33,"🔒",) | Q33: =IF($D33,"🔒",) | S33: Макс. из наших | T33: Короб | U33: 1 | V33: =IF($D33,"🔒",) | W33: =IF($D33,"🔒",) | X33: =IF($D33,"🔒",) | Y33: =IF($D33,"🔒",) | Z33: 0 | AA33: =1.7*(1+AJ33)*Z33 -> 0 | AB33: =IF($D33,"🔒",) | AC33: =IF($D33,"🔒",) | AD33: =IF($D33,"🔒",) | AE33: 30 | AF33: 0 | AG33: 0 | AH33: 0 | AI33: =(AF33*AG33*AH33)/1000 -> 0 | AJ33: =if(AI33>1,(AI33-1),0) -> 0 | AK33: =IF($D33,"🔒",) | AL33: {=H33*(1-I33)*VLOOKUP(AT33,{'▶️ Инструкция'!C:C,'▶️ Инструкция'!AI:AI},2,false)} -> #N/A | AM33: =IF($D33,"🔒",) | AN33: 0 | AO33: 0 | AP33: 0 | AQ33: 1 | AR33: 0 | AS33: 0 | AT33: ИП Иванов И.И. | AU33: WB | AV33: FBS | AW33: =AS33*H33 -> 0 | AX33: =(1/(AQ33))*H33*AS33 -> 0 | AY33: =AX33/BC33 -> #N/A | AZ33: 250 | BA33: =AZ33/H33 -> 0.25 | BB33: =H33-AW33 -> 1000 | BC33: =BX33 -> #N/A | BD33: =BC33*L33 -> #N/A | BE33: =H33*(1-I33)*L33 -> 0 | BF33: =IFERROR(BC33/BV33,) | BG33: =IFERROR(BC33/H33,) | BH33: =IFERROR(if(BW33>0,BC33/BW33,-BC33/BW33),) | BJ33: =IFERROR(__xludf.DUMMYFUNCTION("IF(AU33=data!A$5, IF(AV33=data!A$8, IF(T33=data!A$3, VLOOKUP(S33,filter('🔒 Доп. информация'!D:H,'🔒 Доп. информация'!C:C=T33),4,FALSE)+VLOOKUP(S33,filter('🔒 Доп. информация'!D:H,'🔒 Доп. информация'!C:C=T33),5,FALSE)*AJ33, IF(AND(MAX(AF33:AH33)<80,SUM(A"&"F33:AH33)<=160,AI33<20,XLOOKUP(M33,'📄 Комиссии'!C:C,'📄 Комиссии'!B:B)<>""Продукты""), VLOOKUP(S33,filter('🔒 Доп. информация'!D:H,'🔒 Доп. информация'!C:C=data!$A$3),4,FALSE)+VLOOKUP(S33,filter('🔒 Доп. информация'!D:H,'🔒 Доп. информация'!C:C=data!$A$3"&"),5,FALSE)*AJ33, VLOOKUP(S33,filter('🔒 Доп. информация'!D:H,'🔒 Доп. информация'!C:C=T33),4,FALSE)*ROUNDUP(AF33*AG33*AH33*L33/(120*80*175))/L33) ) *(AE33/2) ,) ,)*0"),0.0) -> 0 | BK33: =IFERROR(__xludf.DUMMYFUNCTION("IF(AU33=data!A$5, IF(AI33<=1,IF(AI33<=0.8,IF(AI33<=0.6,IF(AI33<=0.4,IF(AI33<=0.2,23,26),29),30),32)*VLOOKUP(S33,filter('🔒 Доп. информация'!D:E,'🔒 Доп. информация'!C:C=T33),2,FALSE)/'🔒 Доп. информация'!$K$9, IF(AV33=data!A$8,U33,1)*VLOOKUP(S33,filter('"&"🔒 Доп. информация'!D:E,'🔒 Доп. информация'!C:C=T33),2,FALSE)+ IF(AV33=data!A$8,U33,1)*VLOOKUP(S33,filter('🔒 Доп. информация'!D:F,'🔒 Доп. информация'!C:C=T33),3,FALSE)*AJ33) ,0)"),69.0) -> 69 | BL33: =IF($D33,"🔒",) | BM33: =IF($D33,"🔒",) | BN33: =VLOOKUP(T33,'🔒 Доп. информация'!J:P,7,false) -> 50 | BO33: =IF(AV33=data!A$9, (AA33+AO33+AP33+BJ33+BK33+BN33)+H33*AS33, (BJ33+BK33+BN33)+H33*AS33 ) -> 119 | BP33: =AA33+BJ33+BK33 -> 69 | BQ33: =H33*N33 -> 320 | BR33: =BP33+BQ33+AS33*H33+((1-AQ33)/AQ33)*BO33+AL33+H33*J33*1.1 -> #N/A | BS33: {=IF(VLOOKUP(AT33,{'▶️ Инструкция'!C:C,'▶️ Инструкция'!Y:Y},2,FALSE)=data!A$15, H33*(1-I33), (H33-BR33)) *VLOOKUP(AT33,{'▶️ Инструкция'!C:C,'▶️ Инструкция'!AD:AD},2,FALSE)/(1+VLOOKUP(AT33,{'▶️ Инструкция'!C:C,'▶️ Инструкция'!AD:AD},2,FALSE))} -> #N/A | BT33: {=IF(VLOOKUP(AT33,{'▶️ Инструкция'!C:C,'▶️ Инструкция'!Y:Y},2,FALSE)=data!A$15, H33*(1-I33)-BS33, (H33-BR33-BS33)) * VLOOKUP(AT33,{'▶️ Инструкция'!C:C,'▶️ Инструкция'!R:R},2,FALSE) +BS33} -> #N/A | BU33: =(G33*AR33)+if(AV33=data!A$9,AO33,AN33)+AP33+BR33+BT33 -> #N/A | BV33: =(G33*AR33)+if(AV33=data!A$9,AO33,AN33)+AP33+BT33+G33 -> #N/A | BW33: =H33-BR33 -> #N/A | BX33: =BW33-BV33 -> #N/A
A34: =if(D34=true,if(F34=data!A$1,data!A$10,data!A$11),) | B34: =AV34 -> FBS | C34: Название товара | D34: FALSE | E34: Имя | F34: {=IF(D34=TRUE,IF(IF(BG$3=VLOOKUP(AT34,{'▶️ Инструкция'!C:C,'▶️ Инструкция'!G:G},2,FALSE),BG34,BH34)>VLOOKUP(AT34,{'▶️ Инструкция'!C:C,'▶️ Инструкция'!N:N},2,FALSE),data!A$1,data!A$2),)} | G34: 0 | H34: 1000 | I34: 0 | J34: 0 | K34: =IF($D34,"🔒",) | L34: 0 | M34: Лопатки игрушечные | N34: =IFERROR(__xludf.DUMMYFUNCTION("ArrayFormula(let(category,VLOOKUP($M34, {'📄 Комиссии'!$C:$C , '📄 Комиссии'!$B:$B}, 2, 0), data,MATCH('🔒 Доп. информация'!$J$15:$J203,TRANSPOSE(SPLIT(INDEX('▶️ Инструкция'!$Q:$Q,MATCH($AT34,'▶️ Инструкция'!$R:$R,0)+2),"", "",FALSE)),0), options,COUNTA( "&"ifna( FILTER('🔒 Доп. информация'!$J$15:$J203,('🔒 Доп. информация'!$N$15:$N203=FALSE)*data*('🔒 Доп. информация'!$O$15:$O203=""Опция"")))), commission,VLOOKUP($M34,'📄 Комиссии'!$C:$E,IF($AV34=data!A$8,2,3),0), IF(NOT(ISBLANK($M34)),commission/100+ IFERR"&"OR(VLOOKUP($AT34,{'▶️ Инструкция'!$R:$R,'▶️ Инструкция'!$AK:$AK},2,0)+ IF((( category = ""Одежда"")+( category = ""Обувь"" ))*((options+SUM( ifna( FILTER('🔒 Доп. информация'!$M$15:$M203,('🔒 Доп. информация'!$N$15:$N203=FALSE)*data*('🔒 Доп. информация'!"&"$O$15:$O203=""Пакет"")))))>=5), -5% + 2%, IF((options>=1)* (COUNTA( ifna( FILTER('🔒 Доп. информация'!$J$15:$J203,('🔒 Доп. информация'!$N$15:$N203=FALSE)*data*('🔒 Доп. информация'!$O$15:$O203=""Пакет""))))>=1)* (commission>=14.5)* (category<> ""Одежда"&""")*( category <> ""Обувь"" ),-3% + 2%,0))))))"),0.32) -> 0.32 | O34: =IF($D34,"🔒",) | Q34: =IF($D34,"🔒",) | S34: Макс. из наших | T34: Короб | U34: 1 | V34: =IF($D34,"🔒",) | W34: =IF($D34,"🔒",) | X34: =IF($D34,"🔒",) | Y34: =IF($D34,"🔒",) | Z34: 0 | AA34: =1.7*(1+AJ34)*Z34 -> 0 | AB34: =IF($D34,"🔒",) | AC34: =IF($D34,"🔒",) | AD34: =IF($D34,"🔒",) | AE34: 30 | AF34: 0 | AG34: 0 | AH34: 0 | AI34: =(AF34*AG34*AH34)/1000 -> 0 | AJ34: =if(AI34>1,(AI34-1),0) -> 0 | AK34: =IF($D34,"🔒",) | AL34: {=H34*(1-I34)*VLOOKUP(AT34,{'▶️ Инструкция'!C:C,'▶️ Инструкция'!AI:AI},2,false)} -> #N/A | AM34: =IF($D34,"🔒",) | AN34: 0 | AO34: 0 | AP34: 0 | AQ34: 1 | AR34: 0 | AS34: 0 | AT34: ИП Иванов И.И. | AU34: WB | AV34: FBS | AW34: =AS34*H34 -> 0 | AX34: =(1/(AQ34))*H34*AS34 -> 0 | AY34: =AX34/BC34 -> #N/A | AZ34: 250 | BA34: =AZ34/H34 -> 0.25 | BB34: =H34-AW34 -> 1000 | BC34: =BX34 -> #N/A | BD34: =BC34*L34 -> #N/A | BE34: =H34*(1-I34)*L34 -> 0 | BF34: =IFERROR(BC34/BV34,) | BG34: =IFERROR(BC34/H34,) | BH34: =IFERROR(if(BW34>0,BC34/BW34,-BC34/BW34),) | BJ34: =IFERROR(__xludf.DUMMYFUNCTION("IF(AU34=data!A$5, IF(AV34=data!A$8, IF(T34=data!A$3, VLOOKUP(S34,filter('🔒 Доп. информация'!D:H,'🔒 Доп. информация'!C:C=T34),4,FALSE)+VLOOKUP(S34,filter('🔒 Доп. информация'!D:H,'🔒 Доп. информация'!C:C=T34),5,FALSE)*AJ34, IF(AND(MAX(AF34:AH34)<80,SUM(A"&"F34:AH34)<=160,AI34<20,XLOOKUP(M34,'📄 Комиссии'!C:C,'📄 Комиссии'!B:B)<>""Продукты""), VLOOKUP(S34,filter('🔒 Доп. информация'!D:H,'🔒 Доп. информация'!C:C=data!$A$3),4,FALSE)+VLOOKUP(S34,filter('🔒 Доп. информация'!D:H,'🔒 Доп. информация'!C:C=data!$A$3"&"),5,FALSE)*AJ34, VLOOKUP(S34,filter('🔒 Доп. информация'!D:H,'🔒 Доп. информация'!C:C=T34),4,FALSE)*ROUNDUP(AF34*AG34*AH34*L34/(120*80*175))/L34) ) *(AE34/2) ,) ,)*0"),0.0) -> 0 | BK34: =IFERROR(__xludf.DUMMYFUNCTION("IF(AU34=data!A$5, IF(AI34<=1,IF(AI34<=0.8,IF(AI34<=0.6,IF(AI34<=0.4,IF(AI34<=0.2,23,26),29),30),32)*VLOOKUP(S34,filter('🔒 Доп. информация'!D:E,'🔒 Доп. информация'!C:C=T34),2,FALSE)/'🔒 Доп. информация'!$K$9, IF(AV34=data!A$8,U34,1)*VLOOKUP(S34,filter('"&"🔒 Доп. информация'!D:E,'🔒 Доп. информация'!C:C=T34),2,FALSE)+ IF(AV34=data!A$8,U34,1)*VLOOKUP(S34,filter('🔒 Доп. информация'!D:F,'🔒 Доп. информация'!C:C=T34),3,FALSE)*AJ34) ,0)"),69.0) -> 69 | BL34: =IF($D34,"🔒",) | BM34: =IF($D34,"🔒",) | BN34: =VLOOKUP(T34,'🔒 Доп. информация'!J:P,7,false) -> 50 | BO34: =IF(AV34=data!A$9, (AA34+AO34+AP34+BJ34+BK34+BN34)+H34*AS34, (BJ34+BK34+BN34)+H34*AS34 ) -> 119 | BP34: =AA34+BJ34+BK34 -> 69 | BQ34: =H34*N34 -> 320 | BR34: =BP34+BQ34+AS34*H34+((1-AQ34)/AQ34)*BO34+AL34+H34*J34*1.1 -> #N/A | BS34: {=IF(VLOOKUP(AT34,{'▶️ Инструкция'!C:C,'▶️ Инструкция'!Y:Y},2,FALSE)=data!A$15, H34*(1-I34), (H34-BR34)) *VLOOKUP(AT34,{'▶️ Инструкция'!C:C,'▶️ Инструкция'!AD:AD},2,FALSE)/(1+VLOOKUP(AT34,{'▶️ Инструкция'!C:C,'▶️ Инструкция'!AD:AD},2,FALSE))} -> #N/A | BT34: {=IF(VLOOKUP(AT34,{'▶️ Инструкция'!C:C,'▶️ Инструкция'!Y:Y},2,FALSE)=data!A$15, H34*(1-I34)-BS34, (H34-BR34-BS34)) * VLOOKUP(AT34,{'▶️ Инструкция'!C:C,'▶️ Инструкция'!R:R},2,FALSE) +BS34} -> #N/A | BU34: =(G34*AR34)+if(AV34=data!A$9,AO34,AN34)+AP34+BR34+BT34 -> #N/A | BV34: =(G34*AR34)+if(AV34=data!A$9,AO34,AN34)+AP34+BT34+G34 -> #N/A | BW34: =H34-BR34 -> #N/A | BX34: =BW34-BV34 -> #N/A
A35: =if(D35=true,if(F35=data!A$1,data!A$10,data!A$11),) | B35: =AV35 -> FBS | C35: Название товара | D35: FALSE | E35: Имя | F35: {=IF(D35=TRUE,IF(IF(BG$3=VLOOKUP(AT35,{'▶️ Инструкция'!C:C,'▶️ Инструкция'!G:G},2,FALSE),BG35,BH35)>VLOOKUP(AT35,{'▶️ Инструкция'!C:C,'▶️ Инструкция'!N:N},2,FALSE),data!A$1,data!A$2),)} | G35: 0 | H35: 1000 | I35: 0 | J35: 0 | K35: =IF($D35,"🔒",) | L35: 0 | M35: Лопатки игрушечные | N35: =IFERROR(__xludf.DUMMYFUNCTION("ArrayFormula(let(category,VLOOKUP($M35, {'📄 Комиссии'!$C:$C , '📄 Комиссии'!$B:$B}, 2, 0), data,MATCH('🔒 Доп. информация'!$J$15:$J203,TRANSPOSE(SPLIT(INDEX('▶️ Инструкция'!$Q:$Q,MATCH($AT35,'▶️ Инструкция'!$R:$R,0)+2),"", "",FALSE)),0), options,COUNTA( "&"ifna( FILTER('🔒 Доп. информация'!$J$15:$J203,('🔒 Доп. информация'!$N$15:$N203=FALSE)*data*('🔒 Доп. информация'!$O$15:$O203=""Опция"")))), commission,VLOOKUP($M35,'📄 Комиссии'!$C:$E,IF($AV35=data!A$8,2,3),0), IF(NOT(ISBLANK($M35)),commission/100+ IFERR"&"OR(VLOOKUP($AT35,{'▶️ Инструкция'!$R:$R,'▶️ Инструкция'!$AK:$AK},2,0)+ IF((( category = ""Одежда"")+( category = ""Обувь"" ))*((options+SUM( ifna( FILTER('🔒 Доп. информация'!$M$15:$M203,('🔒 Доп. информация'!$N$15:$N203=FALSE)*data*('🔒 Доп. информация'!"&"$O$15:$O203=""Пакет"")))))>=5), -5% + 2%, IF((options>=1)* (COUNTA( ifna( FILTER('🔒 Доп. информация'!$J$15:$J203,('🔒 Доп. информация'!$N$15:$N203=FALSE)*data*('🔒 Доп. информация'!$O$15:$O203=""Пакет""))))>=1)* (commission>=14.5)* (category<> ""Одежда"&""")*( category <> ""Обувь"" ),-3% + 2%,0))))))"),0.32) -> 0.32 | O35: =IF($D35,"🔒",) | Q35: =IF($D35,"🔒",) | S35: Макс. из наших | T35: Короб | U35: 1 | V35: =IF($D35,"🔒",) | W35: =IF($D35,"🔒",) | X35: =IF($D35,"🔒",) | Y35: =IF($D35,"🔒",) | Z35: 0 | AA35: =1.7*(1+AJ35)*Z35 -> 0 | AB35: =IF($D35,"🔒",) | AC35: =IF($D35,"🔒",) | AD35: =IF($D35,"🔒",) | AE35: 30 | AF35: 0 | AG35: 0 | AH35: 0 | AI35: =(AF35*AG35*AH35)/1000 -> 0 | AJ35: =if(AI35>1,(AI35-1),0) -> 0 | AK35: =IF($D35,"🔒",) | AL35: {=H35*(1-I35)*VLOOKUP(AT35,{'▶️ Инструкция'!C:C,'▶️ Инструкция'!AI:AI},2,false)} -> #N/A | AM35: =IF($D35,"🔒",) | AN35: 0 | AO35: 0 | AP35: 0 | AQ35: 1 | AR35: 0 | AS35: 0 | AT35: ИП Иванов И.И. | AU35: WB | AV35: FBS | AW35: =AS35*H35 -> 0 | AX35: =(1/(AQ35))*H35*AS35 -> 0 | AY35: =AX35/BC35 -> #N/A | AZ35: 250 | BA35: =AZ35/H35 -> 0.25 | BB35: =H35-AW35 -> 1000 | BC35: =BX35 -> #N/A | BD35: =BC35*L35 -> #N/A | BE35: =H35*(1-I35)*L35 -> 0 | BF35: =IFERROR(BC35/BV35,) | BG35: =IFERROR(BC35/H35,) | BH35: =IFERROR(if(BW35>0,BC35/BW35,-BC35/BW35),) | BJ35: =IFERROR(__xludf.DUMMYFUNCTION("IF(AU35=data!A$5, IF(AV35=data!A$8, IF(T35=data!A$3, VLOOKUP(S35,filter('🔒 Доп. информация'!D:H,'🔒 Доп. информация'!C:C=T35),4,FALSE)+VLOOKUP(S35,filter('🔒 Доп. информация'!D:H,'🔒 Доп. информация'!C:C=T35),5,FALSE)*AJ35, IF(AND(MAX(AF35:AH35)<80,SUM(A"&"F35:AH35)<=160,AI35<20,XLOOKUP(M35,'📄 Комиссии'!C:C,'📄 Комиссии'!B:B)<>""Продукты""), VLOOKUP(S35,filter('🔒 Доп. информация'!D:H,'🔒 Доп. информация'!C:C=data!$A$3),4,FALSE)+VLOOKUP(S35,filter('🔒 Доп. информация'!D:H,'🔒 Доп. информация'!C:C=data!$A$3"&"),5,FALSE)*AJ35, VLOOKUP(S35,filter('🔒 Доп. информация'!D:H,'🔒 Доп. информация'!C:C=T35),4,FALSE)*ROUNDUP(AF35*AG35*AH35*L35/(120*80*175))/L35) ) *(AE35/2) ,) ,)*0"),0.0) -> 0 | BK35: =IFERROR(__xludf.DUMMYFUNCTION("IF(AU35=data!A$5, IF(AI35<=1,IF(AI35<=0.8,IF(AI35<=0.6,IF(AI35<=0.4,IF(AI35<=0.2,23,26),29),30),32)*VLOOKUP(S35,filter('🔒 Доп. информация'!D:E,'🔒 Доп. информация'!C:C=T35),2,FALSE)/'🔒 Доп. информация'!$K$9, IF(AV35=data!A$8,U35,1)*VLOOKUP(S35,filter('"&"🔒 Доп. информация'!D:E,'🔒 Доп. информация'!C:C=T35),2,FALSE)+ IF(AV35=data!A$8,U35,1)*VLOOKUP(S35,filter('🔒 Доп. информация'!D:F,'🔒 Доп. информация'!C:C=T35),3,FALSE)*AJ35) ,0)"),69.0) -> 69 | BL35: =IF($D35,"🔒",) | BM35: =IF($D35,"🔒",) | BN35: =VLOOKUP(T35,'🔒 Доп. информация'!J:P,7,false) -> 50 | BO35: =IF(AV35=data!A$9, (AA35+AO35+AP35+BJ35+BK35+BN35)+H35*AS35, (BJ35+BK35+BN35)+H35*AS35 ) -> 119 | BP35: =AA35+BJ35+BK35 -> 69 | BQ35: =H35*N35 -> 320 | BR35: =BP35+BQ35+AS35*H35+((1-AQ35)/AQ35)*BO35+AL35+H35*J35*1.1 -> #N/A | BS35: {=IF(VLOOKUP(AT35,{'▶️ Инструкция'!C:C,'▶️ Инструкция'!Y:Y},2,FALSE)=data!A$15, H35*(1-I35), (H35-BR35)) *VLOOKUP(AT35,{'▶️ Инструкция'!C:C,'▶️ Инструкция'!AD:AD},2,FALSE)/(1+VLOOKUP(AT35,{'▶️ Инструкция'!C:C,'▶️ Инструкция'!AD:AD},2,FALSE))} -> #N/A | BT35: {=IF(VLOOKUP(AT35,{'▶️ Инструкция'!C:C,'▶️ Инструкция'!Y:Y},2,FALSE)=data!A$15, H35*(1-I35)-BS35, (H35-BR35-BS35)) * VLOOKUP(AT35,{'▶️ Инструкция'!C:C,'▶️ Инструкция'!R:R},2,FALSE) +BS35} -> #N/A | BU35: =(G35*AR35)+if(AV35=data!A$9,AO35,AN35)+AP35+BR35+BT35 -> #N/A | BV35: =(G35*AR35)+if(AV35=data!A$9,AO35,AN35)+AP35+BT35+G35 -> #N/A | BW35: =H35-BR35 -> #N/A | BX35: =BW35-BV35 -> #N/A
A36: =if(D36=true,if(F36=data!A$1,data!A$10,data!A$11),) | B36: =AV36 -> FBS | C36: Название товара | D36: FALSE | E36: Имя | F36: {=IF(D36=TRUE,IF(IF(BG$3=VLOOKUP(AT36,{'▶️ Инструкция'!C:C,'▶️ Инструкция'!G:G},2,FALSE),BG36,BH36)>VLOOKUP(AT36,{'▶️ Инструкция'!C:C,'▶️ Инструкция'!N:N},2,FALSE),data!A$1,data!A$2),)} | G36: 0 | H36: 1000 | I36: 0 | J36: 0 | K36: =IF($D36,"🔒",) | L36: 0 | M36: Лопатки игрушечные | N36: =IFERROR(__xludf.DUMMYFUNCTION("ArrayFormula(let(category,VLOOKUP($M36, {'📄 Комиссии'!$C:$C , '📄 Комиссии'!$B:$B}, 2, 0), data,MATCH('🔒 Доп. информация'!$J$15:$J203,TRANSPOSE(SPLIT(INDEX('▶️ Инструкция'!$Q:$Q,MATCH($AT36,'▶️ Инструкция'!$R:$R,0)+2),"", "",FALSE)),0), options,COUNTA( "&"ifna( FILTER('🔒 Доп. информация'!$J$15:$J203,('🔒 Доп. информация'!$N$15:$N203=FALSE)*data*('🔒 Доп. информация'!$O$15:$O203=""Опция"")))), commission,VLOOKUP($M36,'📄 Комиссии'!$C:$E,IF($AV36=data!A$8,2,3),0), IF(NOT(ISBLANK($M36)),commission/100+ IFERR"&"OR(VLOOKUP($AT36,{'▶️ Инструкция'!$R:$R,'▶️ Инструкция'!$AK:$AK},2,0)+ IF((( category = ""Одежда"")+( category = ""Обувь"" ))*((options+SUM( ifna( FILTER('🔒 Доп. информация'!$M$15:$M203,('🔒 Доп. информация'!$N$15:$N203=FALSE)*data*('🔒 Доп. информация'!"&"$O$15:$O203=""Пакет"")))))>=5), -5% + 2%, IF((options>=1)* (COUNTA( ifna( FILTER('🔒 Доп. информация'!$J$15:$J203,('🔒 Доп. информация'!$N$15:$N203=FALSE)*data*('🔒 Доп. информация'!$O$15:$O203=""Пакет""))))>=1)* (commission>=14.5)* (category<> ""Одежда"&""")*( category <> ""Обувь"" ),-3% + 2%,0))))))"),0.32) -> 0.32 | O36: =IF($D36,"🔒",) | Q36: =IF($D36,"🔒",) | S36: Макс. из наших | T36: Короб | U36: 1 | V36: =IF($D36,"🔒",) | W36: =IF($D36,"🔒",) | X36: =IF($D36,"🔒",) | Y36: =IF($D36,"🔒",) | Z36: 0 | AA36: =1.7*(1+AJ36)*Z36 -> 0 | AB36: =IF($D36,"🔒",) | AC36: =IF($D36,"🔒",) | AD36: =IF($D36,"🔒",) | AE36: 30 | AF36: 0 | AG36: 0 | AH36: 0 | AI36: =(AF36*AG36*AH36)/1000 -> 0 | AJ36: =if(AI36>1,(AI36-1),0) -> 0 | AK36: =IF($D36,"🔒",) | AL36: {=H36*(1-I36)*VLOOKUP(AT36,{'▶️ Инструкция'!C:C,'▶️ Инструкция'!AI:AI},2,false)} -> #N/A | AM36: =IF($D36,"🔒",) | AN36: 0 | AO36: 0 | AP36: 0 | AQ36: 1 | AR36: 0 | AS36: 0 | AT36: ИП Иванов И.И. | AU36: WB | AV36: FBS | AW36: =AS36*H36 -> 0 | AX36: =(1/(AQ36))*H36*AS36 -> 0 | AY36: =AX36/BC36 -> #N/A | AZ36: 250 | BA36: =AZ36/H36 -> 0.25 | BB36: =H36-AW36 -> 1000 | BC36: =BX36 -> #N/A | BD36: =BC36*L36 -> #N/A | BE36: =H36*(1-I36)*L36 -> 0 | BF36: =IFERROR(BC36/BV36,) | BG36: =IFERROR(BC36/H36,) | BH36: =IFERROR(if(BW36>0,BC36/BW36,-BC36/BW36),) | BJ36: =IFERROR(__xludf.DUMMYFUNCTION("IF(AU36=data!A$5, IF(AV36=data!A$8, IF(T36=data!A$3, VLOOKUP(S36,filter('🔒 Доп. информация'!D:H,'🔒 Доп. информация'!C:C=T36),4,FALSE)+VLOOKUP(S36,filter('🔒 Доп. информация'!D:H,'🔒 Доп. информация'!C:C=T36),5,FALSE)*AJ36, IF(AND(MAX(AF36:AH36)<80,SUM(A"&"F36:AH36)<=160,AI36<20,XLOOKUP(M36,'📄 Комиссии'!C:C,'📄 Комиссии'!B:B)<>""Продукты""), VLOOKUP(S36,filter('🔒 Доп. информация'!D:H,'🔒 Доп. информация'!C:C=data!$A$3),4,FALSE)+VLOOKUP(S36,filter('🔒 Доп. информация'!D:H,'🔒 Доп. информация'!C:C=data!$A$3"&"),5,FALSE)*AJ36, VLOOKUP(S36,filter('🔒 Доп. информация'!D:H,'🔒 Доп. информация'!C:C=T36),4,FALSE)*ROUNDUP(AF36*AG36*AH36*L36/(120*80*175))/L36) ) *(AE36/2) ,) ,)*0"),0.0) -> 0 | BK36: =IFERROR(__xludf.DUMMYFUNCTION("IF(AU36=data!A$5, IF(AI36<=1,IF(AI36<=0.8,IF(AI36<=0.6,IF(AI36<=0.4,IF(AI36<=0.2,23,26),29),30),32)*VLOOKUP(S36,filter('🔒 Доп. информация'!D:E,'🔒 Доп. информация'!C:C=T36),2,FALSE)/'🔒 Доп. информация'!$K$9, IF(AV36=data!A$8,U36,1)*VLOOKUP(S36,filter('"&"🔒 Доп. информация'!D:E,'🔒 Доп. информация'!C:C=T36),2,FALSE)+ IF(AV36=data!A$8,U36,1)*VLOOKUP(S36,filter('🔒 Доп. информация'!D:F,'🔒 Доп. информация'!C:C=T36),3,FALSE)*AJ36) ,0)"),69.0) -> 69 | BL36: =IF($D36,"🔒",) | BM36: =IF($D36,"🔒",) | BN36: =VLOOKUP(T36,'🔒 Доп. информация'!J:P,7,false) -> 50 | BO36: =IF(AV36=data!A$9, (AA36+AO36+AP36+BJ36+BK36+BN36)+H36*AS36, (BJ36+BK36+BN36)+H36*AS36 ) -> 119 | BP36: =AA36+BJ36+BK36 -> 69 | BQ36: =H36*N36 -> 320 | BR36: =BP36+BQ36+AS36*H36+((1-AQ36)/AQ36)*BO36+AL36+H36*J36*1.1 -> #N/A | BS36: {=IF(VLOOKUP(AT36,{'▶️ Инструкция'!C:C,'▶️ Инструкция'!Y:Y},2,FALSE)=data!A$15, H36*(1-I36), (H36-BR36)) *VLOOKUP(AT36,{'▶️ Инструкция'!C:C,'▶️ Инструкция'!AD:AD},2,FALSE)/(1+VLOOKUP(AT36,{'▶️ Инструкция'!C:C,'▶️ Инструкция'!AD:AD},2,FALSE))} -> #N/A | BT36: {=IF(VLOOKUP(AT36,{'▶️ Инструкция'!C:C,'▶️ Инструкция'!Y:Y},2,FALSE)=data!A$15, H36*(1-I36)-BS36, (H36-BR36-BS36)) * VLOOKUP(AT36,{'▶️ Инструкция'!C:C,'▶️ Инструкция'!R:R},2,FALSE) +BS36} -> #N/A | BU36: =(G36*AR36)+if(AV36=data!A$9,AO36,AN36)+AP36+BR36+BT36 -> #N/A | BV36: =(G36*AR36)+if(AV36=data!A$9,AO36,AN36)+AP36+BT36+G36 -> #N/A | BW36: =H36-BR36 -> #N/A | BX36: =BW36-BV36 -> #N/A
A37: =if(D37=true,if(F37=data!A$1,data!A$10,data!A$11),) | B37: =AV37 -> FBS | C37: Название товара | D37: FALSE | E37: Имя | F37: {=IF(D37=TRUE,IF(IF(BG$3=VLOOKUP(AT37,{'▶️ Инструкция'!C:C,'▶️ Инструкция'!G:G},2,FALSE),BG37,BH37)>VLOOKUP(AT37,{'▶️ Инструкция'!C:C,'▶️ Инструкция'!N:N},2,FALSE),data!A$1,data!A$2),)} | G37: 0 | H37: 1000 | I37: 0 | J37: 0 | K37: =IF($D37,"🔒",) | L37: 0 | M37: Лопатки игрушечные | N37: =IFERROR(__xludf.DUMMYFUNCTION("ArrayFormula(let(category,VLOOKUP($M37, {'📄 Комиссии'!$C:$C , '📄 Комиссии'!$B:$B}, 2, 0), data,MATCH('🔒 Доп. информация'!$J$15:$J203,TRANSPOSE(SPLIT(INDEX('▶️ Инструкция'!$Q:$Q,MATCH($AT37,'▶️ Инструкция'!$R:$R,0)+2),"", "",FALSE)),0), options,COUNTA( "&"ifna( FILTER('🔒 Доп. информация'!$J$15:$J203,('🔒 Доп. информация'!$N$15:$N203=FALSE)*data*('🔒 Доп. информация'!$O$15:$O203=""Опция"")))), commission,VLOOKUP($M37,'📄 Комиссии'!$C:$E,IF($AV37=data!A$8,2,3),0), IF(NOT(ISBLANK($M37)),commission/100+ IFERR"&"OR(VLOOKUP($AT37,{'▶️ Инструкция'!$R:$R,'▶️ Инструкция'!$AK:$AK},2,0)+ IF((( category = ""Одежда"")+( category = ""Обувь"" ))*((options+SUM( ifna( FILTER('🔒 Доп. информация'!$M$15:$M203,('🔒 Доп. информация'!$N$15:$N203=FALSE)*data*('🔒 Доп. информация'!"&"$O$15:$O203=""Пакет"")))))>=5), -5% + 2%, IF((options>=1)* (COUNTA( ifna( FILTER('🔒 Доп. информация'!$J$15:$J203,('🔒 Доп. информация'!$N$15:$N203=FALSE)*data*('🔒 Доп. информация'!$O$15:$O203=""Пакет""))))>=1)* (commission>=14.5)* (category<> ""Одежда"&""")*( category <> ""Обувь"" ),-3% + 2%,0))))))"),0.32) -> 0.32 | O37: =IF($D37,"🔒",) | Q37: =IF($D37,"🔒",) | S37: Макс. из наших | T37: Короб | U37: 1 | V37: =IF($D37,"🔒",) | W37: =IF($D37,"🔒",) | X37: =IF($D37,"🔒",) | Y37: =IF($D37,"🔒",) | Z37: 0 | AA37: =1.7*(1+AJ37)*Z37 -> 0 | AB37: =IF($D37,"🔒",) | AC37: =IF($D37,"🔒",) | AD37: =IF($D37,"🔒",) | AE37: 30 | AF37: 0 | AG37: 0 | AH37: 0 | AI37: =(AF37*AG37*AH37)/1000 -> 0 | AJ37: =if(AI37>1,(AI37-1),0) -> 0 | AK37: =IF($D37,"🔒",) | AL37: {=H37*(1-I37)*VLOOKUP(AT37,{'▶️ Инструкция'!C:C,'▶️ Инструкция'!AI:AI},2,false)} -> #N/A | AM37: =IF($D37,"🔒",) | AN37: 0 | AO37: 0 | AP37: 0 | AQ37: 1 | AR37: 0 | AS37: 0 | AT37: ИП Иванов И.И. | AU37: WB | AV37: FBS | AW37: =AS37*H37 -> 0 | AX37: =(1/(AQ37))*H37*AS37 -> 0 | AY37: =AX37/BC37 -> #N/A | AZ37: 250 | BA37: =AZ37/H37 -> 0.25 | BB37: =H37-AW37 -> 1000 | BC37: =BX37 -> #N/A | BD37: =BC37*L37 -> #N/A | BE37: =H37*(1-I37)*L37 -> 0 | BF37: =IFERROR(BC37/BV37,) | BG37: =IFERROR(BC37/H37,) | BH37: =IFERROR(if(BW37>0,BC37/BW37,-BC37/BW37),) | BJ37: =IFERROR(__xludf.DUMMYFUNCTION("IF(AU37=data!A$5, IF(AV37=data!A$8, IF(T37=data!A$3, VLOOKUP(S37,filter('🔒 Доп. информация'!D:H,'🔒 Доп. информация'!C:C=T37),4,FALSE)+VLOOKUP(S37,filter('🔒 Доп. информация'!D:H,'🔒 Доп. информация'!C:C=T37),5,FALSE)*AJ37, IF(AND(MAX(AF37:AH37)<80,SUM(A"&"F37:AH37)<=160,AI37<20,XLOOKUP(M37,'📄 Комиссии'!C:C,'📄 Комиссии'!B:B)<>""Продукты""), VLOOKUP(S37,filter('🔒 Доп. информация'!D:H,'🔒 Доп. информация'!C:C=data!$A$3),4,FALSE)+VLOOKUP(S37,filter('🔒 Доп. информация'!D:H,'🔒 Доп. информация'!C:C=data!$A$3"&"),5,FALSE)*AJ37, VLOOKUP(S37,filter('🔒 Доп. информация'!D:H,'🔒 Доп. информация'!C:C=T37),4,FALSE)*ROUNDUP(AF37*AG37*AH37*L37/(120*80*175))/L37) ) *(AE37/2) ,) ,)*0"),0.0) -> 0 | BK37: =IFERROR(__xludf.DUMMYFUNCTION("IF(AU37=data!A$5, IF(AI37<=1,IF(AI37<=0.8,IF(AI37<=0.6,IF(AI37<=0.4,IF(AI37<=0.2,23,26),29),30),32)*VLOOKUP(S37,filter('🔒 Доп. информация'!D:E,'🔒 Доп. информация'!C:C=T37),2,FALSE)/'🔒 Доп. информация'!$K$9, IF(AV37=data!A$8,U37,1)*VLOOKUP(S37,filter('"&"🔒 Доп. информация'!D:E,'🔒 Доп. информация'!C:C=T37),2,FALSE)+ IF(AV37=data!A$8,U37,1)*VLOOKUP(S37,filter('🔒 Доп. информация'!D:F,'🔒 Доп. информация'!C:C=T37),3,FALSE)*AJ37) ,0)"),69.0) -> 69 | BL37: =IF($D37,"🔒",) | BM37: =IF($D37,"🔒",) | BN37: =VLOOKUP(T37,'🔒 Доп. информация'!J:P,7,false) -> 50 | BO37: =IF(AV37=data!A$9, (AA37+AO37+AP37+BJ37+BK37+BN37)+H37*AS37, (BJ37+BK37+BN37)+H37*AS37 ) -> 119 | BP37: =AA37+BJ37+BK37 -> 69 | BQ37: =H37*N37 -> 320 | BR37: =BP37+BQ37+AS37*H37+((1-AQ37)/AQ37)*BO37+AL37+H37*J37*1.1 -> #N/A | BS37: {=IF(VLOOKUP(AT37,{'▶️ Инструкция'!C:C,'▶️ Инструкция'!Y:Y},2,FALSE)=data!A$15, H37*(1-I37), (H37-BR37)) *VLOOKUP(AT37,{'▶️ Инструкция'!C:C,'▶️ Инструкция'!AD:AD},2,FALSE)/(1+VLOOKUP(AT37,{'▶️ Инструкция'!C:C,'▶️ Инструкция'!AD:AD},2,FALSE))} -> #N/A | BT37: {=IF(VLOOKUP(AT37,{'▶️ Инструкция'!C:C,'▶️ Инструкция'!Y:Y},2,FALSE)=data!A$15, H37*(1-I37)-BS37, (H37-BR37-BS37)) * VLOOKUP(AT37,{'▶️ Инструкция'!C:C,'▶️ Инструкция'!R:R},2,FALSE) +BS37} -> #N/A | BU37: =(G37*AR37)+if(AV37=data!A$9,AO37,AN37)+AP37+BR37+BT37 -> #N/A | BV37: =(G37*AR37)+if(AV37=data!A$9,AO37,AN37)+AP37+BT37+G37 -> #N/A | BW37: =H37-BR37 -> #N/A | BX37: =BW37-BV37 -> #N/A
A38: =if(D38=true,if(F38=data!A$1,data!A$10,data!A$11),) | B38: =AV38 -> FBS | C38: Название товара | D38: FALSE | E38: Имя | F38: {=IF(D38=TRUE,IF(IF(BG$3=VLOOKUP(AT38,{'▶️ Инструкция'!C:C,'▶️ Инструкция'!G:G},2,FALSE),BG38,BH38)>VLOOKUP(AT38,{'▶️ Инструкция'!C:C,'▶️ Инструкция'!N:N},2,FALSE),data!A$1,data!A$2),)} | G38: 0 | H38: 1000 | I38: 0 | J38: 0 | K38: =IF($D38,"🔒",) | L38: 0 | M38: Лопатки игрушечные | N38: =IFERROR(__xludf.DUMMYFUNCTION("ArrayFormula(let(category,VLOOKUP($M38, {'📄 Комиссии'!$C:$C , '📄 Комиссии'!$B:$B}, 2, 0), data,MATCH('🔒 Доп. информация'!$J$15:$J203,TRANSPOSE(SPLIT(INDEX('▶️ Инструкция'!$Q:$Q,MATCH($AT38,'▶️ Инструкция'!$R:$R,0)+2),"", "",FALSE)),0), options,COUNTA( "&"ifna( FILTER('🔒 Доп. информация'!$J$15:$J203,('🔒 Доп. информация'!$N$15:$N203=FALSE)*data*('🔒 Доп. информация'!$O$15:$O203=""Опция"")))), commission,VLOOKUP($M38,'📄 Комиссии'!$C:$E,IF($AV38=data!A$8,2,3),0), IF(NOT(ISBLANK($M38)),commission/100+ IFERR"&"OR(VLOOKUP($AT38,{'▶️ Инструкция'!$R:$R,'▶️ Инструкция'!$AK:$AK},2,0)+ IF((( category = ""Одежда"")+( category = ""Обувь"" ))*((options+SUM( ifna( FILTER('🔒 Доп. информация'!$M$15:$M203,('🔒 Доп. информация'!$N$15:$N203=FALSE)*data*('🔒 Доп. информация'!"&"$O$15:$O203=""Пакет"")))))>=5), -5% + 2%, IF((options>=1)* (COUNTA( ifna( FILTER('🔒 Доп. информация'!$J$15:$J203,('🔒 Доп. информация'!$N$15:$N203=FALSE)*data*('🔒 Доп. информация'!$O$15:$O203=""Пакет""))))>=1)* (commission>=14.5)* (category<> ""Одежда"&""")*( category <> ""Обувь"" ),-3% + 2%,0))))))"),0.32) -> 0.32 | O38: =IF($D38,"🔒",) | Q38: =IF($D38,"🔒",) | S38: Макс. из наших | T38: Короб | U38: 1 | V38: =IF($D38,"🔒",) | W38: =IF($D38,"🔒",) | X38: =IF($D38,"🔒",) | Y38: =IF($D38,"🔒",) | Z38: 0 | AA38: =1.7*(1+AJ38)*Z38 -> 0 | AB38: =IF($D38,"🔒",) | AC38: =IF($D38,"🔒",) | AD38: =IF($D38,"🔒",) | AE38: 30 | AF38: 0 | AG38: 0 | AH38: 0 | AI38: =(AF38*AG38*AH38)/1000 -> 0 | AJ38: =if(AI38>1,(AI38-1),0) -> 0 | AK38: =IF($D38,"🔒",) | AL38: {=H38*(1-I38)*VLOOKUP(AT38,{'▶️ Инструкция'!C:C,'▶️ Инструкция'!AI:AI},2,false)} -> #N/A | AM38: =IF($D38,"🔒",) | AN38: 0 | AO38: 0 | AP38: 0 | AQ38: 1 | AR38: 0 | AS38: 0 | AT38: ИП Иванов И.И. | AU38: WB | AV38: FBS | AW38: =AS38*H38 -> 0 | AX38: =(1/(AQ38))*H38*AS38 -> 0 | AY38: =AX38/BC38 -> #N/A | AZ38: 250 | BA38: =AZ38/H38 -> 0.25 | BB38: =H38-AW38 -> 1000 | BC38: =BX38 -> #N/A | BD38: =BC38*L38 -> #N/A | BE38: =H38*(1-I38)*L38 -> 0 | BF38: =IFERROR(BC38/BV38,) | BG38: =IFERROR(BC38/H38,) | BH38: =IFERROR(if(BW38>0,BC38/BW38,-BC38/BW38),) | BJ38: =IFERROR(__xludf.DUMMYFUNCTION("IF(AU38=data!A$5, IF(AV38=data!A$8, IF(T38=data!A$3, VLOOKUP(S38,filter('🔒 Доп. информация'!D:H,'🔒 Доп. информация'!C:C=T38),4,FALSE)+VLOOKUP(S38,filter('🔒 Доп. информация'!D:H,'🔒 Доп. информация'!C:C=T38),5,FALSE)*AJ38, IF(AND(MAX(AF38:AH38)<80,SUM(A"&"F38:AH38)<=160,AI38<20,XLOOKUP(M38,'📄 Комиссии'!C:C,'📄 Комиссии'!B:B)<>""Продукты""), VLOOKUP(S38,filter('🔒 Доп. информация'!D:H,'🔒 Доп. информация'!C:C=data!$A$3),4,FALSE)+VLOOKUP(S38,filter('🔒 Доп. информация'!D:H,'🔒 Доп. информация'!C:C=data!$A$3"&"),5,FALSE)*AJ38, VLOOKUP(S38,filter('🔒 Доп. информация'!D:H,'🔒 Доп. информация'!C:C=T38),4,FALSE)*ROUNDUP(AF38*AG38*AH38*L38/(120*80*175))/L38) ) *(AE38/2) ,) ,)*0"),0.0) -> 0 | BK38: =IFERROR(__xludf.DUMMYFUNCTION("IF(AU38=data!A$5, IF(AI38<=1,IF(AI38<=0.8,IF(AI38<=0.6,IF(AI38<=0.4,IF(AI38<=0.2,23,26),29),30),32)*VLOOKUP(S38,filter('🔒 Доп. информация'!D:E,'🔒 Доп. информация'!C:C=T38),2,FALSE)/'🔒 Доп. информация'!$K$9, IF(AV38=data!A$8,U38,1)*VLOOKUP(S38,filter('"&"🔒 Доп. информация'!D:E,'🔒 Доп. информация'!C:C=T38),2,FALSE)+ IF(AV38=data!A$8,U38,1)*VLOOKUP(S38,filter('🔒 Доп. информация'!D:F,'🔒 Доп. информация'!C:C=T38),3,FALSE)*AJ38) ,0)"),69.0) -> 69 | BL38: =IF($D38,"🔒",) | BM38: =IF($D38,"🔒",) | BN38: =VLOOKUP(T38,'🔒 Доп. информация'!J:P,7,false) -> 50 | BO38: =IF(AV38=data!A$9, (AA38+AO38+AP38+BJ38+BK38+BN38)+H38*AS38, (BJ38+BK38+BN38)+H38*AS38 ) -> 119 | BP38: =AA38+BJ38+BK38 -> 69 | BQ38: =H38*N38 -> 320 | BR38: =BP38+BQ38+AS38*H38+((1-AQ38)/AQ38)*BO38+AL38+H38*J38*1.1 -> #N/A | BS38: {=IF(VLOOKUP(AT38,{'▶️ Инструкция'!C:C,'▶️ Инструкция'!Y:Y},2,FALSE)=data!A$15, H38*(1-I38), (H38-BR38)) *VLOOKUP(AT38,{'▶️ Инструкция'!C:C,'▶️ Инструкция'!AD:AD},2,FALSE)/(1+VLOOKUP(AT38,{'▶️ Инструкция'!C:C,'▶️ Инструкция'!AD:AD},2,FALSE))} -> #N/A | BT38: {=IF(VLOOKUP(AT38,{'▶️ Инструкция'!C:C,'▶️ Инструкция'!Y:Y},2,FALSE)=data!A$15, H38*(1-I38)-BS38, (H38-BR38-BS38)) * VLOOKUP(AT38,{'▶️ Инструкция'!C:C,'▶️ Инструкция'!R:R},2,FALSE) +BS38} -> #N/A | BU38: =(G38*AR38)+if(AV38=data!A$9,AO38,AN38)+AP38+BR38+BT38 -> #N/A | BV38: =(G38*AR38)+if(AV38=data!A$9,AO38,AN38)+AP38+BT38+G38 -> #N/A | BW38: =H38-BR38 -> #N/A | BX38: =BW38-BV38 -> #N/A
A39: =if(D39=true,if(F39=data!A$1,data!A$10,data!A$11),) | B39: =AV39 -> FBS | C39: Название товара | D39: FALSE | E39: Имя | F39: {=IF(D39=TRUE,IF(IF(BG$3=VLOOKUP(AT39,{'▶️ Инструкция'!C:C,'▶️ Инструкция'!G:G},2,FALSE),BG39,BH39)>VLOOKUP(AT39,{'▶️ Инструкция'!C:C,'▶️ Инструкция'!N:N},2,FALSE),data!A$1,data!A$2),)} | G39: 0 | H39: 1000 | I39: 0 | J39: 0 | K39: =IF($D39,"🔒",) | L39: 0 | M39: Лопатки игрушечные | N39: =IFERROR(__xludf.DUMMYFUNCTION("ArrayFormula(let(category,VLOOKUP($M39, {'📄 Комиссии'!$C:$C , '📄 Комиссии'!$B:$B}, 2, 0), data,MATCH('🔒 Доп. информация'!$J$15:$J203,TRANSPOSE(SPLIT(INDEX('▶️ Инструкция'!$Q:$Q,MATCH($AT39,'▶️ Инструкция'!$R:$R,0)+2),"", "",FALSE)),0), options,COUNTA( "&"ifna( FILTER('🔒 Доп. информация'!$J$15:$J203,('🔒 Доп. информация'!$N$15:$N203=FALSE)*data*('🔒 Доп. информация'!$O$15:$O203=""Опция"")))), commission,VLOOKUP($M39,'📄 Комиссии'!$C:$E,IF($AV39=data!A$8,2,3),0), IF(NOT(ISBLANK($M39)),commission/100+ IFERR"&"OR(VLOOKUP($AT39,{'▶️ Инструкция'!$R:$R,'▶️ Инструкция'!$AK:$AK},2,0)+ IF((( category = ""Одежда"")+( category = ""Обувь"" ))*((options+SUM( ifna( FILTER('🔒 Доп. информация'!$M$15:$M203,('🔒 Доп. информация'!$N$15:$N203=FALSE)*data*('🔒 Доп. информация'!"&"$O$15:$O203=""Пакет"")))))>=5), -5% + 2%, IF((options>=1)* (COUNTA( ifna( FILTER('🔒 Доп. информация'!$J$15:$J203,('🔒 Доп. информация'!$N$15:$N203=FALSE)*data*('🔒 Доп. информация'!$O$15:$O203=""Пакет""))))>=1)* (commission>=14.5)* (category<> ""Одежда"&""")*( category <> ""Обувь"" ),-3% + 2%,0))))))"),0.32) -> 0.32 | O39: =IF($D39,"🔒",) | Q39: =IF($D39,"🔒",) | S39: Макс. из наших | T39: Короб | U39: 1 | V39: =IF($D39,"🔒",) | W39: =IF($D39,"🔒",) | X39: =IF($D39,"🔒",) | Y39: =IF($D39,"🔒",) | Z39: 0 | AA39: =1.7*(1+AJ39)*Z39 -> 0 | AB39: =IF($D39,"🔒",) | AC39: =IF($D39,"🔒",) | AD39: =IF($D39,"🔒",) | AE39: 30 | AF39: 0 | AG39: 0 | AH39: 0 | AI39: =(AF39*AG39*AH39)/1000 -> 0 | AJ39: =if(AI39>1,(AI39-1),0) -> 0 | AK39: =IF($D39,"🔒",) | AL39: {=H39*(1-I39)*VLOOKUP(AT39,{'▶️ Инструкция'!C:C,'▶️ Инструкция'!AI:AI},2,false)} -> #N/A | AM39: =IF($D39,"🔒",) | AN39: 0 | AO39: 0 | AP39: 0 | AQ39: 1 | AR39: 0 | AS39: 0 | AT39: ИП Иванов И.И. | AU39: WB | AV39: FBS | AW39: =AS39*H39 -> 0 | AX39: =(1/(AQ39))*H39*AS39 -> 0 | AY39: =AX39/BC39 -> #N/A | AZ39: 250 | BA39: =AZ39/H39 -> 0.25 | BB39: =H39-AW39 -> 1000 | BC39: =BX39 -> #N/A | BD39: =BC39*L39 -> #N/A | BE39: =H39*(1-I39)*L39 -> 0 | BF39: =IFERROR(BC39/BV39,) | BG39: =IFERROR(BC39/H39,) | BH39: =IFERROR(if(BW39>0,BC39/BW39,-BC39/BW39),) | BJ39: =IFERROR(__xludf.DUMMYFUNCTION("IF(AU39=data!A$5, IF(AV39=data!A$8, IF(T39=data!A$3, VLOOKUP(S39,filter('🔒 Доп. информация'!D:H,'🔒 Доп. информация'!C:C=T39),4,FALSE)+VLOOKUP(S39,filter('🔒 Доп. информация'!D:H,'🔒 Доп. информация'!C:C=T39),5,FALSE)*AJ39, IF(AND(MAX(AF39:AH39)<80,SUM(A"&"F39:AH39)<=160,AI39<20,XLOOKUP(M39,'📄 Комиссии'!C:C,'📄 Комиссии'!B:B)<>""Продукты""), VLOOKUP(S39,filter('🔒 Доп. информация'!D:H,'🔒 Доп. информация'!C:C=data!$A$3),4,FALSE)+VLOOKUP(S39,filter('🔒 Доп. информация'!D:H,'🔒 Доп. информация'!C:C=data!$A$3"&"),5,FALSE)*AJ39, VLOOKUP(S39,filter('🔒 Доп. информация'!D:H,'🔒 Доп. информация'!C:C=T39),4,FALSE)*ROUNDUP(AF39*AG39*AH39*L39/(120*80*175))/L39) ) *(AE39/2) ,) ,)*0"),0.0) -> 0 | BK39: =IFERROR(__xludf.DUMMYFUNCTION("IF(AU39=data!A$5, IF(AI39<=1,IF(AI39<=0.8,IF(AI39<=0.6,IF(AI39<=0.4,IF(AI39<=0.2,23,26),29),30),32)*VLOOKUP(S39,filter('🔒 Доп. информация'!D:E,'🔒 Доп. информация'!C:C=T39),2,FALSE)/'🔒 Доп. информация'!$K$9, IF(AV39=data!A$8,U39,1)*VLOOKUP(S39,filter('"&"🔒 Доп. информация'!D:E,'🔒 Доп. информация'!C:C=T39),2,FALSE)+ IF(AV39=data!A$8,U39,1)*VLOOKUP(S39,filter('🔒 Доп. информация'!D:F,'🔒 Доп. информация'!C:C=T39),3,FALSE)*AJ39) ,0)"),69.0) -> 69 | BL39: =IF($D39,"🔒",) | BM39: =IF($D39,"🔒",) | BN39: =VLOOKUP(T39,'🔒 Доп. информация'!J:P,7,false) -> 50 | BO39: =IF(AV39=data!A$9, (AA39+AO39+AP39+BJ39+BK39+BN39)+H39*AS39, (BJ39+BK39+BN39)+H39*AS39 ) -> 119 | BP39: =AA39+BJ39+BK39 -> 69 | BQ39: =H39*N39 -> 320 | BR39: =BP39+BQ39+AS39*H39+((1-AQ39)/AQ39)*BO39+AL39+H39*J39*1.1 -> #N/A | BS39: {=IF(VLOOKUP(AT39,{'▶️ Инструкция'!C:C,'▶️ Инструкция'!Y:Y},2,FALSE)=data!A$15, H39*(1-I39), (H39-BR39)) *VLOOKUP(AT39,{'▶️ Инструкция'!C:C,'▶️ Инструкция'!AD:AD},2,FALSE)/(1+VLOOKUP(AT39,{'▶️ Инструкция'!C:C,'▶️ Инструкция'!AD:AD},2,FALSE))} -> #N/A | BT39: {=IF(VLOOKUP(AT39,{'▶️ Инструкция'!C:C,'▶️ Инструкция'!Y:Y},2,FALSE)=data!A$15, H39*(1-I39)-BS39, (H39-BR39-BS39)) * VLOOKUP(AT39,{'▶️ Инструкция'!C:C,'▶️ Инструкция'!R:R},2,FALSE) +BS39} -> #N/A | BU39: =(G39*AR39)+if(AV39=data!A$9,AO39,AN39)+AP39+BR39+BT39 -> #N/A | BV39: =(G39*AR39)+if(AV39=data!A$9,AO39,AN39)+AP39+BT39+G39 -> #N/A | BW39: =H39-BR39 -> #N/A | BX39: =BW39-BV39 -> #N/A
A40: =if(D40=true,if(F40=data!A$1,data!A$10,data!A$11),) | B40: =AV40 -> FBS | C40: Название товара | D40: FALSE | E40: Имя | F40: {=IF(D40=TRUE,IF(IF(BG$3=VLOOKUP(AT40,{'▶️ Инструкция'!C:C,'▶️ Инструкция'!G:G},2,FALSE),BG40,BH40)>VLOOKUP(AT40,{'▶️ Инструкция'!C:C,'▶️ Инструкция'!N:N},2,FALSE),data!A$1,data!A$2),)} | G40: 0 | H40: 1000 | I40: 0 | J40: 0 | K40: =IF($D40,"🔒",) | L40: 0 | M40: Лопатки игрушечные | N40: =IFERROR(__xludf.DUMMYFUNCTION("ArrayFormula(let(category,VLOOKUP($M40, {'📄 Комиссии'!$C:$C , '📄 Комиссии'!$B:$B}, 2, 0), data,MATCH('🔒 Доп. информация'!$J$15:$J203,TRANSPOSE(SPLIT(INDEX('▶️ Инструкция'!$Q:$Q,MATCH($AT40,'▶️ Инструкция'!$R:$R,0)+2),"", "",FALSE)),0), options,COUNTA( "&"ifna( FILTER('🔒 Доп. информация'!$J$15:$J203,('🔒 Доп. информация'!$N$15:$N203=FALSE)*data*('🔒 Доп. информация'!$O$15:$O203=""Опция"")))), commission,VLOOKUP($M40,'📄 Комиссии'!$C:$E,IF($AV40=data!A$8,2,3),0), IF(NOT(ISBLANK($M40)),commission/100+ IFERR"&"OR(VLOOKUP($AT40,{'▶️ Инструкция'!$R:$R,'▶️ Инструкция'!$AK:$AK},2,0)+ IF((( category = ""Одежда"")+( category = ""Обувь"" ))*((options+SUM( ifna( FILTER('🔒 Доп. информация'!$M$15:$M203,('🔒 Доп. информация'!$N$15:$N203=FALSE)*data*('🔒 Доп. информация'!"&"$O$15:$O203=""Пакет"")))))>=5), -5% + 2%, IF((options>=1)* (COUNTA( ifna( FILTER('🔒 Доп. информация'!$J$15:$J203,('🔒 Доп. информация'!$N$15:$N203=FALSE)*data*('🔒 Доп. информация'!$O$15:$O203=""Пакет""))))>=1)* (commission>=14.5)* (category<> ""Одежда"&""")*( category <> ""Обувь"" ),-3% + 2%,0))))))"),0.32) -> 0.32 | O40: =IF($D40,"🔒",) | Q40: =IF($D40,"🔒",) | S40: Макс. из наших | T40: Короб | U40: 1 | V40: =IF($D40,"🔒",) | W40: =IF($D40,"🔒",) | X40: =IF($D40,"🔒",) | Y40: =IF($D40,"🔒",) | Z40: 0 | AA40: =1.7*(1+AJ40)*Z40 -> 0 | AB40: =IF($D40,"🔒",) | AC40: =IF($D40,"🔒",) | AD40: =IF($D40,"🔒",) | AE40: 30 | AF40: 0 | AG40: 0 | AH40: 0 | AI40: =(AF40*AG40*AH40)/1000 -> 0 | AJ40: =if(AI40>1,(AI40-1),0) -> 0 | AK40: =IF($D40,"🔒",) | AL40: {=H40*(1-I40)*VLOOKUP(AT40,{'▶️ Инструкция'!C:C,'▶️ Инструкция'!AI:AI},2,false)} -> #N/A | AM40: =IF($D40,"🔒",) | AN40: 0 | AO40: 0 | AP40: 0 | AQ40: 1 | AR40: 0 | AS40: 0 | AT40: ИП Иванов И.И. | AU40: WB | AV40: FBS | AW40: =AS40*H40 -> 0 | AX40: =(1/(AQ40))*H40*AS40 -> 0 | AY40: =AX40/BC40 -> #N/A | AZ40: 250 | BA40: =AZ40/H40 -> 0.25 | BB40: =H40-AW40 -> 1000 | BC40: =BX40 -> #N/A | BD40: =BC40*L40 -> #N/A | BE40: =H40*(1-I40)*L40 -> 0 | BF40: =IFERROR(BC40/BV40,) | BG40: =IFERROR(BC40/H40,) | BH40: =IFERROR(if(BW40>0,BC40/BW40,-BC40/BW40),) | BJ40: =IFERROR(__xludf.DUMMYFUNCTION("IF(AU40=data!A$5, IF(AV40=data!A$8, IF(T40=data!A$3, VLOOKUP(S40,filter('🔒 Доп. информация'!D:H,'🔒 Доп. информация'!C:C=T40),4,FALSE)+VLOOKUP(S40,filter('🔒 Доп. информация'!D:H,'🔒 Доп. информация'!C:C=T40),5,FALSE)*AJ40, IF(AND(MAX(AF40:AH40)<80,SUM(A"&"F40:AH40)<=160,AI40<20,XLOOKUP(M40,'📄 Комиссии'!C:C,'📄 Комиссии'!B:B)<>""Продукты""), VLOOKUP(S40,filter('🔒 Доп. информация'!D:H,'🔒 Доп. информация'!C:C=data!$A$3),4,FALSE)+VLOOKUP(S40,filter('🔒 Доп. информация'!D:H,'🔒 Доп. информация'!C:C=data!$A$3"&"),5,FALSE)*AJ40, VLOOKUP(S40,filter('🔒 Доп. информация'!D:H,'🔒 Доп. информация'!C:C=T40),4,FALSE)*ROUNDUP(AF40*AG40*AH40*L40/(120*80*175))/L40) ) *(AE40/2) ,) ,)*0"),0.0) -> 0 | BK40: =IFERROR(__xludf.DUMMYFUNCTION("IF(AU40=data!A$5, IF(AI40<=1,IF(AI40<=0.8,IF(AI40<=0.6,IF(AI40<=0.4,IF(AI40<=0.2,23,26),29),30),32)*VLOOKUP(S40,filter('🔒 Доп. информация'!D:E,'🔒 Доп. информация'!C:C=T40),2,FALSE)/'🔒 Доп. информация'!$K$9, IF(AV40=data!A$8,U40,1)*VLOOKUP(S40,filter('"&"🔒 Доп. информация'!D:E,'🔒 Доп. информация'!C:C=T40),2,FALSE)+ IF(AV40=data!A$8,U40,1)*VLOOKUP(S40,filter('🔒 Доп. информация'!D:F,'🔒 Доп. информация'!C:C=T40),3,FALSE)*AJ40) ,0)"),69.0) -> 69 | BL40: =IF($D40,"🔒",) | BM40: =IF($D40,"🔒",) | BN40: =VLOOKUP(T40,'🔒 Доп. информация'!J:P,7,false) -> 50 | BO40: =IF(AV40=data!A$9, (AA40+AO40+AP40+BJ40+BK40+BN40)+H40*AS40, (BJ40+BK40+BN40)+H40*AS40 ) -> 119 | BP40: =AA40+BJ40+BK40 -> 69 | BQ40: =H40*N40 -> 320 | BR40: =BP40+BQ40+AS40*H40+((1-AQ40)/AQ40)*BO40+AL40+H40*J40*1.1 -> #N/A | BS40: {=IF(VLOOKUP(AT40,{'▶️ Инструкция'!C:C,'▶️ Инструкция'!Y:Y},2,FALSE)=data!A$15, H40*(1-I40), (H40-BR40)) *VLOOKUP(AT40,{'▶️ Инструкция'!C:C,'▶️ Инструкция'!AD:AD},2,FALSE)/(1+VLOOKUP(AT40,{'▶️ Инструкция'!C:C,'▶️ Инструкция'!AD:AD},2,FALSE))} -> #N/A | BT40: {=IF(VLOOKUP(AT40,{'▶️ Инструкция'!C:C,'▶️ Инструкция'!Y:Y},2,FALSE)=data!A$15, H40*(1-I40)-BS40, (H40-BR40-BS40)) * VLOOKUP(AT40,{'▶️ Инструкция'!C:C,'▶️ Инструкция'!R:R},2,FALSE) +BS40} -> #N/A | BU40: =(G40*AR40)+if(AV40=data!A$9,AO40,AN40)+AP40+BR40+BT40 -> #N/A | BV40: =(G40*AR40)+if(AV40=data!A$9,AO40,AN40)+AP40+BT40+G40 -> #N/A | BW40: =H40-BR40 -> #N/A | BX40: =BW40-BV40 -> #N/A
A41: =if(D41=true,if(F41=data!A$1,data!A$10,data!A$11),) | B41: =AV41 -> FBS | C41: Название товара | D41: FALSE | E41: Имя | F41: {=IF(D41=TRUE,IF(IF(BG$3=VLOOKUP(AT41,{'▶️ Инструкция'!C:C,'▶️ Инструкция'!G:G},2,FALSE),BG41,BH41)>VLOOKUP(AT41,{'▶️ Инструкция'!C:C,'▶️ Инструкция'!N:N},2,FALSE),data!A$1,data!A$2),)} | G41: 0 | H41: 1000 | I41: 0 | J41: 0 | K41: =IF($D41,"🔒",) | L41: 0 | M41: Лопатки игрушечные | N41: =IFERROR(__xludf.DUMMYFUNCTION("ArrayFormula(let(category,VLOOKUP($M41, {'📄 Комиссии'!$C:$C , '📄 Комиссии'!$B:$B}, 2, 0), data,MATCH('🔒 Доп. информация'!$J$15:$J203,TRANSPOSE(SPLIT(INDEX('▶️ Инструкция'!$Q:$Q,MATCH($AT41,'▶️ Инструкция'!$R:$R,0)+2),"", "",FALSE)),0), options,COUNTA( "&"ifna( FILTER('🔒 Доп. информация'!$J$15:$J203,('🔒 Доп. информация'!$N$15:$N203=FALSE)*data*('🔒 Доп. информация'!$O$15:$O203=""Опция"")))), commission,VLOOKUP($M41,'📄 Комиссии'!$C:$E,IF($AV41=data!A$8,2,3),0), IF(NOT(ISBLANK($M41)),commission/100+ IFERR"&"OR(VLOOKUP($AT41,{'▶️ Инструкция'!$R:$R,'▶️ Инструкция'!$AK:$AK},2,0)+ IF((( category = ""Одежда"")+( category = ""Обувь"" ))*((options+SUM( ifna( FILTER('🔒 Доп. информация'!$M$15:$M203,('🔒 Доп. информация'!$N$15:$N203=FALSE)*data*('🔒 Доп. информация'!"&"$O$15:$O203=""Пакет"")))))>=5), -5% + 2%, IF((options>=1)* (COUNTA( ifna( FILTER('🔒 Доп. информация'!$J$15:$J203,('🔒 Доп. информация'!$N$15:$N203=FALSE)*data*('🔒 Доп. информация'!$O$15:$O203=""Пакет""))))>=1)* (commission>=14.5)* (category<> ""Одежда"&""")*( category <> ""Обувь"" ),-3% + 2%,0))))))"),0.32) -> 0.32 | O41: =IF($D41,"🔒",) | Q41: =IF($D41,"🔒",) | S41: Макс. из наших | T41: Короб | U41: 1 | V41: =IF($D41,"🔒",) | W41: =IF($D41,"🔒",) | X41: =IF($D41,"🔒",) | Y41: =IF($D41,"🔒",) | Z41: 0 | AA41: =1.7*(1+AJ41)*Z41 -> 0 | AB41: =IF($D41,"🔒",) | AC41: =IF($D41,"🔒",) | AD41: =IF($D41,"🔒",) | AE41: 30 | AF41: 0 | AG41: 0 | AH41: 0 | AI41: =(AF41*AG41*AH41)/1000 -> 0 | AJ41: =if(AI41>1,(AI41-1),0) -> 0 | AK41: =IF($D41,"🔒",) | AL41: {=H41*(1-I41)*VLOOKUP(AT41,{'▶️ Инструкция'!C:C,'▶️ Инструкция'!AI:AI},2,false)} -> #N/A | AM41: =IF($D41,"🔒",) | AN41: 0 | AO41: 0 | AP41: 0 | AQ41: 1 | AR41: 0 | AS41: 0 | AT41: ИП Иванов И.И. | AU41: WB | AV41: FBS | AW41: =AS41*H41 -> 0 | AX41: =(1/(AQ41))*H41*AS41 -> 0 | AY41: =AX41/BC41 -> #N/A | AZ41: 250 | BA41: =AZ41/H41 -> 0.25 | BB41: =H41-AW41 -> 1000 | BC41: =BX41 -> #N/A | BD41: =BC41*L41 -> #N/A | BE41: =H41*(1-I41)*L41 -> 0 | BF41: =IFERROR(BC41/BV41,) | BG41: =IFERROR(BC41/H41,) | BH41: =IFERROR(if(BW41>0,BC41/BW41,-BC41/BW41),) | BJ41: =IFERROR(__xludf.DUMMYFUNCTION("IF(AU41=data!A$5, IF(AV41=data!A$8, IF(T41=data!A$3, VLOOKUP(S41,filter('🔒 Доп. информация'!D:H,'🔒 Доп. информация'!C:C=T41),4,FALSE)+VLOOKUP(S41,filter('🔒 Доп. информация'!D:H,'🔒 Доп. информация'!C:C=T41),5,FALSE)*AJ41, IF(AND(MAX(AF41:AH41)<80,SUM(A"&"F41:AH41)<=160,AI41<20,XLOOKUP(M41,'📄 Комиссии'!C:C,'📄 Комиссии'!B:B)<>""Продукты""), VLOOKUP(S41,filter('🔒 Доп. информация'!D:H,'🔒 Доп. информация'!C:C=data!$A$3),4,FALSE)+VLOOKUP(S41,filter('🔒 Доп. информация'!D:H,'🔒 Доп. информация'!C:C=data!$A$3"&"),5,FALSE)*AJ41, VLOOKUP(S41,filter('🔒 Доп. информация'!D:H,'🔒 Доп. информация'!C:C=T41),4,FALSE)*ROUNDUP(AF41*AG41*AH41*L41/(120*80*175))/L41) ) *(AE41/2) ,) ,)*0"),0.0) -> 0 | BK41: =IFERROR(__xludf.DUMMYFUNCTION("IF(AU41=data!A$5, IF(AI41<=1,IF(AI41<=0.8,IF(AI41<=0.6,IF(AI41<=0.4,IF(AI41<=0.2,23,26),29),30),32)*VLOOKUP(S41,filter('🔒 Доп. информация'!D:E,'🔒 Доп. информация'!C:C=T41),2,FALSE)/'🔒 Доп. информация'!$K$9, IF(AV41=data!A$8,U41,1)*VLOOKUP(S41,filter('"&"🔒 Доп. информация'!D:E,'🔒 Доп. информация'!C:C=T41),2,FALSE)+ IF(AV41=data!A$8,U41,1)*VLOOKUP(S41,filter('🔒 Доп. информация'!D:F,'🔒 Доп. информация'!C:C=T41),3,FALSE)*AJ41) ,0)"),69.0) -> 69 | BL41: =IF($D41,"🔒",) | BM41: =IF($D41,"🔒",) | BN41: =VLOOKUP(T41,'🔒 Доп. информация'!J:P,7,false) -> 50 | BO41: =IF(AV41=data!A$9, (AA41+AO41+AP41+BJ41+BK41+BN41)+H41*AS41, (BJ41+BK41+BN41)+H41*AS41 ) -> 119 | BP41: =AA41+BJ41+BK41 -> 69 | BQ41: =H41*N41 -> 320 | BR41: =BP41+BQ41+AS41*H41+((1-AQ41)/AQ41)*BO41+AL41+H41*J41*1.1 -> #N/A | BS41: {=IF(VLOOKUP(AT41,{'▶️ Инструкция'!C:C,'▶️ Инструкция'!Y:Y},2,FALSE)=data!A$15, H41*(1-I41), (H41-BR41)) *VLOOKUP(AT41,{'▶️ Инструкция'!C:C,'▶️ Инструкция'!AD:AD},2,FALSE)/(1+VLOOKUP(AT41,{'▶️ Инструкция'!C:C,'▶️ Инструкция'!AD:AD},2,FALSE))} -> #N/A | BT41: {=IF(VLOOKUP(AT41,{'▶️ Инструкция'!C:C,'▶️ Инструкция'!Y:Y},2,FALSE)=data!A$15, H41*(1-I41)-BS41, (H41-BR41-BS41)) * VLOOKUP(AT41,{'▶️ Инструкция'!C:C,'▶️ Инструкция'!R:R},2,FALSE) +BS41} -> #N/A | BU41: =(G41*AR41)+if(AV41=data!A$9,AO41,AN41)+AP41+BR41+BT41 -> #N/A | BV41: =(G41*AR41)+if(AV41=data!A$9,AO41,AN41)+AP41+BT41+G41 -> #N/A | BW41: =H41-BR41 -> #N/A | BX41: =BW41-BV41 -> #N/A
A42: =if(D42=true,if(F42=data!A$1,data!A$10,data!A$11),) | B42: =AV42 -> FBS | C42: Название товара | D42: FALSE | E42: Имя | F42: {=IF(D42=TRUE,IF(IF(BG$3=VLOOKUP(AT42,{'▶️ Инструкция'!C:C,'▶️ Инструкция'!G:G},2,FALSE),BG42,BH42)>VLOOKUP(AT42,{'▶️ Инструкция'!C:C,'▶️ Инструкция'!N:N},2,FALSE),data!A$1,data!A$2),)} | G42: 0 | H42: 1000 | I42: 0 | J42: 0 | K42: =IF($D42,"🔒",) | L42: 0 | M42: Лопатки игрушечные | N42: =IFERROR(__xludf.DUMMYFUNCTION("ArrayFormula(let(category,VLOOKUP($M42, {'📄 Комиссии'!$C:$C , '📄 Комиссии'!$B:$B}, 2, 0), data,MATCH('🔒 Доп. информация'!$J$15:$J203,TRANSPOSE(SPLIT(INDEX('▶️ Инструкция'!$Q:$Q,MATCH($AT42,'▶️ Инструкция'!$R:$R,0)+2),"", "",FALSE)),0), options,COUNTA( "&"ifna( FILTER('🔒 Доп. информация'!$J$15:$J203,('🔒 Доп. информация'!$N$15:$N203=FALSE)*data*('🔒 Доп. информация'!$O$15:$O203=""Опция"")))), commission,VLOOKUP($M42,'📄 Комиссии'!$C:$E,IF($AV42=data!A$8,2,3),0), IF(NOT(ISBLANK($M42)),commission/100+ IFERR"&"OR(VLOOKUP($AT42,{'▶️ Инструкция'!$R:$R,'▶️ Инструкция'!$AK:$AK},2,0)+ IF((( category = ""Одежда"")+( category = ""Обувь"" ))*((options+SUM( ifna( FILTER('🔒 Доп. информация'!$M$15:$M203,('🔒 Доп. информация'!$N$15:$N203=FALSE)*data*('🔒 Доп. информация'!"&"$O$15:$O203=""Пакет"")))))>=5), -5% + 2%, IF((options>=1)* (COUNTA( ifna( FILTER('🔒 Доп. информация'!$J$15:$J203,('🔒 Доп. информация'!$N$15:$N203=FALSE)*data*('🔒 Доп. информация'!$O$15:$O203=""Пакет""))))>=1)* (commission>=14.5)* (category<> ""Одежда"&""")*( category <> ""Обувь"" ),-3% + 2%,0))))))"),0.32) -> 0.32 | O42: =IF($D42,"🔒",) | Q42: =IF($D42,"🔒",) | S42: Макс. из наших | T42: Короб | U42: 1 | V42: =IF($D42,"🔒",) | W42: =IF($D42,"🔒",) | X42: =IF($D42,"🔒",) | Y42: =IF($D42,"🔒",) | Z42: 0 | AA42: =1.7*(1+AJ42)*Z42 -> 0 | AB42: =IF($D42,"🔒",) | AC42: =IF($D42,"🔒",) | AD42: =IF($D42,"🔒",) | AE42: 30 | AF42: 0 | AG42: 0 | AH42: 0 | AI42: =(AF42*AG42*AH42)/1000 -> 0 | AJ42: =if(AI42>1,(AI42-1),0) -> 0 | AK42: =IF($D42,"🔒",) | AL42: {=H42*(1-I42)*VLOOKUP(AT42,{'▶️ Инструкция'!C:C,'▶️ Инструкция'!AI:AI},2,false)} -> #N/A | AM42: =IF($D42,"🔒",) | AN42: 0 | AO42: 0 | AP42: 0 | AQ42: 1 | AR42: 0 | AS42: 0 | AT42: ИП Иванов И.И. | AU42: WB | AV42: FBS | AW42: =AS42*H42 -> 0 | AX42: =(1/(AQ42))*H42*AS42 -> 0 | AY42: =AX42/BC42 -> #N/A | AZ42: 250 | BA42: =AZ42/H42 -> 0.25 | BB42: =H42-AW42 -> 1000 | BC42: =BX42 -> #N/A | BD42: =BC42*L42 -> #N/A | BE42: =H42*(1-I42)*L42 -> 0 | BF42: =IFERROR(BC42/BV42,) | BG42: =IFERROR(BC42/H42,) | BH42: =IFERROR(if(BW42>0,BC42/BW42,-BC42/BW42),) | BJ42: =IFERROR(__xludf.DUMMYFUNCTION("IF(AU42=data!A$5, IF(AV42=data!A$8, IF(T42=data!A$3, VLOOKUP(S42,filter('🔒 Доп. информация'!D:H,'🔒 Доп. информация'!C:C=T42),4,FALSE)+VLOOKUP(S42,filter('🔒 Доп. информация'!D:H,'🔒 Доп. информация'!C:C=T42),5,FALSE)*AJ42, IF(AND(MAX(AF42:AH42)<80,SUM(A"&"F42:AH42)<=160,AI42<20,XLOOKUP(M42,'📄 Комиссии'!C:C,'📄 Комиссии'!B:B)<>""Продукты""), VLOOKUP(S42,filter('🔒 Доп. информация'!D:H,'🔒 Доп. информация'!C:C=data!$A$3),4,FALSE)+VLOOKUP(S42,filter('🔒 Доп. информация'!D:H,'🔒 Доп. информация'!C:C=data!$A$3"&"),5,FALSE)*AJ42, VLOOKUP(S42,filter('🔒 Доп. информация'!D:H,'🔒 Доп. информация'!C:C=T42),4,FALSE)*ROUNDUP(AF42*AG42*AH42*L42/(120*80*175))/L42) ) *(AE42/2) ,) ,)*0"),0.0) -> 0 | BK42: =IFERROR(__xludf.DUMMYFUNCTION("IF(AU42=data!A$5, IF(AI42<=1,IF(AI42<=0.8,IF(AI42<=0.6,IF(AI42<=0.4,IF(AI42<=0.2,23,26),29),30),32)*VLOOKUP(S42,filter('🔒 Доп. информация'!D:E,'🔒 Доп. информация'!C:C=T42),2,FALSE)/'🔒 Доп. информация'!$K$9, IF(AV42=data!A$8,U42,1)*VLOOKUP(S42,filter('"&"🔒 Доп. информация'!D:E,'🔒 Доп. информация'!C:C=T42),2,FALSE)+ IF(AV42=data!A$8,U42,1)*VLOOKUP(S42,filter('🔒 Доп. информация'!D:F,'🔒 Доп. информация'!C:C=T42),3,FALSE)*AJ42) ,0)"),69.0) -> 69 | BL42: =IF($D42,"🔒",) | BM42: =IF($D42,"🔒",) | BN42: =VLOOKUP(T42,'🔒 Доп. информация'!J:P,7,false) -> 50 | BO42: =IF(AV42=data!A$9, (AA42+AO42+AP42+BJ42+BK42+BN42)+H42*AS42, (BJ42+BK42+BN42)+H42*AS42 ) -> 119 | BP42: =AA42+BJ42+BK42 -> 69 | BQ42: =H42*N42 -> 320 | BR42: =BP42+BQ42+AS42*H42+((1-AQ42)/AQ42)*BO42+AL42+H42*J42*1.1 -> #N/A | BS42: {=IF(VLOOKUP(AT42,{'▶️ Инструкция'!C:C,'▶️ Инструкция'!Y:Y},2,FALSE)=data!A$15, H42*(1-I42), (H42-BR42)) *VLOOKUP(AT42,{'▶️ Инструкция'!C:C,'▶️ Инструкция'!AD:AD},2,FALSE)/(1+VLOOKUP(AT42,{'▶️ Инструкция'!C:C,'▶️ Инструкция'!AD:AD},2,FALSE))} -> #N/A | BT42: {=IF(VLOOKUP(AT42,{'▶️ Инструкция'!C:C,'▶️ Инструкция'!Y:Y},2,FALSE)=data!A$15, H42*(1-I42)-BS42, (H42-BR42-BS42)) * VLOOKUP(AT42,{'▶️ Инструкция'!C:C,'▶️ Инструкция'!R:R},2,FALSE) +BS42} -> #N/A | BU42: =(G42*AR42)+if(AV42=data!A$9,AO42,AN42)+AP42+BR42+BT42 -> #N/A | BV42: =(G42*AR42)+if(AV42=data!A$9,AO42,AN42)+AP42+BT42+G42 -> #N/A | BW42: =H42-BR42 -> #N/A | BX42: =BW42-BV42 -> #N/A
A43: =if(D43=true,if(F43=data!A$1,data!A$10,data!A$11),) | B43: =AV43 -> FBS | C43: Название товара | D43: FALSE | E43: Имя | F43: {=IF(D43=TRUE,IF(IF(BG$3=VLOOKUP(AT43,{'▶️ Инструкция'!C:C,'▶️ Инструкция'!G:G},2,FALSE),BG43,BH43)>VLOOKUP(AT43,{'▶️ Инструкция'!C:C,'▶️ Инструкция'!N:N},2,FALSE),data!A$1,data!A$2),)} | G43: 0 | H43: 1000 | I43: 0 | J43: 0 | K43: =IF($D43,"🔒",) | L43: 0 | M43: Лопатки игрушечные | N43: =IFERROR(__xludf.DUMMYFUNCTION("ArrayFormula(let(category,VLOOKUP($M43, {'📄 Комиссии'!$C:$C , '📄 Комиссии'!$B:$B}, 2, 0), data,MATCH('🔒 Доп. информация'!$J$15:$J203,TRANSPOSE(SPLIT(INDEX('▶️ Инструкция'!$Q:$Q,MATCH($AT43,'▶️ Инструкция'!$R:$R,0)+2),"", "",FALSE)),0), options,COUNTA( "&"ifna( FILTER('🔒 Доп. информация'!$J$15:$J203,('🔒 Доп. информация'!$N$15:$N203=FALSE)*data*('🔒 Доп. информация'!$O$15:$O203=""Опция"")))), commission,VLOOKUP($M43,'📄 Комиссии'!$C:$E,IF($AV43=data!A$8,2,3),0), IF(NOT(ISBLANK($M43)),commission/100+ IFERR"&"OR(VLOOKUP($AT43,{'▶️ Инструкция'!$R:$R,'▶️ Инструкция'!$AK:$AK},2,0)+ IF((( category = ""Одежда"")+( category = ""Обувь"" ))*((options+SUM( ifna( FILTER('🔒 Доп. информация'!$M$15:$M203,('🔒 Доп. информация'!$N$15:$N203=FALSE)*data*('🔒 Доп. информация'!"&"$O$15:$O203=""Пакет"")))))>=5), -5% + 2%, IF((options>=1)* (COUNTA( ifna( FILTER('🔒 Доп. информация'!$J$15:$J203,('🔒 Доп. информация'!$N$15:$N203=FALSE)*data*('🔒 Доп. информация'!$O$15:$O203=""Пакет""))))>=1)* (commission>=14.5)* (category<> ""Одежда"&""")*( category <> ""Обувь"" ),-3% + 2%,0))))))"),0.32) -> 0.32 | O43: =IF($D43,"🔒",) | Q43: =IF($D43,"🔒",) | S43: Макс. из наших | T43: Короб | U43: 1 | V43: =IF($D43,"🔒",) | W43: =IF($D43,"🔒",) | X43: =IF($D43,"🔒",) | Y43: =IF($D43,"🔒",) | Z43: 0 | AA43: =1.7*(1+AJ43)*Z43 -> 0 | AB43: =IF($D43,"🔒",) | AC43: =IF($D43,"🔒",) | AD43: =IF($D43,"🔒",) | AE43: 30 | AF43: 0 | AG43: 0 | AH43: 0 | AI43: =(AF43*AG43*AH43)/1000 -> 0 | AJ43: =if(AI43>1,(AI43-1),0) -> 0 | AK43: =IF($D43,"🔒",) | AL43: {=H43*(1-I43)*VLOOKUP(AT43,{'▶️ Инструкция'!C:C,'▶️ Инструкция'!AI:AI},2,false)} -> #N/A | AM43: =IF($D43,"🔒",) | AN43: 0 | AO43: 0 | AP43: 0 | AQ43: 1 | AR43: 0 | AS43: 0 | AT43: ИП Иванов И.И. | AU43: WB | AV43: FBS | AW43: =AS43*H43 -> 0 | AX43: =(1/(AQ43))*H43*AS43 -> 0 | AY43: =AX43/BC43 -> #N/A | AZ43: 250 | BA43: =AZ43/H43 -> 0.25 | BB43: =H43-AW43 -> 1000 | BC43: =BX43 -> #N/A | BD43: =BC43*L43 -> #N/A | BE43: =H43*(1-I43)*L43 -> 0 | BF43: =IFERROR(BC43/BV43,) | BG43: =IFERROR(BC43/H43,) | BH43: =IFERROR(if(BW43>0,BC43/BW43,-BC43/BW43),) | BJ43: =IFERROR(__xludf.DUMMYFUNCTION("IF(AU43=data!A$5, IF(AV43=data!A$8, IF(T43=data!A$3, VLOOKUP(S43,filter('🔒 Доп. информация'!D:H,'🔒 Доп. информация'!C:C=T43),4,FALSE)+VLOOKUP(S43,filter('🔒 Доп. информация'!D:H,'🔒 Доп. информация'!C:C=T43),5,FALSE)*AJ43, IF(AND(MAX(AF43:AH43)<80,SUM(A"&"F43:AH43)<=160,AI43<20,XLOOKUP(M43,'📄 Комиссии'!C:C,'📄 Комиссии'!B:B)<>""Продукты""), VLOOKUP(S43,filter('🔒 Доп. информация'!D:H,'🔒 Доп. информация'!C:C=data!$A$3),4,FALSE)+VLOOKUP(S43,filter('🔒 Доп. информация'!D:H,'🔒 Доп. информация'!C:C=data!$A$3"&"),5,FALSE)*AJ43, VLOOKUP(S43,filter('🔒 Доп. информация'!D:H,'🔒 Доп. информация'!C:C=T43),4,FALSE)*ROUNDUP(AF43*AG43*AH43*L43/(120*80*175))/L43) ) *(AE43/2) ,) ,)*0"),0.0) -> 0 | BK43: =IFERROR(__xludf.DUMMYFUNCTION("IF(AU43=data!A$5, IF(AI43<=1,IF(AI43<=0.8,IF(AI43<=0.6,IF(AI43<=0.4,IF(AI43<=0.2,23,26),29),30),32)*VLOOKUP(S43,filter('🔒 Доп. информация'!D:E,'🔒 Доп. информация'!C:C=T43),2,FALSE)/'🔒 Доп. информация'!$K$9, IF(AV43=data!A$8,U43,1)*VLOOKUP(S43,filter('"&"🔒 Доп. информация'!D:E,'🔒 Доп. информация'!C:C=T43),2,FALSE)+ IF(AV43=data!A$8,U43,1)*VLOOKUP(S43,filter('🔒 Доп. информация'!D:F,'🔒 Доп. информация'!C:C=T43),3,FALSE)*AJ43) ,0)"),69.0) -> 69 | BL43: =IF($D43,"🔒",) | BM43: =IF($D43,"🔒",) | BN43: =VLOOKUP(T43,'🔒 Доп. информация'!J:P,7,false) -> 50 | BO43: =IF(AV43=data!A$9, (AA43+AO43+AP43+BJ43+BK43+BN43)+H43*AS43, (BJ43+BK43+BN43)+H43*AS43 ) -> 119 | BP43: =AA43+BJ43+BK43 -> 69 | BQ43: =H43*N43 -> 320 | BR43: =BP43+BQ43+AS43*H43+((1-AQ43)/AQ43)*BO43+AL43+H43*J43*1.1 -> #N/A | BS43: {=IF(VLOOKUP(AT43,{'▶️ Инструкция'!C:C,'▶️ Инструкция'!Y:Y},2,FALSE)=data!A$15, H43*(1-I43), (H43-BR43)) *VLOOKUP(AT43,{'▶️ Инструкция'!C:C,'▶️ Инструкция'!AD:AD},2,FALSE)/(1+VLOOKUP(AT43,{'▶️ Инструкция'!C:C,'▶️ Инструкция'!AD:AD},2,FALSE))} -> #N/A | BT43: {=IF(VLOOKUP(AT43,{'▶️ Инструкция'!C:C,'▶️ Инструкция'!Y:Y},2,FALSE)=data!A$15, H43*(1-I43)-BS43, (H43-BR43-BS43)) * VLOOKUP(AT43,{'▶️ Инструкция'!C:C,'▶️ Инструкция'!R:R},2,FALSE) +BS43} -> #N/A | BU43: =(G43*AR43)+if(AV43=data!A$9,AO43,AN43)+AP43+BR43+BT43 -> #N/A | BV43: =(G43*AR43)+if(AV43=data!A$9,AO43,AN43)+AP43+BT43+G43 -> #N/A | BW43: =H43-BR43 -> #N/A | BX43: =BW43-BV43 -> #N/A
A44: =if(D44=true,if(F44=data!A$1,data!A$10,data!A$11),) | B44: =AV44 -> FBS | C44: Название товара | D44: FALSE | E44: Имя | F44: {=IF(D44=TRUE,IF(IF(BG$3=VLOOKUP(AT44,{'▶️ Инструкция'!C:C,'▶️ Инструкция'!G:G},2,FALSE),BG44,BH44)>VLOOKUP(AT44,{'▶️ Инструкция'!C:C,'▶️ Инструкция'!N:N},2,FALSE),data!A$1,data!A$2),)} | G44: 0 | H44: 1000 | I44: 0 | J44: 0 | K44: =IF($D44,"🔒",) | L44: 0 | M44: Лопатки игрушечные | N44: =IFERROR(__xludf.DUMMYFUNCTION("ArrayFormula(let(category,VLOOKUP($M44, {'📄 Комиссии'!$C:$C , '📄 Комиссии'!$B:$B}, 2, 0), data,MATCH('🔒 Доп. информация'!$J$15:$J203,TRANSPOSE(SPLIT(INDEX('▶️ Инструкция'!$Q:$Q,MATCH($AT44,'▶️ Инструкция'!$R:$R,0)+2),"", "",FALSE)),0), options,COUNTA( "&"ifna( FILTER('🔒 Доп. информация'!$J$15:$J203,('🔒 Доп. информация'!$N$15:$N203=FALSE)*data*('🔒 Доп. информация'!$O$15:$O203=""Опция"")))), commission,VLOOKUP($M44,'📄 Комиссии'!$C:$E,IF($AV44=data!A$8,2,3),0), IF(NOT(ISBLANK($M44)),commission/100+ IFERR"&"OR(VLOOKUP($AT44,{'▶️ Инструкция'!$R:$R,'▶️ Инструкция'!$AK:$AK},2,0)+ IF((( category = ""Одежда"")+( category = ""Обувь"" ))*((options+SUM( ifna( FILTER('🔒 Доп. информация'!$M$15:$M203,('🔒 Доп. информация'!$N$15:$N203=FALSE)*data*('🔒 Доп. информация'!"&"$O$15:$O203=""Пакет"")))))>=5), -5% + 2%, IF((options>=1)* (COUNTA( ifna( FILTER('🔒 Доп. информация'!$J$15:$J203,('🔒 Доп. информация'!$N$15:$N203=FALSE)*data*('🔒 Доп. информация'!$O$15:$O203=""Пакет""))))>=1)* (commission>=14.5)* (category<> ""Одежда"&""")*( category <> ""Обувь"" ),-3% + 2%,0))))))"),0.32) -> 0.32 | O44: =IF($D44,"🔒",) | Q44: =IF($D44,"🔒",) | S44: Макс. из наших | T44: Короб | U44: 1 | V44: =IF($D44,"🔒",) | W44: =IF($D44,"🔒",) | X44: =IF($D44,"🔒",) | Y44: =IF($D44,"🔒",) | Z44: 0 | AA44: =1.7*(1+AJ44)*Z44 -> 0 | AB44: =IF($D44,"🔒",) | AC44: =IF($D44,"🔒",) | AD44: =IF($D44,"🔒",) | AE44: 30 | AF44: 0 | AG44: 0 | AH44: 0 | AI44: =(AF44*AG44*AH44)/1000 -> 0 | AJ44: =if(AI44>1,(AI44-1),0) -> 0 | AK44: =IF($D44,"🔒",) | AL44: {=H44*(1-I44)*VLOOKUP(AT44,{'▶️ Инструкция'!C:C,'▶️ Инструкция'!AI:AI},2,false)} -> #N/A | AM44: =IF($D44,"🔒",) | AN44: 0 | AO44: 0 | AP44: 0 | AQ44: 1 | AR44: 0 | AS44: 0 | AT44: ИП Иванов И.И. | AU44: WB | AV44: FBS | AW44: =AS44*H44 -> 0 | AX44: =(1/(AQ44))*H44*AS44 -> 0 | AY44: =AX44/BC44 -> #N/A | AZ44: 250 | BA44: =AZ44/H44 -> 0.25 | BB44: =H44-AW44 -> 1000 | BC44: =BX44 -> #N/A | BD44: =BC44*L44 -> #N/A | BE44: =H44*(1-I44)*L44 -> 0 | BF44: =IFERROR(BC44/BV44,) | BG44: =IFERROR(BC44/H44,) | BH44: =IFERROR(if(BW44>0,BC44/BW44,-BC44/BW44),) | BJ44: =IFERROR(__xludf.DUMMYFUNCTION("IF(AU44=data!A$5, IF(AV44=data!A$8, IF(T44=data!A$3, VLOOKUP(S44,filter('🔒 Доп. информация'!D:H,'🔒 Доп. информация'!C:C=T44),4,FALSE)+VLOOKUP(S44,filter('🔒 Доп. информация'!D:H,'🔒 Доп. информация'!C:C=T44),5,FALSE)*AJ44, IF(AND(MAX(AF44:AH44)<80,SUM(A"&"F44:AH44)<=160,AI44<20,XLOOKUP(M44,'📄 Комиссии'!C:C,'📄 Комиссии'!B:B)<>""Продукты""), VLOOKUP(S44,filter('🔒 Доп. информация'!D:H,'🔒 Доп. информация'!C:C=data!$A$3),4,FALSE)+VLOOKUP(S44,filter('🔒 Доп. информация'!D:H,'🔒 Доп. информация'!C:C=data!$A$3"&"),5,FALSE)*AJ44, VLOOKUP(S44,filter('🔒 Доп. информация'!D:H,'🔒 Доп. информация'!C:C=T44),4,FALSE)*ROUNDUP(AF44*AG44*AH44*L44/(120*80*175))/L44) ) *(AE44/2) ,) ,)*0"),0.0) -> 0 | BK44: =IFERROR(__xludf.DUMMYFUNCTION("IF(AU44=data!A$5, IF(AI44<=1,IF(AI44<=0.8,IF(AI44<=0.6,IF(AI44<=0.4,IF(AI44<=0.2,23,26),29),30),32)*VLOOKUP(S44,filter('🔒 Доп. информация'!D:E,'🔒 Доп. информация'!C:C=T44),2,FALSE)/'🔒 Доп. информация'!$K$9, IF(AV44=data!A$8,U44,1)*VLOOKUP(S44,filter('"&"🔒 Доп. информация'!D:E,'🔒 Доп. информация'!C:C=T44),2,FALSE)+ IF(AV44=data!A$8,U44,1)*VLOOKUP(S44,filter('🔒 Доп. информация'!D:F,'🔒 Доп. информация'!C:C=T44),3,FALSE)*AJ44) ,0)"),69.0) -> 69 | BL44: =IF($D44,"🔒",) | BM44: =IF($D44,"🔒",) | BN44: =VLOOKUP(T44,'🔒 Доп. информация'!J:P,7,false) -> 50 | BO44: =IF(AV44=data!A$9, (AA44+AO44+AP44+BJ44+BK44+BN44)+H44*AS44, (BJ44+BK44+BN44)+H44*AS44 ) -> 119 | BP44: =AA44+BJ44+BK44 -> 69 | BQ44: =H44*N44 -> 320 | BR44: =BP44+BQ44+AS44*H44+((1-AQ44)/AQ44)*BO44+AL44+H44*J44*1.1 -> #N/A | BS44: {=IF(VLOOKUP(AT44,{'▶️ Инструкция'!C:C,'▶️ Инструкция'!Y:Y},2,FALSE)=data!A$15, H44*(1-I44), (H44-BR44)) *VLOOKUP(AT44,{'▶️ Инструкция'!C:C,'▶️ Инструкция'!AD:AD},2,FALSE)/(1+VLOOKUP(AT44,{'▶️ Инструкция'!C:C,'▶️ Инструкция'!AD:AD},2,FALSE))} -> #N/A | BT44: {=IF(VLOOKUP(AT44,{'▶️ Инструкция'!C:C,'▶️ Инструкция'!Y:Y},2,FALSE)=data!A$15, H44*(1-I44)-BS44, (H44-BR44-BS44)) * VLOOKUP(AT44,{'▶️ Инструкция'!C:C,'▶️ Инструкция'!R:R},2,FALSE) +BS44} -> #N/A | BU44: =(G44*AR44)+if(AV44=data!A$9,AO44,AN44)+AP44+BR44+BT44 -> #N/A | BV44: =(G44*AR44)+if(AV44=data!A$9,AO44,AN44)+AP44+BT44+G44 -> #N/A | BW44: =H44-BR44 -> #N/A | BX44: =BW44-BV44 -> #N/A
